Workbook

Sheet Raw
A1: namespaces: | F1: "
B2: https://onerecord.iata.org/ns/cargo#
B3: https://onerecord.iata.org/ns/code-lists/
B4: http://www.w3.org/2001/XMLSchema# | F4: _ instead of : because of filenames :(
AP5: Core | AV5: Full
A6: SPARQL results: | L6: Normalized IRIs: | Q6: Property Type: | R6: syntax tables: | AF6: csv tables concat: | AG6: csv edges
A7: type | B7: element | C7: class | D7: property | E7: elementValue | F7: value | G7: cardinality | H7: inverse | I7: class_description_full | J7: property_description_full | K7: value_subclasses | L7: class | M7: property | N7: value | O7: inverse | P7: value_subclasses | Q7: type | R7: "table_schema" | S7: "table_name" | T7: "column_name" | U7: "schema_type" | V7: "data_type" | W7: "ordinal_position" | X7: "table_description" | Y7: "property_description" | Z7: "is_array" | AA7: "is_codelist" | AB7: "data_type_subclasses" | AC7: "class_IRI" | AD7: "property_IRI" | AE7: "value_IRI" | AF7: =IF(A7="Implicit","",R7&","&S7&","&T7&","&U7&","&V7&","&W7&","&X7&","&Y7&","&Z7&","&AA7&","&AB7&","&AC7&","&AD7&","&AE7) -> "table_schema","table_name","column_name","schema_type","data_type","ordinal_position","table_description","property_description","is_array","is_codelist","data_type_subclasses","class_IRI","property_IRI","value_IRI" | AG7: "source" | AH7: "sourceKey" | AI7: "target" | AJ7: "targetKey" | AK7: "relation" | AL7: "source","sourceKey","target","targetKey","relation" | AN7: Class | AO7: Link | AQ7: =AF7 -> "table_schema","table_name","column_name","schema_type","data_type","ordinal_position","table_description","property_description","is_array","is_codelist","data_type_subclasses","class_IRI","property_IRI","value_IRI" | AR7: =AL7 -> "source","sourceKey","target","targetKey","relation" | AT7: Class | AU7: Link | AV7: Link_Manual | AW7: =AF7 -> "table_schema","table_name","column_name","schema_type","data_type","ordinal_position","table_description","property_description","is_array","is_codelist","data_type_subclasses","class_IRI","property_IRI","value_IRI" | AX7: =AR7 -> "source","sourceKey","target","targetKey","relation" | AY7: =AX7 -> "source","sourceKey","target","targetKey","relation"
A8: Explicit | B8: Embedded | C8: https://onerecord.iata.org/ns/cargo#AccountNumber | D8: https://onerecord.iata.org/ns/cargo#accountNumberType | E8: Enum | F8: https://onerecord.iata.org/ns/cargo#AccountType | G8: 1 | J8: Type of the account of the account number | L8: =SUBSTITUTE(SUBSTITUTE(SUBSTITUTE(C8,$B$2,$A$2),$B$3,$A$3),$B$4,$A$4) -> AccountNumber | M8: =SUBSTITUTE(SUBSTITUTE(SUBSTITUTE(D8,$B$2,$A$2),$B$3,$A$3),$A$4,$B$4) -> accountNumberType | N8: =SUBSTITUTE(SUBSTITUTE(SUBSTITUTE(F8,$B$2,$A$2),$B$3,$A$3),$B$4,$A$4) -> AccountType | O8: =SUBSTITUTE(SUBSTITUTE(SUBSTITUTE(H8,$B$2,$A$2),$B$3,$A$3),$B$4,$A$4) | P8: =SUBSTITUTE(SUBSTITUTE(SUBSTITUTE(K8,$B$2,$A$2),$B$3,$A$3),$B$4,$A$4) | Q8: =IF(LEFT(N8,3)="xsd","Data","Object") -> Object | R8: =IF($A8="Implicit","",$F$1&B8&$F$1) -> "Embedded" | S8: =IF($A8="Implicit","",$F$1&L8&$F$1) -> "AccountNumber" | T8: =IF($A8="Implicit","",$F$1&M8&$F$1) -> "accountNumberType" | U8: =IF($A8="Implicit","",$F$1&E8&$F$1) -> "Enum" | V8: =IF($A8="Implicit","",$F$1&N8&$F$1) -> "AccountType" | W8: =IF($A8="Implicit","",COUNTIFS($C$8:C8,C8,$A$8:A8,"Explicit")) -> 1 | X8: =IF($A8="Implicit","",$F$1&SUBSTITUTE(IF(I8=0,"",I8),",",";")&$F$1) -> "" | Y8: =IF($A8="Implicit","",$F$1&SUBSTITUTE(IF(J8=0,"",J8),",",";")&$F$1) -> "Type of the account of the account number" | Z8: =IF($A8="Implicit","",$F$1&IF(G8=1,"false","true")&$F$1) -> "false" | AA8: =IF($A8="Implicit","",$F$1&IF(OR(E8="Enum",E8="CodeList"),"true","false")&$F$1) -> "true" | AB8: =IF($A8="Implicit","",$F$1&P8&$F$1) -> "" | AC8: =IF($A8="Implicit","",$F$1&C8&$F$1) -> "https://onerecord.iata.org/ns/cargo#AccountNumber" | AD8: =IF($A8="Implicit","",$F$1&D8&$F$1) -> "https://onerecord.iata.org/ns/cargo#accountNumberType" | AE8: =IF($A8="Implicit","",$F$1&F8&$F$1) -> "https://onerecord.iata.org/ns/cargo#AccountType" | AF8: =IF(A8="Implicit","",R8&","&S8&","&T8&","&U8&","&V8&","&W8&","&X8&","&Y8&","&Z8&","&AA8&","&AB8&","&AC8&","&AD8&","&AE8) -> "Embedded","AccountNumber","accountNumberType","Enum","AccountType",1,"","Type of the account of the account number","false","true","","https://onerecord.iata.org/ns/cargo#AccountNumber","https://onerecord.iata.org/ns/cargo#accountNumberType","https://onerecord.iata.org/ns/cargo#AccountType" | AG8: =IF(Q8="Data","",$F$1&B8&"."&L8&$F$1) -> "Embedded.AccountNumber" | AH8: =IF(Q8="Data","",$F$1&M8&$F$1) -> "accountNumberType" | AI8: =IF(Q8="Data","",$F$1&E8&"."&N8&$F$1) -> "Enum.AccountType" | AJ8: =IF(Q8="Data","",$F$1&O8&$F$1) -> "" | AK8: =IF(Q8="Data","",$F$1&IF(G8=1,"hasOne","hasMany")&$F$1) -> "hasOne" | AL8: =IF(Q8="Data","",AG8&","&AH8&","&AI8&","&AJ8&","&AK8) -> "Embedded.AccountNumber","accountNumberType","Enum.AccountType","","hasOne" | AN8: =COUNTIF(View_conceptual!G:G,L8) -> 0 | AO8: =COUNTIF(View_conceptual!H:H,L8)+COUNTIF(View_conceptual!I:I,N8) -> 0 | AQ8: =IF(AN8=1,AF8,"") | AR8: =IF(AO8=2,AL8,"") | AT8: =COUNTIF(View_full!G:G,L8) -> 0 | AU8: =COUNTIF(View_full!H:H,L8)+COUNTIF(View_full!I:I,N8) -> 0 | AV8: =COUNTIFS(Property_Manual!$A$2:$A$1206,Raw!L8,Property_Manual!$B$2:$B$1206,Raw!M8,Property_Manual!$C$2:$C$1206,Raw!N8,Property_Manual!$D$2:$D$1206,Raw!O8,Property_Manual!$F$2:$F$1206,"x") -> 0 | AW8: =IF(AT8=1,AF8,"") | AX8: =IF(AU8=2,AL8,"") | AY8: =IF(AV8=1,AL8,"")
A9: Implicit | B9: Embedded | C9: https://onerecord.iata.org/ns/cargo#AccountNumber | D9: https://onerecord.iata.org/ns/cargo#accountNumberType | E9: Enum | F9: https://onerecord.iata.org/ns/cargo#AccountType | G9: 1 | J9: Type of the account of the account number | L9: =SUBSTITUTE(SUBSTITUTE(SUBSTITUTE(C9,$B$2,$A$2),$B$3,$A$3),$B$4,$A$4) -> AccountNumber | M9: =SUBSTITUTE(SUBSTITUTE(SUBSTITUTE(D9,$B$2,$A$2),$B$3,$A$3),$A$4,$B$4) -> accountNumberType | N9: =SUBSTITUTE(SUBSTITUTE(SUBSTITUTE(F9,$B$2,$A$2),$B$3,$A$3),$B$4,$A$4) -> AccountType | O9: =SUBSTITUTE(SUBSTITUTE(SUBSTITUTE(H9,$B$2,$A$2),$B$3,$A$3),$B$4,$A$4) | P9: =SUBSTITUTE(SUBSTITUTE(SUBSTITUTE(K9,$B$2,$A$2),$B$3,$A$3),$B$4,$A$4) | Q9: =IF(LEFT(N9,3)="xsd","Data","Object") -> Object | R9: =IF($A9="Implicit","",$F$1&B9&$F$1) | S9: =IF($A9="Implicit","",$F$1&L9&$F$1) | T9: =IF($A9="Implicit","",$F$1&M9&$F$1) | U9: =IF($A9="Implicit","",$F$1&E9&$F$1) | V9: =IF($A9="Implicit","",$F$1&N9&$F$1) | W9: =IF($A9="Implicit","",COUNTIFS($C$8:C9,C9,$A$8:A9,"Explicit")) | X9: =IF($A9="Implicit","",$F$1&SUBSTITUTE(IF(I9=0,"",I9),",",";")&$F$1) | Y9: =IF($A9="Implicit","",$F$1&SUBSTITUTE(IF(J9=0,"",J9),",",";")&$F$1) | Z9: =IF($A9="Implicit","",$F$1&IF(G9=1,"false","true")&$F$1) | AA9: =IF($A9="Implicit","",$F$1&IF(OR(E9="Enum",E9="CodeList"),"true","false")&$F$1) | AB9: =IF($A9="Implicit","",$F$1&P9&$F$1) | AC9: =IF($A9="Implicit","",$F$1&C9&$F$1) | AD9: =IF($A9="Implicit","",$F$1&D9&$F$1) | AE9: =IF($A9="Implicit","",$F$1&F9&$F$1) | AF9: =IF(A9="Implicit","",R9&","&S9&","&T9&","&U9&","&V9&","&W9&","&X9&","&Y9&","&Z9&","&AA9&","&AB9&","&AC9&","&AD9&","&AE9) | AG9: =IF(Q9="Data","",$F$1&B9&"."&L9&$F$1) -> "Embedded.AccountNumber" | AH9: =IF(Q9="Data","",$F$1&M9&$F$1) -> "accountNumberType" | AI9: =IF(Q9="Data","",$F$1&E9&"."&N9&$F$1) -> "Enum.AccountType" | AJ9: =IF(Q9="Data","",$F$1&O9&$F$1) -> "" | AK9: =IF(Q9="Data","",$F$1&IF(G9=1,"hasOne","hasMany")&$F$1) -> "hasOne" | AL9: =IF(Q9="Data","",AG9&","&AH9&","&AI9&","&AJ9&","&AK9) -> "Embedded.AccountNumber","accountNumberType","Enum.AccountType","","hasOne" | AN9: =COUNTIF(View_conceptual!G:G,L9) -> 0 | AO9: =COUNTIF(View_conceptual!H:H,L9)+COUNTIF(View_conceptual!I:I,N9) -> 0 | AQ9: =IF(AN9=1,AF9,"") | AR9: =IF(AO9=2,AL9,"") | AT9: =COUNTIF(View_full!G:G,L9) -> 0 | AU9: =COUNTIF(View_full!H:H,L9)+COUNTIF(View_full!I:I,N9) -> 0 | AV9: =COUNTIFS(Property_Manual!$A$2:$A$1206,Raw!L9,Property_Manual!$B$2:$B$1206,Raw!M9,Property_Manual!$C$2:$C$1206,Raw!N9,Property_Manual!$D$2:$D$1206,Raw!O9,Property_Manual!$F$2:$F$1206,"x") -> 0 | AW9: =IF(AT9=1,AF9,"") | AX9: =IF(AU9=2,AL9,"") | AY9: =IF(AV9=1,AL9,"")
A10: Explicit | B10: Embedded | C10: https://onerecord.iata.org/ns/cargo#AccountNumber | D10: https://onerecord.iata.org/ns/cargo#textualValue | F10: http://www.w3.org/2001/XMLSchema#string | G10: 1 | J10: Textual value filled on use context (eg. characteristic colour, contactDetail mail address, etc.) | L10: =SUBSTITUTE(SUBSTITUTE(SUBSTITUTE(C10,$B$2,$A$2),$B$3,$A$3),$B$4,$A$4) -> AccountNumber | M10: =SUBSTITUTE(SUBSTITUTE(SUBSTITUTE(D10,$B$2,$A$2),$B$3,$A$3),$A$4,$B$4) -> textualValue | N10: =SUBSTITUTE(SUBSTITUTE(SUBSTITUTE(F10,$B$2,$A$2),$B$3,$A$3),$B$4,$A$4) -> string | O10: =SUBSTITUTE(SUBSTITUTE(SUBSTITUTE(H10,$B$2,$A$2),$B$3,$A$3),$B$4,$A$4) | P10: =SUBSTITUTE(SUBSTITUTE(SUBSTITUTE(K10,$B$2,$A$2),$B$3,$A$3),$B$4,$A$4) | Q10: =IF(LEFT(N10,3)="xsd","Data","Object") -> Object | R10: =IF($A10="Implicit","",$F$1&B10&$F$1) -> "Embedded" | S10: =IF($A10="Implicit","",$F$1&L10&$F$1) -> "AccountNumber" | T10: =IF($A10="Implicit","",$F$1&M10&$F$1) -> "textualValue" | U10: =IF($A10="Implicit","",$F$1&E10&$F$1) -> "" | V10: =IF($A10="Implicit","",$F$1&N10&$F$1) -> "string" | W10: =IF($A10="Implicit","",COUNTIFS($C$8:C10,C10,$A$8:A10,"Explicit")) -> 2 | X10: =IF($A10="Implicit","",$F$1&SUBSTITUTE(IF(I10=0,"",I10),",",";")&$F$1) -> "" | Y10: =IF($A10="Implicit","",$F$1&SUBSTITUTE(IF(J10=0,"",J10),",",";")&$F$1) -> "Textual value filled on use context (eg. characteristic colour; contactDetail mail address; etc.)" | Z10: =IF($A10="Implicit","",$F$1&IF(G10=1,"false","true")&$F$1) -> "false" | AA10: =IF($A10="Implicit","",$F$1&IF(OR(E10="Enum",E10="CodeList"),"true","false")&$F$1) -> "false" | AB10: =IF($A10="Implicit","",$F$1&P10&$F$1) -> "" | AC10: =IF($A10="Implicit","",$F$1&C10&$F$1) -> "https://onerecord.iata.org/ns/cargo#AccountNumber" | AD10: =IF($A10="Implicit","",$F$1&D10&$F$1) -> "https://onerecord.iata.org/ns/cargo#textualValue" | AE10: =IF($A10="Implicit","",$F$1&F10&$F$1) -> "http://www.w3.org/2001/XMLSchema#string" | AF10: =IF(A10="Implicit","",R10&","&S10&","&T10&","&U10&","&V10&","&W10&","&X10&","&Y10&","&Z10&","&AA10&","&AB10&","&AC10&","&AD10&","&AE10) -> "Embedded","AccountNumber","textualValue","","string",2,"","Textual value filled on use context (eg. characteristic colour; contactDetail mail address; etc.)","false","false","","https://onerecord.iata.org/ns/cargo#AccountNumber","https://onerecord.iata.org/ns/cargo#textualValue","http://www.w3.org/2001/XMLSchema#string" | AG10: =IF(Q10="Data","",$F$1&B10&"."&L10&$F$1) -> "Embedded.AccountNumber" | AH10: =IF(Q10="Data","",$F$1&M10&$F$1) -> "textualValue" | AI10: =IF(Q10="Data","",$F$1&E10&"."&N10&$F$1) -> ".string" | AJ10: =IF(Q10="Data","",$F$1&O10&$F$1) -> "" | AK10: =IF(Q10="Data","",$F$1&IF(G10=1,"hasOne","hasMany")&$F$1) -> "hasOne" | AL10: =IF(Q10="Data","",AG10&","&AH10&","&AI10&","&AJ10&","&AK10) -> "Embedded.AccountNumber","textualValue",".string","","hasOne" | AN10: =COUNTIF(View_conceptual!G:G,L10) -> 0 | AO10: =COUNTIF(View_conceptual!H:H,L10)+COUNTIF(View_conceptual!I:I,N10) -> 0 | AQ10: =IF(AN10=1,AF10,"") | AR10: =IF(AO10=2,AL10,"") | AT10: =COUNTIF(View_full!G:G,L10) -> 0 | AU10: =COUNTIF(View_full!H:H,L10)+COUNTIF(View_full!I:I,N10) -> 0 | AV10: =COUNTIFS(Property_Manual!$A$2:$A$1206,Raw!L10,Property_Manual!$B$2:$B$1206,Raw!M10,Property_Manual!$C$2:$C$1206,Raw!N10,Property_Manual!$D$2:$D$1206,Raw!O10,Property_Manual!$F$2:$F$1206,"x") -> 0 | AW10: =IF(AT10=1,AF10,"") | AX10: =IF(AU10=2,AL10,"") | AY10: =IF(AV10=1,AL10,"")
A11: Explicit | B11: Enum | C11: https://onerecord.iata.org/ns/cargo#AccountType | D11: https://onerecord.iata.org/ns/cargo#code | F11: http://www.w3.org/2001/XMLSchema#string | G11: 1 | I11: Open code list for Account types | J11: Code or short version of a code, for example "CH" for Switzerland when referring to the UN/LOCODE code list | L11: =SUBSTITUTE(SUBSTITUTE(SUBSTITUTE(C11,$B$2,$A$2),$B$3,$A$3),$B$4,$A$4) -> AccountType | M11: =SUBSTITUTE(SUBSTITUTE(SUBSTITUTE(D11,$B$2,$A$2),$B$3,$A$3),$A$4,$B$4) -> code | N11: =SUBSTITUTE(SUBSTITUTE(SUBSTITUTE(F11,$B$2,$A$2),$B$3,$A$3),$B$4,$A$4) -> string | O11: =SUBSTITUTE(SUBSTITUTE(SUBSTITUTE(H11,$B$2,$A$2),$B$3,$A$3),$B$4,$A$4) | P11: =SUBSTITUTE(SUBSTITUTE(SUBSTITUTE(K11,$B$2,$A$2),$B$3,$A$3),$B$4,$A$4) | Q11: =IF(LEFT(N11,3)="xsd","Data","Object") -> Object | R11: =IF($A11="Implicit","",$F$1&B11&$F$1) -> "Enum" | S11: =IF($A11="Implicit","",$F$1&L11&$F$1) -> "AccountType" | T11: =IF($A11="Implicit","",$F$1&M11&$F$1) -> "code" | U11: =IF($A11="Implicit","",$F$1&E11&$F$1) -> "" | V11: =IF($A11="Implicit","",$F$1&N11&$F$1) -> "string" | W11: =IF($A11="Implicit","",COUNTIFS($C$8:C11,C11,$A$8:A11,"Explicit")) -> 1 | X11: =IF($A11="Implicit","",$F$1&SUBSTITUTE(IF(I11=0,"",I11),",",";")&$F$1) -> "Open code list for Account types" | Y11: =IF($A11="Implicit","",$F$1&SUBSTITUTE(IF(J11=0,"",J11),",",";")&$F$1) -> "Code or short version of a code; for example "CH" for Switzerland when referring to the UN/LOCODE code list" | Z11: =IF($A11="Implicit","",$F$1&IF(G11=1,"false","true")&$F$1) -> "false" | AA11: =IF($A11="Implicit","",$F$1&IF(OR(E11="Enum",E11="CodeList"),"true","false")&$F$1) -> "false" | AB11: =IF($A11="Implicit","",$F$1&P11&$F$1) -> "" | AC11: =IF($A11="Implicit","",$F$1&C11&$F$1) -> "https://onerecord.iata.org/ns/cargo#AccountType" | AD11: =IF($A11="Implicit","",$F$1&D11&$F$1) -> "https://onerecord.iata.org/ns/cargo#code" | AE11: =IF($A11="Implicit","",$F$1&F11&$F$1) -> "http://www.w3.org/2001/XMLSchema#string" | AF11: =IF(A11="Implicit","",R11&","&S11&","&T11&","&U11&","&V11&","&W11&","&X11&","&Y11&","&Z11&","&AA11&","&AB11&","&AC11&","&AD11&","&AE11) -> "Enum","AccountType","code","","string",1,"Open code list for Account types","Code or short version of a code; for example "CH" for Switzerland when referring to the UN/LOCODE code list","false","false","","https://onerecord.iata.org/ns/cargo#AccountType","https://onerecord.iata.org/ns/cargo#code","http://www.w3.org/2001/XMLSchema#string" | AG11: =IF(Q11="Data","",$F$1&B11&"."&L11&$F$1) -> "Enum.AccountType" | AH11: =IF(Q11="Data","",$F$1&M11&$F$1) -> "code" | AI11: =IF(Q11="Data","",$F$1&E11&"."&N11&$F$1) -> ".string" | AJ11: =IF(Q11="Data","",$F$1&O11&$F$1) -> "" | AK11: =IF(Q11="Data","",$F$1&IF(G11=1,"hasOne","hasMany")&$F$1) -> "hasOne" | AL11: =IF(Q11="Data","",AG11&","&AH11&","&AI11&","&AJ11&","&AK11) -> "Enum.AccountType","code",".string","","hasOne" | AN11: =COUNTIF(View_conceptual!G:G,L11) -> 0 | AO11: =COUNTIF(View_conceptual!H:H,L11)+COUNTIF(View_conceptual!I:I,N11) -> 0 | AQ11: =IF(AN11=1,AF11,"") | AR11: =IF(AO11=2,AL11,"") | AT11: =COUNTIF(View_full!G:G,L11) -> 0 | AU11: =COUNTIF(View_full!H:H,L11)+COUNTIF(View_full!I:I,N11) -> 0 | AV11: =COUNTIFS(Property_Manual!$A$2:$A$1206,Raw!L11,Property_Manual!$B$2:$B$1206,Raw!M11,Property_Manual!$C$2:$C$1206,Raw!N11,Property_Manual!$D$2:$D$1206,Raw!O11,Property_Manual!$F$2:$F$1206,"x") -> 0 | AW11: =IF(AT11=1,AF11,"") | AX11: =IF(AU11=2,AL11,"") | AY11: =IF(AV11=1,AL11,"")
A12: Explicit | B12: Enum | C12: https://onerecord.iata.org/ns/cargo#AccountType | D12: https://onerecord.iata.org/ns/cargo#codeDescription | F12: http://www.w3.org/2001/XMLSchema#string | G12: 1 | I12: Open code list for Account types | J12: Description or long version of the code, for example "Switzerland" for Switzerland when referring to the UN/LOCODE code list | L12: =SUBSTITUTE(SUBSTITUTE(SUBSTITUTE(C12,$B$2,$A$2),$B$3,$A$3),$B$4,$A$4) -> AccountType | M12: =SUBSTITUTE(SUBSTITUTE(SUBSTITUTE(D12,$B$2,$A$2),$B$3,$A$3),$A$4,$B$4) -> codeDescription | N12: =SUBSTITUTE(SUBSTITUTE(SUBSTITUTE(F12,$B$2,$A$2),$B$3,$A$3),$B$4,$A$4) -> string | O12: =SUBSTITUTE(SUBSTITUTE(SUBSTITUTE(H12,$B$2,$A$2),$B$3,$A$3),$B$4,$A$4) | P12: =SUBSTITUTE(SUBSTITUTE(SUBSTITUTE(K12,$B$2,$A$2),$B$3,$A$3),$B$4,$A$4) | Q12: =IF(LEFT(N12,3)="xsd","Data","Object") -> Object | R12: =IF($A12="Implicit","",$F$1&B12&$F$1) -> "Enum" | S12: =IF($A12="Implicit","",$F$1&L12&$F$1) -> "AccountType" | T12: =IF($A12="Implicit","",$F$1&M12&$F$1) -> "codeDescription" | U12: =IF($A12="Implicit","",$F$1&E12&$F$1) -> "" | V12: =IF($A12="Implicit","",$F$1&N12&$F$1) -> "string" | W12: =IF($A12="Implicit","",COUNTIFS($C$8:C12,C12,$A$8:A12,"Explicit")) -> 2 | X12: =IF($A12="Implicit","",$F$1&SUBSTITUTE(IF(I12=0,"",I12),",",";")&$F$1) -> "Open code list for Account types" | Y12: =IF($A12="Implicit","",$F$1&SUBSTITUTE(IF(J12=0,"",J12),",",";")&$F$1) -> "Description or long version of the code; for example "Switzerland" for Switzerland when referring to the UN/LOCODE code list" | Z12: =IF($A12="Implicit","",$F$1&IF(G12=1,"false","true")&$F$1) -> "false" | AA12: =IF($A12="Implicit","",$F$1&IF(OR(E12="Enum",E12="CodeList"),"true","false")&$F$1) -> "false" | AB12: =IF($A12="Implicit","",$F$1&P12&$F$1) -> "" | AC12: =IF($A12="Implicit","",$F$1&C12&$F$1) -> "https://onerecord.iata.org/ns/cargo#AccountType" | AD12: =IF($A12="Implicit","",$F$1&D12&$F$1) -> "https://onerecord.iata.org/ns/cargo#codeDescription" | AE12: =IF($A12="Implicit","",$F$1&F12&$F$1) -> "http://www.w3.org/2001/XMLSchema#string" | AF12: =IF(A12="Implicit","",R12&","&S12&","&T12&","&U12&","&V12&","&W12&","&X12&","&Y12&","&Z12&","&AA12&","&AB12&","&AC12&","&AD12&","&AE12) -> "Enum","AccountType","codeDescription","","string",2,"Open code list for Account types","Description or long version of the code; for example "Switzerland" for Switzerland when referring to the UN/LOCODE code list","false","false","","https://onerecord.iata.org/ns/cargo#AccountType","https://onerecord.iata.org/ns/cargo#codeDescription","http://www.w3.org/2001/XMLSchema#string" | AG12: =IF(Q12="Data","",$F$1&B12&"."&L12&$F$1) -> "Enum.AccountType" | AH12: =IF(Q12="Data","",$F$1&M12&$F$1) -> "codeDescription" | AI12: =IF(Q12="Data","",$F$1&E12&"."&N12&$F$1) -> ".string" | AJ12: =IF(Q12="Data","",$F$1&O12&$F$1) -> "" | AK12: =IF(Q12="Data","",$F$1&IF(G12=1,"hasOne","hasMany")&$F$1) -> "hasOne" | AL12: =IF(Q12="Data","",AG12&","&AH12&","&AI12&","&AJ12&","&AK12) -> "Enum.AccountType","codeDescription",".string","","hasOne" | AN12: =COUNTIF(View_conceptual!G:G,L12) -> 0 | AO12: =COUNTIF(View_conceptual!H:H,L12)+COUNTIF(View_conceptual!I:I,N12) -> 0 | AQ12: =IF(AN12=1,AF12,"") | AR12: =IF(AO12=2,AL12,"") | AT12: =COUNTIF(View_full!G:G,L12) -> 0 | AU12: =COUNTIF(View_full!H:H,L12)+COUNTIF(View_full!I:I,N12) -> 0 | AV12: =COUNTIFS(Property_Manual!$A$2:$A$1206,Raw!L12,Property_Manual!$B$2:$B$1206,Raw!M12,Property_Manual!$C$2:$C$1206,Raw!N12,Property_Manual!$D$2:$D$1206,Raw!O12,Property_Manual!$F$2:$F$1206,"x") -> 0 | AW12: =IF(AT12=1,AF12,"") | AX12: =IF(AU12=2,AL12,"") | AY12: =IF(AV12=1,AL12,"")
A13: Explicit | B13: Enum | C13: https://onerecord.iata.org/ns/cargo#AccountType | D13: https://onerecord.iata.org/ns/cargo#codeLevel | F13: http://www.w3.org/2001/XMLSchema#integer | G13: 1 | I13: Open code list for Account types | J13: Integer indicating the level of a code if a codelists is hierarchical, for example HS-Codes | L13: =SUBSTITUTE(SUBSTITUTE(SUBSTITUTE(C13,$B$2,$A$2),$B$3,$A$3),$B$4,$A$4) -> AccountType | M13: =SUBSTITUTE(SUBSTITUTE(SUBSTITUTE(D13,$B$2,$A$2),$B$3,$A$3),$A$4,$B$4) -> codeLevel | N13: =SUBSTITUTE(SUBSTITUTE(SUBSTITUTE(F13,$B$2,$A$2),$B$3,$A$3),$B$4,$A$4) -> integer | O13: =SUBSTITUTE(SUBSTITUTE(SUBSTITUTE(H13,$B$2,$A$2),$B$3,$A$3),$B$4,$A$4) | P13: =SUBSTITUTE(SUBSTITUTE(SUBSTITUTE(K13,$B$2,$A$2),$B$3,$A$3),$B$4,$A$4) | Q13: =IF(LEFT(N13,3)="xsd","Data","Object") -> Object | R13: =IF($A13="Implicit","",$F$1&B13&$F$1) -> "Enum" | S13: =IF($A13="Implicit","",$F$1&L13&$F$1) -> "AccountType" | T13: =IF($A13="Implicit","",$F$1&M13&$F$1) -> "codeLevel" | U13: =IF($A13="Implicit","",$F$1&E13&$F$1) -> "" | V13: =IF($A13="Implicit","",$F$1&N13&$F$1) -> "integer" | W13: =IF($A13="Implicit","",COUNTIFS($C$8:C13,C13,$A$8:A13,"Explicit")) -> 3 | X13: =IF($A13="Implicit","",$F$1&SUBSTITUTE(IF(I13=0,"",I13),",",";")&$F$1) -> "Open code list for Account types" | Y13: =IF($A13="Implicit","",$F$1&SUBSTITUTE(IF(J13=0,"",J13),",",";")&$F$1) -> "Integer indicating the level of a code if a codelists is hierarchical; for example HS-Codes" | Z13: =IF($A13="Implicit","",$F$1&IF(G13=1,"false","true")&$F$1) -> "false" | AA13: =IF($A13="Implicit","",$F$1&IF(OR(E13="Enum",E13="CodeList"),"true","false")&$F$1) -> "false" | AB13: =IF($A13="Implicit","",$F$1&P13&$F$1) -> "" | AC13: =IF($A13="Implicit","",$F$1&C13&$F$1) -> "https://onerecord.iata.org/ns/cargo#AccountType" | AD13: =IF($A13="Implicit","",$F$1&D13&$F$1) -> "https://onerecord.iata.org/ns/cargo#codeLevel" | AE13: =IF($A13="Implicit","",$F$1&F13&$F$1) -> "http://www.w3.org/2001/XMLSchema#integer" | AF13: =IF(A13="Implicit","",R13&","&S13&","&T13&","&U13&","&V13&","&W13&","&X13&","&Y13&","&Z13&","&AA13&","&AB13&","&AC13&","&AD13&","&AE13) -> "Enum","AccountType","codeLevel","","integer",3,"Open code list for Account types","Integer indicating the level of a code if a codelists is hierarchical; for example HS-Codes","false","false","","https://onerecord.iata.org/ns/cargo#AccountType","https://onerecord.iata.org/ns/cargo#codeLevel","http://www.w3.org/2001/XMLSchema#integer" | AG13: =IF(Q13="Data","",$F$1&B13&"."&L13&$F$1) -> "Enum.AccountType" | AH13: =IF(Q13="Data","",$F$1&M13&$F$1) -> "codeLevel" | AI13: =IF(Q13="Data","",$F$1&E13&"."&N13&$F$1) -> ".integer" | AJ13: =IF(Q13="Data","",$F$1&O13&$F$1) -> "" | AK13: =IF(Q13="Data","",$F$1&IF(G13=1,"hasOne","hasMany")&$F$1) -> "hasOne" | AL13: =IF(Q13="Data","",AG13&","&AH13&","&AI13&","&AJ13&","&AK13) -> "Enum.AccountType","codeLevel",".integer","","hasOne" | AN13: =COUNTIF(View_conceptual!G:G,L13) -> 0 | AO13: =COUNTIF(View_conceptual!H:H,L13)+COUNTIF(View_conceptual!I:I,N13) -> 0 | AQ13: =IF(AN13=1,AF13,"") | AR13: =IF(AO13=2,AL13,"") | AT13: =COUNTIF(View_full!G:G,L13) -> 0 | AU13: =COUNTIF(View_full!H:H,L13)+COUNTIF(View_full!I:I,N13) -> 0 | AV13: =COUNTIFS(Property_Manual!$A$2:$A$1206,Raw!L13,Property_Manual!$B$2:$B$1206,Raw!M13,Property_Manual!$C$2:$C$1206,Raw!N13,Property_Manual!$D$2:$D$1206,Raw!O13,Property_Manual!$F$2:$F$1206,"x") -> 0 | AW13: =IF(AT13=1,AF13,"") | AX13: =IF(AU13=2,AL13,"") | AY13: =IF(AV13=1,AL13,"")
A14: Explicit | B14: Enum | C14: https://onerecord.iata.org/ns/cargo#AccountType | D14: https://onerecord.iata.org/ns/cargo#codeListName | F14: http://www.w3.org/2001/XMLSchema#string | G14: 1 | I14: Open code list for Account types | J14: Official name of the code list without version number when direct reference is not possible, for example "UN/LOCODE" when referring to the UN/LOCODE code list | L14: =SUBSTITUTE(SUBSTITUTE(SUBSTITUTE(C14,$B$2,$A$2),$B$3,$A$3),$B$4,$A$4) -> AccountType | M14: =SUBSTITUTE(SUBSTITUTE(SUBSTITUTE(D14,$B$2,$A$2),$B$3,$A$3),$A$4,$B$4) -> codeListName | N14: =SUBSTITUTE(SUBSTITUTE(SUBSTITUTE(F14,$B$2,$A$2),$B$3,$A$3),$B$4,$A$4) -> string | O14: =SUBSTITUTE(SUBSTITUTE(SUBSTITUTE(H14,$B$2,$A$2),$B$3,$A$3),$B$4,$A$4) | P14: =SUBSTITUTE(SUBSTITUTE(SUBSTITUTE(K14,$B$2,$A$2),$B$3,$A$3),$B$4,$A$4) | Q14: =IF(LEFT(N14,3)="xsd","Data","Object") -> Object | R14: =IF($A14="Implicit","",$F$1&B14&$F$1) -> "Enum" | S14: =IF($A14="Implicit","",$F$1&L14&$F$1) -> "AccountType" | T14: =IF($A14="Implicit","",$F$1&M14&$F$1) -> "codeListName" | U14: =IF($A14="Implicit","",$F$1&E14&$F$1) -> "" | V14: =IF($A14="Implicit","",$F$1&N14&$F$1) -> "string" | W14: =IF($A14="Implicit","",COUNTIFS($C$8:C14,C14,$A$8:A14,"Explicit")) -> 4 | X14: =IF($A14="Implicit","",$F$1&SUBSTITUTE(IF(I14=0,"",I14),",",";")&$F$1) -> "Open code list for Account types" | Y14: =IF($A14="Implicit","",$F$1&SUBSTITUTE(IF(J14=0,"",J14),",",";")&$F$1) -> "Official name of the code list without version number when direct reference is not possible; for example "UN/LOCODE" when referring to the UN/LOCODE code list" | Z14: =IF($A14="Implicit","",$F$1&IF(G14=1,"false","true")&$F$1) -> "false" | AA14: =IF($A14="Implicit","",$F$1&IF(OR(E14="Enum",E14="CodeList"),"true","false")&$F$1) -> "false" | AB14: =IF($A14="Implicit","",$F$1&P14&$F$1) -> "" | AC14: =IF($A14="Implicit","",$F$1&C14&$F$1) -> "https://onerecord.iata.org/ns/cargo#AccountType" | AD14: =IF($A14="Implicit","",$F$1&D14&$F$1) -> "https://onerecord.iata.org/ns/cargo#codeListName" | AE14: =IF($A14="Implicit","",$F$1&F14&$F$1) -> "http://www.w3.org/2001/XMLSchema#string" | AF14: =IF(A14="Implicit","",R14&","&S14&","&T14&","&U14&","&V14&","&W14&","&X14&","&Y14&","&Z14&","&AA14&","&AB14&","&AC14&","&AD14&","&AE14) -> "Enum","AccountType","codeListName","","string",4,"Open code list for Account types","Official name of the code list without version number when direct reference is not possible; for example "UN/LOCODE" when referring to the UN/LOCODE code list","false","false","","https://onerecord.iata.org/ns/cargo#AccountType","https://onerecord.iata.org/ns/cargo#codeListName","http://www.w3.org/2001/XMLSchema#string" | AG14: =IF(Q14="Data","",$F$1&B14&"."&L14&$F$1) -> "Enum.AccountType" | AH14: =IF(Q14="Data","",$F$1&M14&$F$1) -> "codeListName" | AI14: =IF(Q14="Data","",$F$1&E14&"."&N14&$F$1) -> ".string" | AJ14: =IF(Q14="Data","",$F$1&O14&$F$1) -> "" | AK14: =IF(Q14="Data","",$F$1&IF(G14=1,"hasOne","hasMany")&$F$1) -> "hasOne" | AL14: =IF(Q14="Data","",AG14&","&AH14&","&AI14&","&AJ14&","&AK14) -> "Enum.AccountType","codeListName",".string","","hasOne" | AN14: =COUNTIF(View_conceptual!G:G,L14) -> 0 | AO14: =COUNTIF(View_conceptual!H:H,L14)+COUNTIF(View_conceptual!I:I,N14) -> 0 | AQ14: =IF(AN14=1,AF14,"") | AR14: =IF(AO14=2,AL14,"") | AT14: =COUNTIF(View_full!G:G,L14) -> 0 | AU14: =COUNTIF(View_full!H:H,L14)+COUNTIF(View_full!I:I,N14) -> 0 | AV14: =COUNTIFS(Property_Manual!$A$2:$A$1206,Raw!L14,Property_Manual!$B$2:$B$1206,Raw!M14,Property_Manual!$C$2:$C$1206,Raw!N14,Property_Manual!$D$2:$D$1206,Raw!O14,Property_Manual!$F$2:$F$1206,"x") -> 0 | AW14: =IF(AT14=1,AF14,"") | AX14: =IF(AU14=2,AL14,"") | AY14: =IF(AV14=1,AL14,"")
A15: Explicit | B15: Enum | C15: https://onerecord.iata.org/ns/cargo#AccountType | D15: https://onerecord.iata.org/ns/cargo#codeListReference | F15: http://www.w3.org/2001/XMLSchema#string | G15: 1 | I15: Open code list for Account types | J15: URL to access the code list the code is taken from, for example "https://unece.org/trade/cefact/unlocode-code-list-country-and-territory" for UN/LOCODE. | L15: =SUBSTITUTE(SUBSTITUTE(SUBSTITUTE(C15,$B$2,$A$2),$B$3,$A$3),$B$4,$A$4) -> AccountType | M15: =SUBSTITUTE(SUBSTITUTE(SUBSTITUTE(D15,$B$2,$A$2),$B$3,$A$3),$A$4,$B$4) -> codeListReference | N15: =SUBSTITUTE(SUBSTITUTE(SUBSTITUTE(F15,$B$2,$A$2),$B$3,$A$3),$B$4,$A$4) -> string | O15: =SUBSTITUTE(SUBSTITUTE(SUBSTITUTE(H15,$B$2,$A$2),$B$3,$A$3),$B$4,$A$4) | P15: =SUBSTITUTE(SUBSTITUTE(SUBSTITUTE(K15,$B$2,$A$2),$B$3,$A$3),$B$4,$A$4) | Q15: =IF(LEFT(N15,3)="xsd","Data","Object") -> Object | R15: =IF($A15="Implicit","",$F$1&B15&$F$1) -> "Enum" | S15: =IF($A15="Implicit","",$F$1&L15&$F$1) -> "AccountType" | T15: =IF($A15="Implicit","",$F$1&M15&$F$1) -> "codeListReference" | U15: =IF($A15="Implicit","",$F$1&E15&$F$1) -> "" | V15: =IF($A15="Implicit","",$F$1&N15&$F$1) -> "string" | W15: =IF($A15="Implicit","",COUNTIFS($C$8:C15,C15,$A$8:A15,"Explicit")) -> 5 | X15: =IF($A15="Implicit","",$F$1&SUBSTITUTE(IF(I15=0,"",I15),",",";")&$F$1) -> "Open code list for Account types" | Y15: =IF($A15="Implicit","",$F$1&SUBSTITUTE(IF(J15=0,"",J15),",",";")&$F$1) -> "URL to access the code list the code is taken from; for example "https://unece.org/trade/cefact/unlocode-code-list-country-and-territory" for UN/LOCODE." | Z15: =IF($A15="Implicit","",$F$1&IF(G15=1,"false","true")&$F$1) -> "false" | AA15: =IF($A15="Implicit","",$F$1&IF(OR(E15="Enum",E15="CodeList"),"true","false")&$F$1) -> "false" | AB15: =IF($A15="Implicit","",$F$1&P15&$F$1) -> "" | AC15: =IF($A15="Implicit","",$F$1&C15&$F$1) -> "https://onerecord.iata.org/ns/cargo#AccountType" | AD15: =IF($A15="Implicit","",$F$1&D15&$F$1) -> "https://onerecord.iata.org/ns/cargo#codeListReference" | AE15: =IF($A15="Implicit","",$F$1&F15&$F$1) -> "http://www.w3.org/2001/XMLSchema#string" | AF15: =IF(A15="Implicit","",R15&","&S15&","&T15&","&U15&","&V15&","&W15&","&X15&","&Y15&","&Z15&","&AA15&","&AB15&","&AC15&","&AD15&","&AE15) -> "Enum","AccountType","codeListReference","","string",5,"Open code list for Account types","URL to access the code list the code is taken from; for example "https://unece.org/trade/cefact/unlocode-code-list-country-and-territory" for UN/LOCODE.","false","false","","https://onerecord.iata.org/ns/cargo#AccountType","https://onerecord.iata.org/ns/cargo#codeListReference","http://www.w3.org/2001/XMLSchema#string" | AG15: =IF(Q15="Data","",$F$1&B15&"."&L15&$F$1) -> "Enum.AccountType" | AH15: =IF(Q15="Data","",$F$1&M15&$F$1) -> "codeListReference" | AI15: =IF(Q15="Data","",$F$1&E15&"."&N15&$F$1) -> ".string" | AJ15: =IF(Q15="Data","",$F$1&O15&$F$1) -> "" | AK15: =IF(Q15="Data","",$F$1&IF(G15=1,"hasOne","hasMany")&$F$1) -> "hasOne" | AL15: =IF(Q15="Data","",AG15&","&AH15&","&AI15&","&AJ15&","&AK15) -> "Enum.AccountType","codeListReference",".string","","hasOne" | AN15: =COUNTIF(View_conceptual!G:G,L15) -> 0 | AO15: =COUNTIF(View_conceptual!H:H,L15)+COUNTIF(View_conceptual!I:I,N15) -> 0 | AQ15: =IF(AN15=1,AF15,"") | AR15: =IF(AO15=2,AL15,"") | AT15: =COUNTIF(View_full!G:G,L15) -> 0 | AU15: =COUNTIF(View_full!H:H,L15)+COUNTIF(View_full!I:I,N15) -> 0 | AV15: =COUNTIFS(Property_Manual!$A$2:$A$1206,Raw!L15,Property_Manual!$B$2:$B$1206,Raw!M15,Property_Manual!$C$2:$C$1206,Raw!N15,Property_Manual!$D$2:$D$1206,Raw!O15,Property_Manual!$F$2:$F$1206,"x") -> 0 | AW15: =IF(AT15=1,AF15,"") | AX15: =IF(AU15=2,AL15,"") | AY15: =IF(AV15=1,AL15,"")
A16: Explicit | B16: Enum | C16: https://onerecord.iata.org/ns/cargo#AccountType | D16: https://onerecord.iata.org/ns/cargo#codeListVersion | F16: http://www.w3.org/2001/XMLSchema#string | G16: 1 | I16: Open code list for Account types | J16: Version of the code list, for example "223-1" for UN/LOCODE. Used if the property codeListName is used or the version is not apparent from the resource referred to in property codeListReference. | L16: =SUBSTITUTE(SUBSTITUTE(SUBSTITUTE(C16,$B$2,$A$2),$B$3,$A$3),$B$4,$A$4) -> AccountType | M16: =SUBSTITUTE(SUBSTITUTE(SUBSTITUTE(D16,$B$2,$A$2),$B$3,$A$3),$A$4,$B$4) -> codeListVersion | N16: =SUBSTITUTE(SUBSTITUTE(SUBSTITUTE(F16,$B$2,$A$2),$B$3,$A$3),$B$4,$A$4) -> string | O16: =SUBSTITUTE(SUBSTITUTE(SUBSTITUTE(H16,$B$2,$A$2),$B$3,$A$3),$B$4,$A$4) | P16: =SUBSTITUTE(SUBSTITUTE(SUBSTITUTE(K16,$B$2,$A$2),$B$3,$A$3),$B$4,$A$4) | Q16: =IF(LEFT(N16,3)="xsd","Data","Object") -> Object | R16: =IF($A16="Implicit","",$F$1&B16&$F$1) -> "Enum" | S16: =IF($A16="Implicit","",$F$1&L16&$F$1) -> "AccountType" | T16: =IF($A16="Implicit","",$F$1&M16&$F$1) -> "codeListVersion" | U16: =IF($A16="Implicit","",$F$1&E16&$F$1) -> "" | V16: =IF($A16="Implicit","",$F$1&N16&$F$1) -> "string" | W16: =IF($A16="Implicit","",COUNTIFS($C$8:C16,C16,$A$8:A16,"Explicit")) -> 6 | X16: =IF($A16="Implicit","",$F$1&SUBSTITUTE(IF(I16=0,"",I16),",",";")&$F$1) -> "Open code list for Account types" | Y16: =IF($A16="Implicit","",$F$1&SUBSTITUTE(IF(J16=0,"",J16),",",";")&$F$1) -> "Version of the code list; for example "223-1" for UN/LOCODE. Used if the property codeListName is used or the version is not apparent from the resource referred to in property codeListReference." | Z16: =IF($A16="Implicit","",$F$1&IF(G16=1,"false","true")&$F$1) -> "false" | AA16: =IF($A16="Implicit","",$F$1&IF(OR(E16="Enum",E16="CodeList"),"true","false")&$F$1) -> "false" | AB16: =IF($A16="Implicit","",$F$1&P16&$F$1) -> "" | AC16: =IF($A16="Implicit","",$F$1&C16&$F$1) -> "https://onerecord.iata.org/ns/cargo#AccountType" | AD16: =IF($A16="Implicit","",$F$1&D16&$F$1) -> "https://onerecord.iata.org/ns/cargo#codeListVersion" | AE16: =IF($A16="Implicit","",$F$1&F16&$F$1) -> "http://www.w3.org/2001/XMLSchema#string" | AF16: =IF(A16="Implicit","",R16&","&S16&","&T16&","&U16&","&V16&","&W16&","&X16&","&Y16&","&Z16&","&AA16&","&AB16&","&AC16&","&AD16&","&AE16) -> "Enum","AccountType","codeListVersion","","string",6,"Open code list for Account types","Version of the code list; for example "223-1" for UN/LOCODE. Used if the property codeListName is used or the version is not apparent from the resource referred to in property codeListReference.","false","false","","https://onerecord.iata.org/ns/cargo#AccountType","https://onerecord.iata.org/ns/cargo#codeListVersion","http://www.w3.org/2001/XMLSchema#string" | AG16: =IF(Q16="Data","",$F$1&B16&"."&L16&$F$1) -> "Enum.AccountType" | AH16: =IF(Q16="Data","",$F$1&M16&$F$1) -> "codeListVersion" | AI16: =IF(Q16="Data","",$F$1&E16&"."&N16&$F$1) -> ".string" | AJ16: =IF(Q16="Data","",$F$1&O16&$F$1) -> "" | AK16: =IF(Q16="Data","",$F$1&IF(G16=1,"hasOne","hasMany")&$F$1) -> "hasOne" | AL16: =IF(Q16="Data","",AG16&","&AH16&","&AI16&","&AJ16&","&AK16) -> "Enum.AccountType","codeListVersion",".string","","hasOne" | AN16: =COUNTIF(View_conceptual!G:G,L16) -> 0 | AO16: =COUNTIF(View_conceptual!H:H,L16)+COUNTIF(View_conceptual!I:I,N16) -> 0 | AQ16: =IF(AN16=1,AF16,"") | AR16: =IF(AO16=2,AL16,"") | AT16: =COUNTIF(View_full!G:G,L16) -> 0 | AU16: =COUNTIF(View_full!H:H,L16)+COUNTIF(View_full!I:I,N16) -> 0 | AV16: =COUNTIFS(Property_Manual!$A$2:$A$1206,Raw!L16,Property_Manual!$B$2:$B$1206,Raw!M16,Property_Manual!$C$2:$C$1206,Raw!N16,Property_Manual!$D$2:$D$1206,Raw!O16,Property_Manual!$F$2:$F$1206,"x") -> 0 | AW16: =IF(AT16=1,AF16,"") | AX16: =IF(AU16=2,AL16,"") | AY16: =IF(AV16=1,AL16,"")
A17: Explicit | B17: Embedded | C17: https://onerecord.iata.org/ns/cargo#AccountingNote | D17: https://onerecord.iata.org/ns/cargo#accountingNoteIdentifier | F17: http://www.w3.org/2001/XMLSchema#string | G17: 1 | I17: Embedded object used for AWB mapping (box 10) | J17: String holding accounting information (AWB box 10) | L17: =SUBSTITUTE(SUBSTITUTE(SUBSTITUTE(C17,$B$2,$A$2),$B$3,$A$3),$B$4,$A$4) -> AccountingNote | M17: =SUBSTITUTE(SUBSTITUTE(SUBSTITUTE(D17,$B$2,$A$2),$B$3,$A$3),$A$4,$B$4) -> accountingNoteIdentifier | N17: =SUBSTITUTE(SUBSTITUTE(SUBSTITUTE(F17,$B$2,$A$2),$B$3,$A$3),$B$4,$A$4) -> string | O17: =SUBSTITUTE(SUBSTITUTE(SUBSTITUTE(H17,$B$2,$A$2),$B$3,$A$3),$B$4,$A$4) | P17: =SUBSTITUTE(SUBSTITUTE(SUBSTITUTE(K17,$B$2,$A$2),$B$3,$A$3),$B$4,$A$4) | Q17: =IF(LEFT(N17,3)="xsd","Data","Object") -> Object | R17: =IF($A17="Implicit","",$F$1&B17&$F$1) -> "Embedded" | S17: =IF($A17="Implicit","",$F$1&L17&$F$1) -> "AccountingNote" | T17: =IF($A17="Implicit","",$F$1&M17&$F$1) -> "accountingNoteIdentifier" | U17: =IF($A17="Implicit","",$F$1&E17&$F$1) -> "" | V17: =IF($A17="Implicit","",$F$1&N17&$F$1) -> "string" | W17: =IF($A17="Implicit","",COUNTIFS($C$8:C17,C17,$A$8:A17,"Explicit")) -> 1 | X17: =IF($A17="Implicit","",$F$1&SUBSTITUTE(IF(I17=0,"",I17),",",";")&$F$1) -> "Embedded object used for AWB mapping (box 10)" | Y17: =IF($A17="Implicit","",$F$1&SUBSTITUTE(IF(J17=0,"",J17),",",";")&$F$1) -> "String holding accounting information (AWB box 10)" | Z17: =IF($A17="Implicit","",$F$1&IF(G17=1,"false","true")&$F$1) -> "false" | AA17: =IF($A17="Implicit","",$F$1&IF(OR(E17="Enum",E17="CodeList"),"true","false")&$F$1) -> "false" | AB17: =IF($A17="Implicit","",$F$1&P17&$F$1) -> "" | AC17: =IF($A17="Implicit","",$F$1&C17&$F$1) -> "https://onerecord.iata.org/ns/cargo#AccountingNote" | AD17: =IF($A17="Implicit","",$F$1&D17&$F$1) -> "https://onerecord.iata.org/ns/cargo#accountingNoteIdentifier" | AE17: =IF($A17="Implicit","",$F$1&F17&$F$1) -> "http://www.w3.org/2001/XMLSchema#string" | AF17: =IF(A17="Implicit","",R17&","&S17&","&T17&","&U17&","&V17&","&W17&","&X17&","&Y17&","&Z17&","&AA17&","&AB17&","&AC17&","&AD17&","&AE17) -> "Embedded","AccountingNote","accountingNoteIdentifier","","string",1,"Embedded object used for AWB mapping (box 10)","String holding accounting information (AWB box 10)","false","false","","https://onerecord.iata.org/ns/cargo#AccountingNote","https://onerecord.iata.org/ns/cargo#accountingNoteIdentifier","http://www.w3.org/2001/XMLSchema#string" | AG17: =IF(Q17="Data","",$F$1&B17&"."&L17&$F$1) -> "Embedded.AccountingNote" | AH17: =IF(Q17="Data","",$F$1&M17&$F$1) -> "accountingNoteIdentifier" | AI17: =IF(Q17="Data","",$F$1&E17&"."&N17&$F$1) -> ".string" | AJ17: =IF(Q17="Data","",$F$1&O17&$F$1) -> "" | AK17: =IF(Q17="Data","",$F$1&IF(G17=1,"hasOne","hasMany")&$F$1) -> "hasOne" | AL17: =IF(Q17="Data","",AG17&","&AH17&","&AI17&","&AJ17&","&AK17) -> "Embedded.AccountingNote","accountingNoteIdentifier",".string","","hasOne" | AN17: =COUNTIF(View_conceptual!G:G,L17) -> 0 | AO17: =COUNTIF(View_conceptual!H:H,L17)+COUNTIF(View_conceptual!I:I,N17) -> 0 | AQ17: =IF(AN17=1,AF17,"") | AR17: =IF(AO17=2,AL17,"") | AT17: =COUNTIF(View_full!G:G,L17) -> 1 | AU17: =COUNTIF(View_full!H:H,L17)+COUNTIF(View_full!I:I,N17) -> 1 | AV17: =COUNTIFS(Property_Manual!$A$2:$A$1206,Raw!L17,Property_Manual!$B$2:$B$1206,Raw!M17,Property_Manual!$C$2:$C$1206,Raw!N17,Property_Manual!$D$2:$D$1206,Raw!O17,Property_Manual!$F$2:$F$1206,"x") -> 0 | AW17: =IF(AT17=1,AF17,"") -> "Embedded","AccountingNote","accountingNoteIdentifier","","string",1,"Embedded object used for AWB mapping (box 10)","String holding accounting information (AWB box 10)","false","false","","https://onerecord.iata.org/ns/cargo#AccountingNote","https://onerecord.iata.org/ns/cargo#accountingNoteIdentifier","http://www.w3.org/2001/XMLSchema#string" | AX17: =IF(AU17=2,AL17,"") | AY17: =IF(AV17=1,AL17,"")
A18: Explicit | B18: Embedded | C18: https://onerecord.iata.org/ns/cargo#AccountingNote | D18: https://onerecord.iata.org/ns/cargo#accountingNoteText | F18: http://www.w3.org/2001/XMLSchema#string | G18: 1 | I18: Embedded object used for AWB mapping (box 10) | J18: String holding the identifier in an accounting note (AWB box 10) | L18: =SUBSTITUTE(SUBSTITUTE(SUBSTITUTE(C18,$B$2,$A$2),$B$3,$A$3),$B$4,$A$4) -> AccountingNote | M18: =SUBSTITUTE(SUBSTITUTE(SUBSTITUTE(D18,$B$2,$A$2),$B$3,$A$3),$A$4,$B$4) -> accountingNoteText | N18: =SUBSTITUTE(SUBSTITUTE(SUBSTITUTE(F18,$B$2,$A$2),$B$3,$A$3),$B$4,$A$4) -> string | O18: =SUBSTITUTE(SUBSTITUTE(SUBSTITUTE(H18,$B$2,$A$2),$B$3,$A$3),$B$4,$A$4) | P18: =SUBSTITUTE(SUBSTITUTE(SUBSTITUTE(K18,$B$2,$A$2),$B$3,$A$3),$B$4,$A$4) | Q18: =IF(LEFT(N18,3)="xsd","Data","Object") -> Object | R18: =IF($A18="Implicit","",$F$1&B18&$F$1) -> "Embedded" | S18: =IF($A18="Implicit","",$F$1&L18&$F$1) -> "AccountingNote" | T18: =IF($A18="Implicit","",$F$1&M18&$F$1) -> "accountingNoteText" | U18: =IF($A18="Implicit","",$F$1&E18&$F$1) -> "" | V18: =IF($A18="Implicit","",$F$1&N18&$F$1) -> "string" | W18: =IF($A18="Implicit","",COUNTIFS($C$8:C18,C18,$A$8:A18,"Explicit")) -> 2 | X18: =IF($A18="Implicit","",$F$1&SUBSTITUTE(IF(I18=0,"",I18),",",";")&$F$1) -> "Embedded object used for AWB mapping (box 10)" | Y18: =IF($A18="Implicit","",$F$1&SUBSTITUTE(IF(J18=0,"",J18),",",";")&$F$1) -> "String holding the identifier in an accounting note (AWB box 10)" | Z18: =IF($A18="Implicit","",$F$1&IF(G18=1,"false","true")&$F$1) -> "false" | AA18: =IF($A18="Implicit","",$F$1&IF(OR(E18="Enum",E18="CodeList"),"true","false")&$F$1) -> "false" | AB18: =IF($A18="Implicit","",$F$1&P18&$F$1) -> "" | AC18: =IF($A18="Implicit","",$F$1&C18&$F$1) -> "https://onerecord.iata.org/ns/cargo#AccountingNote" | AD18: =IF($A18="Implicit","",$F$1&D18&$F$1) -> "https://onerecord.iata.org/ns/cargo#accountingNoteText" | AE18: =IF($A18="Implicit","",$F$1&F18&$F$1) -> "http://www.w3.org/2001/XMLSchema#string" | AF18: =IF(A18="Implicit","",R18&","&S18&","&T18&","&U18&","&V18&","&W18&","&X18&","&Y18&","&Z18&","&AA18&","&AB18&","&AC18&","&AD18&","&AE18) -> "Embedded","AccountingNote","accountingNoteText","","string",2,"Embedded object used for AWB mapping (box 10)","String holding the identifier in an accounting note (AWB box 10)","false","false","","https://onerecord.iata.org/ns/cargo#AccountingNote","https://onerecord.iata.org/ns/cargo#accountingNoteText","http://www.w3.org/2001/XMLSchema#string" | AG18: =IF(Q18="Data","",$F$1&B18&"."&L18&$F$1) -> "Embedded.AccountingNote" | AH18: =IF(Q18="Data","",$F$1&M18&$F$1) -> "accountingNoteText" | AI18: =IF(Q18="Data","",$F$1&E18&"."&N18&$F$1) -> ".string" | AJ18: =IF(Q18="Data","",$F$1&O18&$F$1) -> "" | AK18: =IF(Q18="Data","",$F$1&IF(G18=1,"hasOne","hasMany")&$F$1) -> "hasOne" | AL18: =IF(Q18="Data","",AG18&","&AH18&","&AI18&","&AJ18&","&AK18) -> "Embedded.AccountingNote","accountingNoteText",".string","","hasOne" | AN18: =COUNTIF(View_conceptual!G:G,L18) -> 0 | AO18: =COUNTIF(View_conceptual!H:H,L18)+COUNTIF(View_conceptual!I:I,N18) -> 0 | AQ18: =IF(AN18=1,AF18,"") | AR18: =IF(AO18=2,AL18,"") | AT18: =COUNTIF(View_full!G:G,L18) -> 1 | AU18: =COUNTIF(View_full!H:H,L18)+COUNTIF(View_full!I:I,N18) -> 1 | AV18: =COUNTIFS(Property_Manual!$A$2:$A$1206,Raw!L18,Property_Manual!$B$2:$B$1206,Raw!M18,Property_Manual!$C$2:$C$1206,Raw!N18,Property_Manual!$D$2:$D$1206,Raw!O18,Property_Manual!$F$2:$F$1206,"x") -> 0 | AW18: =IF(AT18=1,AF18,"") -> "Embedded","AccountingNote","accountingNoteText","","string",2,"Embedded object used for AWB mapping (box 10)","String holding the identifier in an accounting note (AWB box 10)","false","false","","https://onerecord.iata.org/ns/cargo#AccountingNote","https://onerecord.iata.org/ns/cargo#accountingNoteText","http://www.w3.org/2001/XMLSchema#string" | AX18: =IF(AU18=2,AL18,"") | AY18: =IF(AV18=1,AL18,"")
A19: Explicit | B19: Enum | C19: https://onerecord.iata.org/ns/cargo#ActionTimeType | D19: https://onerecord.iata.org/ns/cargo#code | F19: http://www.w3.org/2001/XMLSchema#string | G19: 1 | I19: Restricted code list for acceptable action times | J19: Code or short version of a code, for example "CH" for Switzerland when referring to the UN/LOCODE code list | L19: =SUBSTITUTE(SUBSTITUTE(SUBSTITUTE(C19,$B$2,$A$2),$B$3,$A$3),$B$4,$A$4) -> ActionTimeType | M19: =SUBSTITUTE(SUBSTITUTE(SUBSTITUTE(D19,$B$2,$A$2),$B$3,$A$3),$A$4,$B$4) -> code | N19: =SUBSTITUTE(SUBSTITUTE(SUBSTITUTE(F19,$B$2,$A$2),$B$3,$A$3),$B$4,$A$4) -> string | O19: =SUBSTITUTE(SUBSTITUTE(SUBSTITUTE(H19,$B$2,$A$2),$B$3,$A$3),$B$4,$A$4) | P19: =SUBSTITUTE(SUBSTITUTE(SUBSTITUTE(K19,$B$2,$A$2),$B$3,$A$3),$B$4,$A$4) | Q19: =IF(LEFT(N19,3)="xsd","Data","Object") -> Object | R19: =IF($A19="Implicit","",$F$1&B19&$F$1) -> "Enum" | S19: =IF($A19="Implicit","",$F$1&L19&$F$1) -> "ActionTimeType" | T19: =IF($A19="Implicit","",$F$1&M19&$F$1) -> "code" | U19: =IF($A19="Implicit","",$F$1&E19&$F$1) -> "" | V19: =IF($A19="Implicit","",$F$1&N19&$F$1) -> "string" | W19: =IF($A19="Implicit","",COUNTIFS($C$8:C19,C19,$A$8:A19,"Explicit")) -> 1 | X19: =IF($A19="Implicit","",$F$1&SUBSTITUTE(IF(I19=0,"",I19),",",";")&$F$1) -> "Restricted code list for acceptable action times" | Y19: =IF($A19="Implicit","",$F$1&SUBSTITUTE(IF(J19=0,"",J19),",",";")&$F$1) -> "Code or short version of a code; for example "CH" for Switzerland when referring to the UN/LOCODE code list" | Z19: =IF($A19="Implicit","",$F$1&IF(G19=1,"false","true")&$F$1) -> "false" | AA19: =IF($A19="Implicit","",$F$1&IF(OR(E19="Enum",E19="CodeList"),"true","false")&$F$1) -> "false" | AB19: =IF($A19="Implicit","",$F$1&P19&$F$1) -> "" | AC19: =IF($A19="Implicit","",$F$1&C19&$F$1) -> "https://onerecord.iata.org/ns/cargo#ActionTimeType" | AD19: =IF($A19="Implicit","",$F$1&D19&$F$1) -> "https://onerecord.iata.org/ns/cargo#code" | AE19: =IF($A19="Implicit","",$F$1&F19&$F$1) -> "http://www.w3.org/2001/XMLSchema#string" | AF19: =IF(A19="Implicit","",R19&","&S19&","&T19&","&U19&","&V19&","&W19&","&X19&","&Y19&","&Z19&","&AA19&","&AB19&","&AC19&","&AD19&","&AE19) -> "Enum","ActionTimeType","code","","string",1,"Restricted code list for acceptable action times","Code or short version of a code; for example "CH" for Switzerland when referring to the UN/LOCODE code list","false","false","","https://onerecord.iata.org/ns/cargo#ActionTimeType","https://onerecord.iata.org/ns/cargo#code","http://www.w3.org/2001/XMLSchema#string" | AG19: =IF(Q19="Data","",$F$1&B19&"."&L19&$F$1) -> "Enum.ActionTimeType" | AH19: =IF(Q19="Data","",$F$1&M19&$F$1) -> "code" | AI19: =IF(Q19="Data","",$F$1&E19&"."&N19&$F$1) -> ".string" | AJ19: =IF(Q19="Data","",$F$1&O19&$F$1) -> "" | AK19: =IF(Q19="Data","",$F$1&IF(G19=1,"hasOne","hasMany")&$F$1) -> "hasOne" | AL19: =IF(Q19="Data","",AG19&","&AH19&","&AI19&","&AJ19&","&AK19) -> "Enum.ActionTimeType","code",".string","","hasOne" | AN19: =COUNTIF(View_conceptual!G:G,L19) -> 0 | AO19: =COUNTIF(View_conceptual!H:H,L19)+COUNTIF(View_conceptual!I:I,N19) -> 0 | AQ19: =IF(AN19=1,AF19,"") | AR19: =IF(AO19=2,AL19,"") | AT19: =COUNTIF(View_full!G:G,L19) -> 0 | AU19: =COUNTIF(View_full!H:H,L19)+COUNTIF(View_full!I:I,N19) -> 0 | AV19: =COUNTIFS(Property_Manual!$A$2:$A$1206,Raw!L19,Property_Manual!$B$2:$B$1206,Raw!M19,Property_Manual!$C$2:$C$1206,Raw!N19,Property_Manual!$D$2:$D$1206,Raw!O19,Property_Manual!$F$2:$F$1206,"x") -> 0 | AW19: =IF(AT19=1,AF19,"") | AX19: =IF(AU19=2,AL19,"") | AY19: =IF(AV19=1,AL19,"")
A20: Explicit | B20: Enum | C20: https://onerecord.iata.org/ns/cargo#ActionTimeType | D20: https://onerecord.iata.org/ns/cargo#codeDescription | F20: http://www.w3.org/2001/XMLSchema#string | G20: 1 | I20: Restricted code list for acceptable action times | J20: Description or long version of the code, for example "Switzerland" for Switzerland when referring to the UN/LOCODE code list | L20: =SUBSTITUTE(SUBSTITUTE(SUBSTITUTE(C20,$B$2,$A$2),$B$3,$A$3),$B$4,$A$4) -> ActionTimeType | M20: =SUBSTITUTE(SUBSTITUTE(SUBSTITUTE(D20,$B$2,$A$2),$B$3,$A$3),$A$4,$B$4) -> codeDescription | N20: =SUBSTITUTE(SUBSTITUTE(SUBSTITUTE(F20,$B$2,$A$2),$B$3,$A$3),$B$4,$A$4) -> string | O20: =SUBSTITUTE(SUBSTITUTE(SUBSTITUTE(H20,$B$2,$A$2),$B$3,$A$3),$B$4,$A$4) | P20: =SUBSTITUTE(SUBSTITUTE(SUBSTITUTE(K20,$B$2,$A$2),$B$3,$A$3),$B$4,$A$4) | Q20: =IF(LEFT(N20,3)="xsd","Data","Object") -> Object | R20: =IF($A20="Implicit","",$F$1&B20&$F$1) -> "Enum" | S20: =IF($A20="Implicit","",$F$1&L20&$F$1) -> "ActionTimeType" | T20: =IF($A20="Implicit","",$F$1&M20&$F$1) -> "codeDescription" | U20: =IF($A20="Implicit","",$F$1&E20&$F$1) -> "" | V20: =IF($A20="Implicit","",$F$1&N20&$F$1) -> "string" | W20: =IF($A20="Implicit","",COUNTIFS($C$8:C20,C20,$A$8:A20,"Explicit")) -> 2 | X20: =IF($A20="Implicit","",$F$1&SUBSTITUTE(IF(I20=0,"",I20),",",";")&$F$1) -> "Restricted code list for acceptable action times" | Y20: =IF($A20="Implicit","",$F$1&SUBSTITUTE(IF(J20=0,"",J20),",",";")&$F$1) -> "Description or long version of the code; for example "Switzerland" for Switzerland when referring to the UN/LOCODE code list" | Z20: =IF($A20="Implicit","",$F$1&IF(G20=1,"false","true")&$F$1) -> "false" | AA20: =IF($A20="Implicit","",$F$1&IF(OR(E20="Enum",E20="CodeList"),"true","false")&$F$1) -> "false" | AB20: =IF($A20="Implicit","",$F$1&P20&$F$1) -> "" | AC20: =IF($A20="Implicit","",$F$1&C20&$F$1) -> "https://onerecord.iata.org/ns/cargo#ActionTimeType" | AD20: =IF($A20="Implicit","",$F$1&D20&$F$1) -> "https://onerecord.iata.org/ns/cargo#codeDescription" | AE20: =IF($A20="Implicit","",$F$1&F20&$F$1) -> "http://www.w3.org/2001/XMLSchema#string" | AF20: =IF(A20="Implicit","",R20&","&S20&","&T20&","&U20&","&V20&","&W20&","&X20&","&Y20&","&Z20&","&AA20&","&AB20&","&AC20&","&AD20&","&AE20) -> "Enum","ActionTimeType","codeDescription","","string",2,"Restricted code list for acceptable action times","Description or long version of the code; for example "Switzerland" for Switzerland when referring to the UN/LOCODE code list","false","false","","https://onerecord.iata.org/ns/cargo#ActionTimeType","https://onerecord.iata.org/ns/cargo#codeDescription","http://www.w3.org/2001/XMLSchema#string" | AG20: =IF(Q20="Data","",$F$1&B20&"."&L20&$F$1) -> "Enum.ActionTimeType" | AH20: =IF(Q20="Data","",$F$1&M20&$F$1) -> "codeDescription" | AI20: =IF(Q20="Data","",$F$1&E20&"."&N20&$F$1) -> ".string" | AJ20: =IF(Q20="Data","",$F$1&O20&$F$1) -> "" | AK20: =IF(Q20="Data","",$F$1&IF(G20=1,"hasOne","hasMany")&$F$1) -> "hasOne" | AL20: =IF(Q20="Data","",AG20&","&AH20&","&AI20&","&AJ20&","&AK20) -> "Enum.ActionTimeType","codeDescription",".string","","hasOne" | AN20: =COUNTIF(View_conceptual!G:G,L20) -> 0 | AO20: =COUNTIF(View_conceptual!H:H,L20)+COUNTIF(View_conceptual!I:I,N20) -> 0 | AQ20: =IF(AN20=1,AF20,"") | AR20: =IF(AO20=2,AL20,"") | AT20: =COUNTIF(View_full!G:G,L20) -> 0 | AU20: =COUNTIF(View_full!H:H,L20)+COUNTIF(View_full!I:I,N20) -> 0 | AV20: =COUNTIFS(Property_Manual!$A$2:$A$1206,Raw!L20,Property_Manual!$B$2:$B$1206,Raw!M20,Property_Manual!$C$2:$C$1206,Raw!N20,Property_Manual!$D$2:$D$1206,Raw!O20,Property_Manual!$F$2:$F$1206,"x") -> 0 | AW20: =IF(AT20=1,AF20,"") | AX20: =IF(AU20=2,AL20,"") | AY20: =IF(AV20=1,AL20,"")
A21: Explicit | B21: Enum | C21: https://onerecord.iata.org/ns/cargo#ActionTimeType | D21: https://onerecord.iata.org/ns/cargo#codeLevel | F21: http://www.w3.org/2001/XMLSchema#integer | G21: 1 | I21: Restricted code list for acceptable action times | J21: Integer indicating the level of a code if a codelists is hierarchical, for example HS-Codes | L21: =SUBSTITUTE(SUBSTITUTE(SUBSTITUTE(C21,$B$2,$A$2),$B$3,$A$3),$B$4,$A$4) -> ActionTimeType | M21: =SUBSTITUTE(SUBSTITUTE(SUBSTITUTE(D21,$B$2,$A$2),$B$3,$A$3),$A$4,$B$4) -> codeLevel | N21: =SUBSTITUTE(SUBSTITUTE(SUBSTITUTE(F21,$B$2,$A$2),$B$3,$A$3),$B$4,$A$4) -> integer | O21: =SUBSTITUTE(SUBSTITUTE(SUBSTITUTE(H21,$B$2,$A$2),$B$3,$A$3),$B$4,$A$4) | P21: =SUBSTITUTE(SUBSTITUTE(SUBSTITUTE(K21,$B$2,$A$2),$B$3,$A$3),$B$4,$A$4) | Q21: =IF(LEFT(N21,3)="xsd","Data","Object") -> Object | R21: =IF($A21="Implicit","",$F$1&B21&$F$1) -> "Enum" | S21: =IF($A21="Implicit","",$F$1&L21&$F$1) -> "ActionTimeType" | T21: =IF($A21="Implicit","",$F$1&M21&$F$1) -> "codeLevel" | U21: =IF($A21="Implicit","",$F$1&E21&$F$1) -> "" | V21: =IF($A21="Implicit","",$F$1&N21&$F$1) -> "integer" | W21: =IF($A21="Implicit","",COUNTIFS($C$8:C21,C21,$A$8:A21,"Explicit")) -> 3 | X21: =IF($A21="Implicit","",$F$1&SUBSTITUTE(IF(I21=0,"",I21),",",";")&$F$1) -> "Restricted code list for acceptable action times" | Y21: =IF($A21="Implicit","",$F$1&SUBSTITUTE(IF(J21=0,"",J21),",",";")&$F$1) -> "Integer indicating the level of a code if a codelists is hierarchical; for example HS-Codes" | Z21: =IF($A21="Implicit","",$F$1&IF(G21=1,"false","true")&$F$1) -> "false" | AA21: =IF($A21="Implicit","",$F$1&IF(OR(E21="Enum",E21="CodeList"),"true","false")&$F$1) -> "false" | AB21: =IF($A21="Implicit","",$F$1&P21&$F$1) -> "" | AC21: =IF($A21="Implicit","",$F$1&C21&$F$1) -> "https://onerecord.iata.org/ns/cargo#ActionTimeType" | AD21: =IF($A21="Implicit","",$F$1&D21&$F$1) -> "https://onerecord.iata.org/ns/cargo#codeLevel" | AE21: =IF($A21="Implicit","",$F$1&F21&$F$1) -> "http://www.w3.org/2001/XMLSchema#integer" | AF21: =IF(A21="Implicit","",R21&","&S21&","&T21&","&U21&","&V21&","&W21&","&X21&","&Y21&","&Z21&","&AA21&","&AB21&","&AC21&","&AD21&","&AE21) -> "Enum","ActionTimeType","codeLevel","","integer",3,"Restricted code list for acceptable action times","Integer indicating the level of a code if a codelists is hierarchical; for example HS-Codes","false","false","","https://onerecord.iata.org/ns/cargo#ActionTimeType","https://onerecord.iata.org/ns/cargo#codeLevel","http://www.w3.org/2001/XMLSchema#integer" | AG21: =IF(Q21="Data","",$F$1&B21&"."&L21&$F$1) -> "Enum.ActionTimeType" | AH21: =IF(Q21="Data","",$F$1&M21&$F$1) -> "codeLevel" | AI21: =IF(Q21="Data","",$F$1&E21&"."&N21&$F$1) -> ".integer" | AJ21: =IF(Q21="Data","",$F$1&O21&$F$1) -> "" | AK21: =IF(Q21="Data","",$F$1&IF(G21=1,"hasOne","hasMany")&$F$1) -> "hasOne" | AL21: =IF(Q21="Data","",AG21&","&AH21&","&AI21&","&AJ21&","&AK21) -> "Enum.ActionTimeType","codeLevel",".integer","","hasOne" | AN21: =COUNTIF(View_conceptual!G:G,L21) -> 0 | AO21: =COUNTIF(View_conceptual!H:H,L21)+COUNTIF(View_conceptual!I:I,N21) -> 0 | AQ21: =IF(AN21=1,AF21,"") | AR21: =IF(AO21=2,AL21,"") | AT21: =COUNTIF(View_full!G:G,L21) -> 0 | AU21: =COUNTIF(View_full!H:H,L21)+COUNTIF(View_full!I:I,N21) -> 0 | AV21: =COUNTIFS(Property_Manual!$A$2:$A$1206,Raw!L21,Property_Manual!$B$2:$B$1206,Raw!M21,Property_Manual!$C$2:$C$1206,Raw!N21,Property_Manual!$D$2:$D$1206,Raw!O21,Property_Manual!$F$2:$F$1206,"x") -> 0 | AW21: =IF(AT21=1,AF21,"") | AX21: =IF(AU21=2,AL21,"") | AY21: =IF(AV21=1,AL21,"")
A22: Explicit | B22: Enum | C22: https://onerecord.iata.org/ns/cargo#ActionTimeType | D22: https://onerecord.iata.org/ns/cargo#codeListName | F22: http://www.w3.org/2001/XMLSchema#string | G22: 1 | I22: Restricted code list for acceptable action times | J22: Official name of the code list without version number when direct reference is not possible, for example "UN/LOCODE" when referring to the UN/LOCODE code list | L22: =SUBSTITUTE(SUBSTITUTE(SUBSTITUTE(C22,$B$2,$A$2),$B$3,$A$3),$B$4,$A$4) -> ActionTimeType | M22: =SUBSTITUTE(SUBSTITUTE(SUBSTITUTE(D22,$B$2,$A$2),$B$3,$A$3),$A$4,$B$4) -> codeListName | N22: =SUBSTITUTE(SUBSTITUTE(SUBSTITUTE(F22,$B$2,$A$2),$B$3,$A$3),$B$4,$A$4) -> string | O22: =SUBSTITUTE(SUBSTITUTE(SUBSTITUTE(H22,$B$2,$A$2),$B$3,$A$3),$B$4,$A$4) | P22: =SUBSTITUTE(SUBSTITUTE(SUBSTITUTE(K22,$B$2,$A$2),$B$3,$A$3),$B$4,$A$4) | Q22: =IF(LEFT(N22,3)="xsd","Data","Object") -> Object | R22: =IF($A22="Implicit","",$F$1&B22&$F$1) -> "Enum" | S22: =IF($A22="Implicit","",$F$1&L22&$F$1) -> "ActionTimeType" | T22: =IF($A22="Implicit","",$F$1&M22&$F$1) -> "codeListName" | U22: =IF($A22="Implicit","",$F$1&E22&$F$1) -> "" | V22: =IF($A22="Implicit","",$F$1&N22&$F$1) -> "string" | W22: =IF($A22="Implicit","",COUNTIFS($C$8:C22,C22,$A$8:A22,"Explicit")) -> 4 | X22: =IF($A22="Implicit","",$F$1&SUBSTITUTE(IF(I22=0,"",I22),",",";")&$F$1) -> "Restricted code list for acceptable action times" | Y22: =IF($A22="Implicit","",$F$1&SUBSTITUTE(IF(J22=0,"",J22),",",";")&$F$1) -> "Official name of the code list without version number when direct reference is not possible; for example "UN/LOCODE" when referring to the UN/LOCODE code list" | Z22: =IF($A22="Implicit","",$F$1&IF(G22=1,"false","true")&$F$1) -> "false" | AA22: =IF($A22="Implicit","",$F$1&IF(OR(E22="Enum",E22="CodeList"),"true","false")&$F$1) -> "false" | AB22: =IF($A22="Implicit","",$F$1&P22&$F$1) -> "" | AC22: =IF($A22="Implicit","",$F$1&C22&$F$1) -> "https://onerecord.iata.org/ns/cargo#ActionTimeType" | AD22: =IF($A22="Implicit","",$F$1&D22&$F$1) -> "https://onerecord.iata.org/ns/cargo#codeListName" | AE22: =IF($A22="Implicit","",$F$1&F22&$F$1) -> "http://www.w3.org/2001/XMLSchema#string" | AF22: =IF(A22="Implicit","",R22&","&S22&","&T22&","&U22&","&V22&","&W22&","&X22&","&Y22&","&Z22&","&AA22&","&AB22&","&AC22&","&AD22&","&AE22) -> "Enum","ActionTimeType","codeListName","","string",4,"Restricted code list for acceptable action times","Official name of the code list without version number when direct reference is not possible; for example "UN/LOCODE" when referring to the UN/LOCODE code list","false","false","","https://onerecord.iata.org/ns/cargo#ActionTimeType","https://onerecord.iata.org/ns/cargo#codeListName","http://www.w3.org/2001/XMLSchema#string" | AG22: =IF(Q22="Data","",$F$1&B22&"."&L22&$F$1) -> "Enum.ActionTimeType" | AH22: =IF(Q22="Data","",$F$1&M22&$F$1) -> "codeListName" | AI22: =IF(Q22="Data","",$F$1&E22&"."&N22&$F$1) -> ".string" | AJ22: =IF(Q22="Data","",$F$1&O22&$F$1) -> "" | AK22: =IF(Q22="Data","",$F$1&IF(G22=1,"hasOne","hasMany")&$F$1) -> "hasOne" | AL22: =IF(Q22="Data","",AG22&","&AH22&","&AI22&","&AJ22&","&AK22) -> "Enum.ActionTimeType","codeListName",".string","","hasOne" | AN22: =COUNTIF(View_conceptual!G:G,L22) -> 0 | AO22: =COUNTIF(View_conceptual!H:H,L22)+COUNTIF(View_conceptual!I:I,N22) -> 0 | AQ22: =IF(AN22=1,AF22,"") | AR22: =IF(AO22=2,AL22,"") | AT22: =COUNTIF(View_full!G:G,L22) -> 0 | AU22: =COUNTIF(View_full!H:H,L22)+COUNTIF(View_full!I:I,N22) -> 0 | AV22: =COUNTIFS(Property_Manual!$A$2:$A$1206,Raw!L22,Property_Manual!$B$2:$B$1206,Raw!M22,Property_Manual!$C$2:$C$1206,Raw!N22,Property_Manual!$D$2:$D$1206,Raw!O22,Property_Manual!$F$2:$F$1206,"x") -> 0 | AW22: =IF(AT22=1,AF22,"") | AX22: =IF(AU22=2,AL22,"") | AY22: =IF(AV22=1,AL22,"")
... A24: Explicit | B24: Enum | C24: https://onerecord.iata.org/ns/cargo#ActionTimeType | D24: https://onerecord.iata.org/ns/cargo#codeListVersion | F24: http://www.w3.org/2001/XMLSchema#string | G24: 1 | I24: Restricted code list for acceptable action times | J24: Version of the code list, for example "223-1" for UN/LOCODE. Used if the property codeListName is used or the version is not apparent from the resource referred to in property codeListReference. | L24: =SUBSTITUTE(SUBSTITUTE(SUBSTITUTE(C24,$B$2,$A$2),$B$3,$A$3),$B$4,$A$4) -> ActionTimeType | M24: =SUBSTITUTE(SUBSTITUTE(SUBSTITUTE(D24,$B$2,$A$2),$B$3,$A$3),$A$4,$B$4) -> codeListVersion | N24: =SUBSTITUTE(SUBSTITUTE(SUBSTITUTE(F24,$B$2,$A$2),$B$3,$A$3),$B$4,$A$4) -> string | O24: =SUBSTITUTE(SUBSTITUTE(SUBSTITUTE(H24,$B$2,$A$2),$B$3,$A$3),$B$4,$A$4) | P24: =SUBSTITUTE(SUBSTITUTE(SUBSTITUTE(K24,$B$2,$A$2),$B$3,$A$3),$B$4,$A$4) | Q24: =IF(LEFT(N24,3)="xsd","Data","Object") -> Object | R24: =IF($A24="Implicit","",$F$1&B24&$F$1) -> "Enum" | S24: =IF($A24="Implicit","",$F$1&L24&$F$1) -> "ActionTimeType" | T24: =IF($A24="Implicit","",$F$1&M24&$F$1) -> "codeListVersion" | U24: =IF($A24="Implicit","",$F$1&E24&$F$1) -> "" | V24: =IF($A24="Implicit","",$F$1&N24&$F$1) -> "string" | W24: =IF($A24="Implicit","",COUNTIFS($C$8:C24,C24,$A$8:A24,"Explicit")) -> 6 | X24: =IF($A24="Implicit","",$F$1&SUBSTITUTE(IF(I24=0,"",I24),",",";")&$F$1) -> "Restricted code list for acceptable action times" | Y24: =IF($A24="Implicit","",$F$1&SUBSTITUTE(IF(J24=0,"",J24),",",";")&$F$1) -> "Version of the code list; for example "223-1" for UN/LOCODE. Used if the property codeListName is used or the version is not apparent from the resource referred to in property codeListReference." | Z24: =IF($A24="Implicit","",$F$1&IF(G24=1,"false","true")&$F$1) -> "false" | AA24: =IF($A24="Implicit","",$F$1&IF(OR(E24="Enum",E24="CodeList"),"true","false")&$F$1) -> "false" | AB24: =IF($A24="Implicit","",$F$1&P24&$F$1) -> "" | AC24: =IF($A24="Implicit","",$F$1&C24&$F$1) -> "https://onerecord.iata.org/ns/cargo#ActionTimeType" | AD24: =IF($A24="Implicit","",$F$1&D24&$F$1) -> "https://onerecord.iata.org/ns/cargo#codeListVersion" | AE24: =IF($A24="Implicit","",$F$1&F24&$F$1) -> "http://www.w3.org/2001/XMLSchema#string" | AF24: =IF(A24="Implicit","",R24&","&S24&","&T24&","&U24&","&V24&","&W24&","&X24&","&Y24&","&Z24&","&AA24&","&AB24&","&AC24&","&AD24&","&AE24) -> "Enum","ActionTimeType","codeListVersion","","string",6,"Restricted code list for acceptable action times","Version of the code list; for example "223-1" for UN/LOCODE. Used if the property codeListName is used or the version is not apparent from the resource referred to in property codeListReference.","false","false","","https://onerecord.iata.org/ns/cargo#ActionTimeType","https://onerecord.iata.org/ns/cargo#codeListVersion","http://www.w3.org/2001/XMLSchema#string" | AG24: =IF(Q24="Data","",$F$1&B24&"."&L24&$F$1) -> "Enum.ActionTimeType" | AH24: =IF(Q24="Data","",$F$1&M24&$F$1) -> "codeListVersion" | AI24: =IF(Q24="Data","",$F$1&E24&"."&N24&$F$1) -> ".string" | AJ24: =IF(Q24="Data","",$F$1&O24&$F$1) -> "" | AK24: =IF(Q24="Data","",$F$1&IF(G24=1,"hasOne","hasMany")&$F$1) -> "hasOne" | AL24: =IF(Q24="Data","",AG24&","&AH24&","&AI24&","&AJ24&","&AK24) -> "Enum.ActionTimeType","codeListVersion",".string","","hasOne" | AN24: =COUNTIF(View_conceptual!G:G,L24) -> 0 | AO24: =COUNTIF(View_conceptual!H:H,L24)+COUNTIF(View_conceptual!I:I,N24) -> 0 | AQ24: =IF(AN24=1,AF24,"") | AR24: =IF(AO24=2,AL24,"") | AT24: =COUNTIF(View_full!G:G,L24) -> 0 | AU24: =COUNTIF(View_full!H:H,L24)+COUNTIF(View_full!I:I,N24) -> 0 | AV24: =COUNTIFS(Property_Manual!$A$2:$A$1206,Raw!L24,Property_Manual!$B$2:$B$1206,Raw!M24,Property_Manual!$C$2:$C$1206,Raw!N24,Property_Manual!$D$2:$D$1206,Raw!O24,Property_Manual!$F$2:$F$1206,"x") -> 0 | AW24: =IF(AT24=1,AF24,"") | AX24: =IF(AU24=2,AL24,"") | AY24: =IF(AV24=1,AL24,"")
A25: Explicit | B25: Embedded | C25: https://onerecord.iata.org/ns/cargo#ActivitySequence | D25: https://onerecord.iata.org/ns/cargo#activity | E25: Abstract | F25: https://onerecord.iata.org/ns/cargo#LogisticsActivity | G25: 1 | I25: Embedded object to create a sequence of Activities in the context of a Service | J25: Reference to the Activity that is performed as part of a Service | K25: https://onerecord.iata.org/ns/cargo#UnitComposition|https://onerecord.iata.org/ns/cargo#TransportMovement|https://onerecord.iata.org/ns/cargo#Storage | L25: =SUBSTITUTE(SUBSTITUTE(SUBSTITUTE(C25,$B$2,$A$2),$B$3,$A$3),$B$4,$A$4) -> ActivitySequence | M25: =SUBSTITUTE(SUBSTITUTE(SUBSTITUTE(D25,$B$2,$A$2),$B$3,$A$3),$A$4,$B$4) -> activity | N25: =SUBSTITUTE(SUBSTITUTE(SUBSTITUTE(F25,$B$2,$A$2),$B$3,$A$3),$B$4,$A$4) -> LogisticsActivity | O25: =SUBSTITUTE(SUBSTITUTE(SUBSTITUTE(H25,$B$2,$A$2),$B$3,$A$3),$B$4,$A$4) | P25: =SUBSTITUTE(SUBSTITUTE(SUBSTITUTE(K25,$B$2,$A$2),$B$3,$A$3),$B$4,$A$4) -> UnitComposition|TransportMovement|Storage | Q25: =IF(LEFT(N25,3)="xsd","Data","Object") -> Object | R25: =IF($A25="Implicit","",$F$1&B25&$F$1) -> "Embedded" | S25: =IF($A25="Implicit","",$F$1&L25&$F$1) -> "ActivitySequence" | T25: =IF($A25="Implicit","",$F$1&M25&$F$1) -> "activity" | U25: =IF($A25="Implicit","",$F$1&E25&$F$1) -> "Abstract" | V25: =IF($A25="Implicit","",$F$1&N25&$F$1) -> "LogisticsActivity" | W25: =IF($A25="Implicit","",COUNTIFS($C$8:C25,C25,$A$8:A25,"Explicit")) -> 1 | X25: =IF($A25="Implicit","",$F$1&SUBSTITUTE(IF(I25=0,"",I25),",",";")&$F$1) -> "Embedded object to create a sequence of Activities in the context of a Service" | Y25: =IF($A25="Implicit","",$F$1&SUBSTITUTE(IF(J25=0,"",J25),",",";")&$F$1) -> "Reference to the Activity that is performed as part of a Service" | Z25: =IF($A25="Implicit","",$F$1&IF(G25=1,"false","true")&$F$1) -> "false" | AA25: =IF($A25="Implicit","",$F$1&IF(OR(E25="Enum",E25="CodeList"),"true","false")&$F$1) -> "false" | AB25: =IF($A25="Implicit","",$F$1&P25&$F$1) -> "UnitComposition|TransportMovement|Storage" | AC25: =IF($A25="Implicit","",$F$1&C25&$F$1) -> "https://onerecord.iata.org/ns/cargo#ActivitySequence" | AD25: =IF($A25="Implicit","",$F$1&D25&$F$1) -> "https://onerecord.iata.org/ns/cargo#activity" | AE25: =IF($A25="Implicit","",$F$1&F25&$F$1) -> "https://onerecord.iata.org/ns/cargo#LogisticsActivity" | AF25: =IF(A25="Implicit","",R25&","&S25&","&T25&","&U25&","&V25&","&W25&","&X25&","&Y25&","&Z25&","&AA25&","&AB25&","&AC25&","&AD25&","&AE25) -> "Embedded","ActivitySequence","activity","Abstract","LogisticsActivity",1,"Embedded object to create a sequence of Activities in the context of a Service","Reference to the Activity that is performed as part of a Service","false","false","UnitComposition|TransportMovement|Storage","https://onerecord.iata.org/ns/cargo#ActivitySequence","https://onerecord.iata.org/ns/cargo#activity","https://onerecord.iata.org/ns/cargo#LogisticsActivity" | AG25: =IF(Q25="Data","",$F$1&B25&"."&L25&$F$1) -> "Embedded.ActivitySequence" | AH25: =IF(Q25="Data","",$F$1&M25&$F$1) -> "activity" | AI25: =IF(Q25="Data","",$F$1&E25&"."&N25&$F$1) -> "Abstract.LogisticsActivity" | AJ25: =IF(Q25="Data","",$F$1&O25&$F$1) -> "" | AK25: =IF(Q25="Data","",$F$1&IF(G25=1,"hasOne","hasMany")&$F$1) -> "hasOne" | AL25: =IF(Q25="Data","",AG25&","&AH25&","&AI25&","&AJ25&","&AK25) -> "Embedded.ActivitySequence","activity","Abstract.LogisticsActivity","","hasOne" | AN25: =COUNTIF(View_conceptual!G:G,L25) -> 1 | AO25: =COUNTIF(View_conceptual!H:H,L25)+COUNTIF(View_conceptual!I:I,N25) -> 1 | AQ25: =IF(AN25=1,AF25,"") -> "Embedded","ActivitySequence","activity","Abstract","LogisticsActivity",1,"Embedded object to create a sequence of Activities in the context of a Service","Reference to the Activity that is performed as part of a Service","false","false","UnitComposition|TransportMovement|Storage","https://onerecord.iata.org/ns/cargo#ActivitySequence","https://onerecord.iata.org/ns/cargo#activity","https://onerecord.iata.org/ns/cargo#LogisticsActivity" | AR25: =IF(AO25=2,AL25,"") | AT25: =COUNTIF(View_full!G:G,L25) -> 1 | AU25: =COUNTIF(View_full!H:H,L25)+COUNTIF(View_full!I:I,N25) -> 1 | AV25: =COUNTIFS(Property_Manual!$A$2:$A$1206,Raw!L25,Property_Manual!$B$2:$B$1206,Raw!M25,Property_Manual!$C$2:$C$1206,Raw!N25,Property_Manual!$D$2:$D$1206,Raw!O25,Property_Manual!$F$2:$F$1206,"x") -> 0 | AW25: =IF(AT25=1,AF25,"") -> "Embedded","ActivitySequence","activity","Abstract","LogisticsActivity",1,"Embedded object to create a sequence of Activities in the context of a Service","Reference to the Activity that is performed as part of a Service","false","false","UnitComposition|TransportMovement|Storage","https://onerecord.iata.org/ns/cargo#ActivitySequence","https://onerecord.iata.org/ns/cargo#activity","https://onerecord.iata.org/ns/cargo#LogisticsActivity" | AX25: =IF(AU25=2,AL25,"") | AY25: =IF(AV25=1,AL25,"")
A26: Implicit | B26: Embedded | C26: https://onerecord.iata.org/ns/cargo#ActivitySequence | D26: https://onerecord.iata.org/ns/cargo#activity | E26: Abstract | F26: https://onerecord.iata.org/ns/cargo#LogisticsActivity | G26: 1 | I26: Embedded object to create a sequence of Activities in the context of a Service | J26: Reference to the Activity that is performed as part of a Service | K26: https://onerecord.iata.org/ns/cargo#UnitComposition|https://onerecord.iata.org/ns/cargo#TransportMovement|https://onerecord.iata.org/ns/cargo#Storage | L26: =SUBSTITUTE(SUBSTITUTE(SUBSTITUTE(C26,$B$2,$A$2),$B$3,$A$3),$B$4,$A$4) -> ActivitySequence | M26: =SUBSTITUTE(SUBSTITUTE(SUBSTITUTE(D26,$B$2,$A$2),$B$3,$A$3),$A$4,$B$4) -> activity | N26: =SUBSTITUTE(SUBSTITUTE(SUBSTITUTE(F26,$B$2,$A$2),$B$3,$A$3),$B$4,$A$4) -> LogisticsActivity | O26: =SUBSTITUTE(SUBSTITUTE(SUBSTITUTE(H26,$B$2,$A$2),$B$3,$A$3),$B$4,$A$4) | P26: =SUBSTITUTE(SUBSTITUTE(SUBSTITUTE(K26,$B$2,$A$2),$B$3,$A$3),$B$4,$A$4) -> UnitComposition|TransportMovement|Storage | Q26: =IF(LEFT(N26,3)="xsd","Data","Object") -> Object | R26: =IF($A26="Implicit","",$F$1&B26&$F$1) | S26: =IF($A26="Implicit","",$F$1&L26&$F$1) | T26: =IF($A26="Implicit","",$F$1&M26&$F$1) | U26: =IF($A26="Implicit","",$F$1&E26&$F$1) | V26: =IF($A26="Implicit","",$F$1&N26&$F$1) | W26: =IF($A26="Implicit","",COUNTIFS($C$8:C26,C26,$A$8:A26,"Explicit")) | X26: =IF($A26="Implicit","",$F$1&SUBSTITUTE(IF(I26=0,"",I26),",",";")&$F$1) | Y26: =IF($A26="Implicit","",$F$1&SUBSTITUTE(IF(J26=0,"",J26),",",";")&$F$1) | Z26: =IF($A26="Implicit","",$F$1&IF(G26=1,"false","true")&$F$1) | AA26: =IF($A26="Implicit","",$F$1&IF(OR(E26="Enum",E26="CodeList"),"true","false")&$F$1) | AB26: =IF($A26="Implicit","",$F$1&P26&$F$1) | AC26: =IF($A26="Implicit","",$F$1&C26&$F$1) | AD26: =IF($A26="Implicit","",$F$1&D26&$F$1) | AE26: =IF($A26="Implicit","",$F$1&F26&$F$1) | AF26: =IF(A26="Implicit","",R26&","&S26&","&T26&","&U26&","&V26&","&W26&","&X26&","&Y26&","&Z26&","&AA26&","&AB26&","&AC26&","&AD26&","&AE26) | AG26: =IF(Q26="Data","",$F$1&B26&"."&L26&$F$1) -> "Embedded.ActivitySequence" | AH26: =IF(Q26="Data","",$F$1&M26&$F$1) -> "activity" | AI26: =IF(Q26="Data","",$F$1&E26&"."&N26&$F$1) -> "Abstract.LogisticsActivity" | AJ26: =IF(Q26="Data","",$F$1&O26&$F$1) -> "" | AK26: =IF(Q26="Data","",$F$1&IF(G26=1,"hasOne","hasMany")&$F$1) -> "hasOne" | AL26: =IF(Q26="Data","",AG26&","&AH26&","&AI26&","&AJ26&","&AK26) -> "Embedded.ActivitySequence","activity","Abstract.LogisticsActivity","","hasOne" | AN26: =COUNTIF(View_conceptual!G:G,L26) -> 1 | AO26: =COUNTIF(View_conceptual!H:H,L26)+COUNTIF(View_conceptual!I:I,N26) -> 1 | AQ26: =IF(AN26=1,AF26,"") | AR26: =IF(AO26=2,AL26,"") | AT26: =COUNTIF(View_full!G:G,L26) -> 1 | AU26: =COUNTIF(View_full!H:H,L26)+COUNTIF(View_full!I:I,N26) -> 1 | AV26: =COUNTIFS(Property_Manual!$A$2:$A$1206,Raw!L26,Property_Manual!$B$2:$B$1206,Raw!M26,Property_Manual!$C$2:$C$1206,Raw!N26,Property_Manual!$D$2:$D$1206,Raw!O26,Property_Manual!$F$2:$F$1206,"x") -> 0 | AW26: =IF(AT26=1,AF26,"") | AX26: =IF(AU26=2,AL26,"") | AY26: =IF(AV26=1,AL26,"")
A27: Implicit | B27: Embedded | C27: https://onerecord.iata.org/ns/cargo#ActivitySequence | D27: https://onerecord.iata.org/ns/cargo#activity | E27: Activity | F27: https://onerecord.iata.org/ns/cargo#UnitComposition | G27: 1 | I27: Embedded object to create a sequence of Activities in the context of a Service | J27: Reference to the Activity that is performed as part of a Service | L27: =SUBSTITUTE(SUBSTITUTE(SUBSTITUTE(C27,$B$2,$A$2),$B$3,$A$3),$B$4,$A$4) -> ActivitySequence | M27: =SUBSTITUTE(SUBSTITUTE(SUBSTITUTE(D27,$B$2,$A$2),$B$3,$A$3),$A$4,$B$4) -> activity | N27: =SUBSTITUTE(SUBSTITUTE(SUBSTITUTE(F27,$B$2,$A$2),$B$3,$A$3),$B$4,$A$4) -> UnitComposition | O27: =SUBSTITUTE(SUBSTITUTE(SUBSTITUTE(H27,$B$2,$A$2),$B$3,$A$3),$B$4,$A$4) | P27: =SUBSTITUTE(SUBSTITUTE(SUBSTITUTE(K27,$B$2,$A$2),$B$3,$A$3),$B$4,$A$4) | Q27: =IF(LEFT(N27,3)="xsd","Data","Object") -> Object | R27: =IF($A27="Implicit","",$F$1&B27&$F$1) | S27: =IF($A27="Implicit","",$F$1&L27&$F$1) | T27: =IF($A27="Implicit","",$F$1&M27&$F$1) | U27: =IF($A27="Implicit","",$F$1&E27&$F$1) | V27: =IF($A27="Implicit","",$F$1&N27&$F$1) | W27: =IF($A27="Implicit","",COUNTIFS($C$8:C27,C27,$A$8:A27,"Explicit")) | X27: =IF($A27="Implicit","",$F$1&SUBSTITUTE(IF(I27=0,"",I27),",",";")&$F$1) | Y27: =IF($A27="Implicit","",$F$1&SUBSTITUTE(IF(J27=0,"",J27),",",";")&$F$1) | Z27: =IF($A27="Implicit","",$F$1&IF(G27=1,"false","true")&$F$1) | AA27: =IF($A27="Implicit","",$F$1&IF(OR(E27="Enum",E27="CodeList"),"true","false")&$F$1) | AB27: =IF($A27="Implicit","",$F$1&P27&$F$1) | AC27: =IF($A27="Implicit","",$F$1&C27&$F$1) | AD27: =IF($A27="Implicit","",$F$1&D27&$F$1) | AE27: =IF($A27="Implicit","",$F$1&F27&$F$1) | AF27: =IF(A27="Implicit","",R27&","&S27&","&T27&","&U27&","&V27&","&W27&","&X27&","&Y27&","&Z27&","&AA27&","&AB27&","&AC27&","&AD27&","&AE27) | AG27: =IF(Q27="Data","",$F$1&B27&"."&L27&$F$1) -> "Embedded.ActivitySequence" | AH27: =IF(Q27="Data","",$F$1&M27&$F$1) -> "activity" | AI27: =IF(Q27="Data","",$F$1&E27&"."&N27&$F$1) -> "Activity.UnitComposition" | AJ27: =IF(Q27="Data","",$F$1&O27&$F$1) -> "" | AK27: =IF(Q27="Data","",$F$1&IF(G27=1,"hasOne","hasMany")&$F$1) -> "hasOne" | AL27: =IF(Q27="Data","",AG27&","&AH27&","&AI27&","&AJ27&","&AK27) -> "Embedded.ActivitySequence","activity","Activity.UnitComposition","","hasOne" | AN27: =COUNTIF(View_conceptual!G:G,L27) -> 1 | AO27: =COUNTIF(View_conceptual!H:H,L27)+COUNTIF(View_conceptual!I:I,N27) -> 2 | AQ27: =IF(AN27=1,AF27,"") | AR27: =IF(AO27=2,AL27,"") -> "Embedded.ActivitySequence","activity","Activity.UnitComposition","","hasOne" | AT27: =COUNTIF(View_full!G:G,L27) -> 1 | AU27: =COUNTIF(View_full!H:H,L27)+COUNTIF(View_full!I:I,N27) -> 2 | AV27: =COUNTIFS(Property_Manual!$A$2:$A$1206,Raw!L27,Property_Manual!$B$2:$B$1206,Raw!M27,Property_Manual!$C$2:$C$1206,Raw!N27,Property_Manual!$D$2:$D$1206,Raw!O27,Property_Manual!$F$2:$F$1206,"x") -> 1 | AW27: =IF(AT27=1,AF27,"") | AX27: =IF(AU27=2,AL27,"") -> "Embedded.ActivitySequence","activity","Activity.UnitComposition","","hasOne" | AY27: =IF(AV27=1,AL27,"") -> "Embedded.ActivitySequence","activity","Activity.UnitComposition","","hasOne"
A28: Implicit | B28: Embedded | C28: https://onerecord.iata.org/ns/cargo#ActivitySequence | D28: https://onerecord.iata.org/ns/cargo#activity | E28: Activity | F28: https://onerecord.iata.org/ns/cargo#TransportMovement | G28: 1 | I28: Embedded object to create a sequence of Activities in the context of a Service | J28: Reference to the Activity that is performed as part of a Service | L28: =SUBSTITUTE(SUBSTITUTE(SUBSTITUTE(C28,$B$2,$A$2),$B$3,$A$3),$B$4,$A$4) -> ActivitySequence | M28: =SUBSTITUTE(SUBSTITUTE(SUBSTITUTE(D28,$B$2,$A$2),$B$3,$A$3),$A$4,$B$4) -> activity | N28: =SUBSTITUTE(SUBSTITUTE(SUBSTITUTE(F28,$B$2,$A$2),$B$3,$A$3),$B$4,$A$4) -> TransportMovement | O28: =SUBSTITUTE(SUBSTITUTE(SUBSTITUTE(H28,$B$2,$A$2),$B$3,$A$3),$B$4,$A$4) | P28: =SUBSTITUTE(SUBSTITUTE(SUBSTITUTE(K28,$B$2,$A$2),$B$3,$A$3),$B$4,$A$4) | Q28: =IF(LEFT(N28,3)="xsd","Data","Object") -> Object | R28: =IF($A28="Implicit","",$F$1&B28&$F$1) | S28: =IF($A28="Implicit","",$F$1&L28&$F$1) | T28: =IF($A28="Implicit","",$F$1&M28&$F$1) | U28: =IF($A28="Implicit","",$F$1&E28&$F$1) | V28: =IF($A28="Implicit","",$F$1&N28&$F$1) | W28: =IF($A28="Implicit","",COUNTIFS($C$8:C28,C28,$A$8:A28,"Explicit")) | X28: =IF($A28="Implicit","",$F$1&SUBSTITUTE(IF(I28=0,"",I28),",",";")&$F$1) | Y28: =IF($A28="Implicit","",$F$1&SUBSTITUTE(IF(J28=0,"",J28),",",";")&$F$1) | Z28: =IF($A28="Implicit","",$F$1&IF(G28=1,"false","true")&$F$1) | AA28: =IF($A28="Implicit","",$F$1&IF(OR(E28="Enum",E28="CodeList"),"true","false")&$F$1) | AB28: =IF($A28="Implicit","",$F$1&P28&$F$1) | AC28: =IF($A28="Implicit","",$F$1&C28&$F$1) | AD28: =IF($A28="Implicit","",$F$1&D28&$F$1) | AE28: =IF($A28="Implicit","",$F$1&F28&$F$1) | AF28: =IF(A28="Implicit","",R28&","&S28&","&T28&","&U28&","&V28&","&W28&","&X28&","&Y28&","&Z28&","&AA28&","&AB28&","&AC28&","&AD28&","&AE28) | AG28: =IF(Q28="Data","",$F$1&B28&"."&L28&$F$1) -> "Embedded.ActivitySequence" | AH28: =IF(Q28="Data","",$F$1&M28&$F$1) -> "activity" | AI28: =IF(Q28="Data","",$F$1&E28&"."&N28&$F$1) -> "Activity.TransportMovement" | AJ28: =IF(Q28="Data","",$F$1&O28&$F$1) -> "" | AK28: =IF(Q28="Data","",$F$1&IF(G28=1,"hasOne","hasMany")&$F$1) -> "hasOne" | AL28: =IF(Q28="Data","",AG28&","&AH28&","&AI28&","&AJ28&","&AK28) -> "Embedded.ActivitySequence","activity","Activity.TransportMovement","","hasOne" | AN28: =COUNTIF(View_conceptual!G:G,L28) -> 1 | AO28: =COUNTIF(View_conceptual!H:H,L28)+COUNTIF(View_conceptual!I:I,N28) -> 2 | AQ28: =IF(AN28=1,AF28,"") | AR28: =IF(AO28=2,AL28,"") -> "Embedded.ActivitySequence","activity","Activity.TransportMovement","","hasOne" | AT28: =COUNTIF(View_full!G:G,L28) -> 1 | AU28: =COUNTIF(View_full!H:H,L28)+COUNTIF(View_full!I:I,N28) -> 2 | AV28: =COUNTIFS(Property_Manual!$A$2:$A$1206,Raw!L28,Property_Manual!$B$2:$B$1206,Raw!M28,Property_Manual!$C$2:$C$1206,Raw!N28,Property_Manual!$D$2:$D$1206,Raw!O28,Property_Manual!$F$2:$F$1206,"x") -> 1 | AW28: =IF(AT28=1,AF28,"") | AX28: =IF(AU28=2,AL28,"") -> "Embedded.ActivitySequence","activity","Activity.TransportMovement","","hasOne" | AY28: =IF(AV28=1,AL28,"") -> "Embedded.ActivitySequence","activity","Activity.TransportMovement","","hasOne"
A29: Implicit | B29: Embedded | C29: https://onerecord.iata.org/ns/cargo#ActivitySequence | D29: https://onerecord.iata.org/ns/cargo#activity | E29: Activity | F29: https://onerecord.iata.org/ns/cargo#Storage | G29: 1 | I29: Embedded object to create a sequence of Activities in the context of a Service | J29: Reference to the Activity that is performed as part of a Service | L29: =SUBSTITUTE(SUBSTITUTE(SUBSTITUTE(C29,$B$2,$A$2),$B$3,$A$3),$B$4,$A$4) -> ActivitySequence | M29: =SUBSTITUTE(SUBSTITUTE(SUBSTITUTE(D29,$B$2,$A$2),$B$3,$A$3),$A$4,$B$4) -> activity | N29: =SUBSTITUTE(SUBSTITUTE(SUBSTITUTE(F29,$B$2,$A$2),$B$3,$A$3),$B$4,$A$4) -> Storage | O29: =SUBSTITUTE(SUBSTITUTE(SUBSTITUTE(H29,$B$2,$A$2),$B$3,$A$3),$B$4,$A$4) | P29: =SUBSTITUTE(SUBSTITUTE(SUBSTITUTE(K29,$B$2,$A$2),$B$3,$A$3),$B$4,$A$4) | Q29: =IF(LEFT(N29,3)="xsd","Data","Object") -> Object | R29: =IF($A29="Implicit","",$F$1&B29&$F$1) | S29: =IF($A29="Implicit","",$F$1&L29&$F$1) | T29: =IF($A29="Implicit","",$F$1&M29&$F$1) | U29: =IF($A29="Implicit","",$F$1&E29&$F$1) | V29: =IF($A29="Implicit","",$F$1&N29&$F$1) | W29: =IF($A29="Implicit","",COUNTIFS($C$8:C29,C29,$A$8:A29,"Explicit")) | X29: =IF($A29="Implicit","",$F$1&SUBSTITUTE(IF(I29=0,"",I29),",",";")&$F$1) | Y29: =IF($A29="Implicit","",$F$1&SUBSTITUTE(IF(J29=0,"",J29),",",";")&$F$1) | Z29: =IF($A29="Implicit","",$F$1&IF(G29=1,"false","true")&$F$1) | AA29: =IF($A29="Implicit","",$F$1&IF(OR(E29="Enum",E29="CodeList"),"true","false")&$F$1) | AB29: =IF($A29="Implicit","",$F$1&P29&$F$1) | AC29: =IF($A29="Implicit","",$F$1&C29&$F$1) | AD29: =IF($A29="Implicit","",$F$1&D29&$F$1) | AE29: =IF($A29="Implicit","",$F$1&F29&$F$1) | AF29: =IF(A29="Implicit","",R29&","&S29&","&T29&","&U29&","&V29&","&W29&","&X29&","&Y29&","&Z29&","&AA29&","&AB29&","&AC29&","&AD29&","&AE29) | AG29: =IF(Q29="Data","",$F$1&B29&"."&L29&$F$1) -> "Embedded.ActivitySequence" | AH29: =IF(Q29="Data","",$F$1&M29&$F$1) -> "activity" | AI29: =IF(Q29="Data","",$F$1&E29&"."&N29&$F$1) -> "Activity.Storage" | AJ29: =IF(Q29="Data","",$F$1&O29&$F$1) -> "" | AK29: =IF(Q29="Data","",$F$1&IF(G29=1,"hasOne","hasMany")&$F$1) -> "hasOne" | AL29: =IF(Q29="Data","",AG29&","&AH29&","&AI29&","&AJ29&","&AK29) -> "Embedded.ActivitySequence","activity","Activity.Storage","","hasOne" | AN29: =COUNTIF(View_conceptual!G:G,L29) -> 1 | AO29: =COUNTIF(View_conceptual!H:H,L29)+COUNTIF(View_conceptual!I:I,N29) -> 1 | AQ29: =IF(AN29=1,AF29,"") | AR29: =IF(AO29=2,AL29,"") | AT29: =COUNTIF(View_full!G:G,L29) -> 1 | AU29: =COUNTIF(View_full!H:H,L29)+COUNTIF(View_full!I:I,N29) -> 2 | AV29: =COUNTIFS(Property_Manual!$A$2:$A$1206,Raw!L29,Property_Manual!$B$2:$B$1206,Raw!M29,Property_Manual!$C$2:$C$1206,Raw!N29,Property_Manual!$D$2:$D$1206,Raw!O29,Property_Manual!$F$2:$F$1206,"x") -> 0 | AW29: =IF(AT29=1,AF29,"") | AX29: =IF(AU29=2,AL29,"") -> "Embedded.ActivitySequence","activity","Activity.Storage","","hasOne" | AY29: =IF(AV29=1,AL29,"")
A30: Explicit | B30: Embedded | C30: https://onerecord.iata.org/ns/cargo#ActivitySequence | D30: https://onerecord.iata.org/ns/cargo#sequenceNumber | F30: http://www.w3.org/2001/XMLSchema#string | G30: 1 | I30: Embedded object to create a sequence of Activities in the context of a Service | J30: Short text to detail sequence number (alphanumeric) | L30: =SUBSTITUTE(SUBSTITUTE(SUBSTITUTE(C30,$B$2,$A$2),$B$3,$A$3),$B$4,$A$4) -> ActivitySequence | M30: =SUBSTITUTE(SUBSTITUTE(SUBSTITUTE(D30,$B$2,$A$2),$B$3,$A$3),$A$4,$B$4) -> sequenceNumber | N30: =SUBSTITUTE(SUBSTITUTE(SUBSTITUTE(F30,$B$2,$A$2),$B$3,$A$3),$B$4,$A$4) -> string | O30: =SUBSTITUTE(SUBSTITUTE(SUBSTITUTE(H30,$B$2,$A$2),$B$3,$A$3),$B$4,$A$4) | P30: =SUBSTITUTE(SUBSTITUTE(SUBSTITUTE(K30,$B$2,$A$2),$B$3,$A$3),$B$4,$A$4) | Q30: =IF(LEFT(N30,3)="xsd","Data","Object") -> Object | R30: =IF($A30="Implicit","",$F$1&B30&$F$1) -> "Embedded" | S30: =IF($A30="Implicit","",$F$1&L30&$F$1) -> "ActivitySequence" | T30: =IF($A30="Implicit","",$F$1&M30&$F$1) -> "sequenceNumber" | U30: =IF($A30="Implicit","",$F$1&E30&$F$1) -> "" | V30: =IF($A30="Implicit","",$F$1&N30&$F$1) -> "string" | W30: =IF($A30="Implicit","",COUNTIFS($C$8:C30,C30,$A$8:A30,"Explicit")) -> 2 | X30: =IF($A30="Implicit","",$F$1&SUBSTITUTE(IF(I30=0,"",I30),",",";")&$F$1) -> "Embedded object to create a sequence of Activities in the context of a Service" | Y30: =IF($A30="Implicit","",$F$1&SUBSTITUTE(IF(J30=0,"",J30),",",";")&$F$1) -> "Short text to detail sequence number (alphanumeric)" | Z30: =IF($A30="Implicit","",$F$1&IF(G30=1,"false","true")&$F$1) -> "false" | AA30: =IF($A30="Implicit","",$F$1&IF(OR(E30="Enum",E30="CodeList"),"true","false")&$F$1) -> "false" | AB30: =IF($A30="Implicit","",$F$1&P30&$F$1) -> "" | AC30: =IF($A30="Implicit","",$F$1&C30&$F$1) -> "https://onerecord.iata.org/ns/cargo#ActivitySequence" | AD30: =IF($A30="Implicit","",$F$1&D30&$F$1) -> "https://onerecord.iata.org/ns/cargo#sequenceNumber" | AE30: =IF($A30="Implicit","",$F$1&F30&$F$1) -> "http://www.w3.org/2001/XMLSchema#string" | AF30: =IF(A30="Implicit","",R30&","&S30&","&T30&","&U30&","&V30&","&W30&","&X30&","&Y30&","&Z30&","&AA30&","&AB30&","&AC30&","&AD30&","&AE30) -> "Embedded","ActivitySequence","sequenceNumber","","string",2,"Embedded object to create a sequence of Activities in the context of a Service","Short text to detail sequence number (alphanumeric)","false","false","","https://onerecord.iata.org/ns/cargo#ActivitySequence","https://onerecord.iata.org/ns/cargo#sequenceNumber","http://www.w3.org/2001/XMLSchema#string" | AG30: =IF(Q30="Data","",$F$1&B30&"."&L30&$F$1) -> "Embedded.ActivitySequence" | AH30: =IF(Q30="Data","",$F$1&M30&$F$1) -> "sequenceNumber" | AI30: =IF(Q30="Data","",$F$1&E30&"."&N30&$F$1) -> ".string" | AJ30: =IF(Q30="Data","",$F$1&O30&$F$1) -> "" | AK30: =IF(Q30="Data","",$F$1&IF(G30=1,"hasOne","hasMany")&$F$1) -> "hasOne" | AL30: =IF(Q30="Data","",AG30&","&AH30&","&AI30&","&AJ30&","&AK30) -> "Embedded.ActivitySequence","sequenceNumber",".string","","hasOne" | AN30: =COUNTIF(View_conceptual!G:G,L30) -> 1 | AO30: =COUNTIF(View_conceptual!H:H,L30)+COUNTIF(View_conceptual!I:I,N30) -> 1 | AQ30: =IF(AN30=1,AF30,"") -> "Embedded","ActivitySequence","sequenceNumber","","string",2,"Embedded object to create a sequence of Activities in the context of a Service","Short text to detail sequence number (alphanumeric)","false","false","","https://onerecord.iata.org/ns/cargo#ActivitySequence","https://onerecord.iata.org/ns/cargo#sequenceNumber","http://www.w3.org/2001/XMLSchema#string" | AR30: =IF(AO30=2,AL30,"") | AT30: =COUNTIF(View_full!G:G,L30) -> 1 | AU30: =COUNTIF(View_full!H:H,L30)+COUNTIF(View_full!I:I,N30) -> 1 | AV30: =COUNTIFS(Property_Manual!$A$2:$A$1206,Raw!L30,Property_Manual!$B$2:$B$1206,Raw!M30,Property_Manual!$C$2:$C$1206,Raw!N30,Property_Manual!$D$2:$D$1206,Raw!O30,Property_Manual!$F$2:$F$1206,"x") -> 0 | AW30: =IF(AT30=1,AF30,"") -> "Embedded","ActivitySequence","sequenceNumber","","string",2,"Embedded object to create a sequence of Activities in the context of a Service","Short text to detail sequence number (alphanumeric)","false","false","","https://onerecord.iata.org/ns/cargo#ActivitySequence","https://onerecord.iata.org/ns/cargo#sequenceNumber","http://www.w3.org/2001/XMLSchema#string" | AX30: =IF(AU30=2,AL30,"") | AY30: =IF(AV30=1,AL30,"")
A31: Explicit | B31: Agent | C31: https://onerecord.iata.org/ns/cargo#Actor | D31: https://onerecord.iata.org/ns/cargo#associatedOrganization | E31: Agent | F31: https://onerecord.iata.org/ns/cargo#Organization | G31: 1 | H31: https://onerecord.iata.org/ns/cargo#contactPersons | I31: Superclass: Actors are Persons or entities acting like a single person | J31: Reference to the Organization the Actor is associated with | K31: https://onerecord.iata.org/ns/cargo#Carrier|https://onerecord.iata.org/ns/cargo#Company|https://onerecord.iata.org/ns/cargo#PublicAuthority | L31: =SUBSTITUTE(SUBSTITUTE(SUBSTITUTE(C31,$B$2,$A$2),$B$3,$A$3),$B$4,$A$4) -> Actor | M31: =SUBSTITUTE(SUBSTITUTE(SUBSTITUTE(D31,$B$2,$A$2),$B$3,$A$3),$A$4,$B$4) -> associatedOrganization | N31: =SUBSTITUTE(SUBSTITUTE(SUBSTITUTE(F31,$B$2,$A$2),$B$3,$A$3),$B$4,$A$4) -> Organization | O31: =SUBSTITUTE(SUBSTITUTE(SUBSTITUTE(H31,$B$2,$A$2),$B$3,$A$3),$B$4,$A$4) -> contactPersons | P31: =SUBSTITUTE(SUBSTITUTE(SUBSTITUTE(K31,$B$2,$A$2),$B$3,$A$3),$B$4,$A$4) -> Carrier|Company|PublicAuthority | Q31: =IF(LEFT(N31,3)="xsd","Data","Object") -> Object | R31: =IF($A31="Implicit","",$F$1&B31&$F$1) -> "Agent" | S31: =IF($A31="Implicit","",$F$1&L31&$F$1) -> "Actor" | T31: =IF($A31="Implicit","",$F$1&M31&$F$1) -> "associatedOrganization" | U31: =IF($A31="Implicit","",$F$1&E31&$F$1) -> "Agent" | V31: =IF($A31="Implicit","",$F$1&N31&$F$1) -> "Organization" | W31: =IF($A31="Implicit","",COUNTIFS($C$8:C31,C31,$A$8:A31,"Explicit")) -> 1 | X31: =IF($A31="Implicit","",$F$1&SUBSTITUTE(IF(I31=0,"",I31),",",";")&$F$1) -> "Superclass: Actors are Persons or entities acting like a single person" | Y31: =IF($A31="Implicit","",$F$1&SUBSTITUTE(IF(J31=0,"",J31),",",";")&$F$1) -> "Reference to the Organization the Actor is associated with" | Z31: =IF($A31="Implicit","",$F$1&IF(G31=1,"false","true")&$F$1) -> "false" | AA31: =IF($A31="Implicit","",$F$1&IF(OR(E31="Enum",E31="CodeList"),"true","false")&$F$1) -> "false" | AB31: =IF($A31="Implicit","",$F$1&P31&$F$1) -> "Carrier|Company|PublicAuthority" | AC31: =IF($A31="Implicit","",$F$1&C31&$F$1) -> "https://onerecord.iata.org/ns/cargo#Actor" | AD31: =IF($A31="Implicit","",$F$1&D31&$F$1) -> "https://onerecord.iata.org/ns/cargo#associatedOrganization" | AE31: =IF($A31="Implicit","",$F$1&F31&$F$1) -> "https://onerecord.iata.org/ns/cargo#Organization" | AF31: =IF(A31="Implicit","",R31&","&S31&","&T31&","&U31&","&V31&","&W31&","&X31&","&Y31&","&Z31&","&AA31&","&AB31&","&AC31&","&AD31&","&AE31) -> "Agent","Actor","associatedOrganization","Agent","Organization",1,"Superclass: Actors are Persons or entities acting like a single person","Reference to the Organization the Actor is associated with","false","false","Carrier|Company|PublicAuthority","https://onerecord.iata.org/ns/cargo#Actor","https://onerecord.iata.org/ns/cargo#associatedOrganization","https://onerecord.iata.org/ns/cargo#Organization" | AG31: =IF(Q31="Data","",$F$1&B31&"."&L31&$F$1) -> "Agent.Actor" | AH31: =IF(Q31="Data","",$F$1&M31&$F$1) -> "associatedOrganization" | AI31: =IF(Q31="Data","",$F$1&E31&"."&N31&$F$1) -> "Agent.Organization" | AJ31: =IF(Q31="Data","",$F$1&O31&$F$1) -> "contactPersons" | AK31: =IF(Q31="Data","",$F$1&IF(G31=1,"hasOne","hasMany")&$F$1) -> "hasOne" | AL31: =IF(Q31="Data","",AG31&","&AH31&","&AI31&","&AJ31&","&AK31) -> "Agent.Actor","associatedOrganization","Agent.Organization","contactPersons","hasOne" | AN31: =COUNTIF(View_conceptual!G:G,L31) -> 0 | AO31: =COUNTIF(View_conceptual!H:H,L31)+COUNTIF(View_conceptual!I:I,N31) -> 0 | AQ31: =IF(AN31=1,AF31,"") | AR31: =IF(AO31=2,AL31,"") | AT31: =COUNTIF(View_full!G:G,L31) -> 1 | AU31: =COUNTIF(View_full!H:H,L31)+COUNTIF(View_full!I:I,N31) -> 0 | AV31: =COUNTIFS(Property_Manual!$A$2:$A$1206,Raw!L31,Property_Manual!$B$2:$B$1206,Raw!M31,Property_Manual!$C$2:$C$1206,Raw!N31,Property_Manual!$D$2:$D$1206,Raw!O31,Property_Manual!$F$2:$F$1206,"x") -> 0 | AW31: =IF(AT31=1,AF31,"") -> "Agent","Actor","associatedOrganization","Agent","Organization",1,"Superclass: Actors are Persons or entities acting like a single person","Reference to the Organization the Actor is associated with","false","false","Carrier|Company|PublicAuthority","https://onerecord.iata.org/ns/cargo#Actor","https://onerecord.iata.org/ns/cargo#associatedOrganization","https://onerecord.iata.org/ns/cargo#Organization" | AX31: =IF(AU31=2,AL31,"") | AY31: =IF(AV31=1,AL31,"")
A32: Implicit | B32: Agent | C32: https://onerecord.iata.org/ns/cargo#Actor | D32: https://onerecord.iata.org/ns/cargo#associatedOrganization | E32: Agent | F32: https://onerecord.iata.org/ns/cargo#Organization | G32: 1 | H32: https://onerecord.iata.org/ns/cargo#contactPersons | I32: Superclass: Actors are Persons or entities acting like a single person | J32: Reference to the Organization the Actor is associated with | K32: https://onerecord.iata.org/ns/cargo#Carrier|https://onerecord.iata.org/ns/cargo#Company|https://onerecord.iata.org/ns/cargo#PublicAuthority | L32: =SUBSTITUTE(SUBSTITUTE(SUBSTITUTE(C32,$B$2,$A$2),$B$3,$A$3),$B$4,$A$4) -> Actor | M32: =SUBSTITUTE(SUBSTITUTE(SUBSTITUTE(D32,$B$2,$A$2),$B$3,$A$3),$A$4,$B$4) -> associatedOrganization | N32: =SUBSTITUTE(SUBSTITUTE(SUBSTITUTE(F32,$B$2,$A$2),$B$3,$A$3),$B$4,$A$4) -> Organization | O32: =SUBSTITUTE(SUBSTITUTE(SUBSTITUTE(H32,$B$2,$A$2),$B$3,$A$3),$B$4,$A$4) -> contactPersons | P32: =SUBSTITUTE(SUBSTITUTE(SUBSTITUTE(K32,$B$2,$A$2),$B$3,$A$3),$B$4,$A$4) -> Carrier|Company|PublicAuthority | Q32: =IF(LEFT(N32,3)="xsd","Data","Object") -> Object | R32: =IF($A32="Implicit","",$F$1&B32&$F$1) | S32: =IF($A32="Implicit","",$F$1&L32&$F$1) | T32: =IF($A32="Implicit","",$F$1&M32&$F$1) | U32: =IF($A32="Implicit","",$F$1&E32&$F$1) | V32: =IF($A32="Implicit","",$F$1&N32&$F$1) | W32: =IF($A32="Implicit","",COUNTIFS($C$8:C32,C32,$A$8:A32,"Explicit")) | X32: =IF($A32="Implicit","",$F$1&SUBSTITUTE(IF(I32=0,"",I32),",",";")&$F$1) | Y32: =IF($A32="Implicit","",$F$1&SUBSTITUTE(IF(J32=0,"",J32),",",";")&$F$1) | Z32: =IF($A32="Implicit","",$F$1&IF(G32=1,"false","true")&$F$1) | AA32: =IF($A32="Implicit","",$F$1&IF(OR(E32="Enum",E32="CodeList"),"true","false")&$F$1) | AB32: =IF($A32="Implicit","",$F$1&P32&$F$1) | AC32: =IF($A32="Implicit","",$F$1&C32&$F$1) | AD32: =IF($A32="Implicit","",$F$1&D32&$F$1) | AE32: =IF($A32="Implicit","",$F$1&F32&$F$1) | AF32: =IF(A32="Implicit","",R32&","&S32&","&T32&","&U32&","&V32&","&W32&","&X32&","&Y32&","&Z32&","&AA32&","&AB32&","&AC32&","&AD32&","&AE32) | AG32: =IF(Q32="Data","",$F$1&B32&"."&L32&$F$1) -> "Agent.Actor" | AH32: =IF(Q32="Data","",$F$1&M32&$F$1) -> "associatedOrganization" | AI32: =IF(Q32="Data","",$F$1&E32&"."&N32&$F$1) -> "Agent.Organization" | AJ32: =IF(Q32="Data","",$F$1&O32&$F$1) -> "contactPersons" | AK32: =IF(Q32="Data","",$F$1&IF(G32=1,"hasOne","hasMany")&$F$1) -> "hasOne" | AL32: =IF(Q32="Data","",AG32&","&AH32&","&AI32&","&AJ32&","&AK32) -> "Agent.Actor","associatedOrganization","Agent.Organization","contactPersons","hasOne" | AN32: =COUNTIF(View_conceptual!G:G,L32) -> 0 | AO32: =COUNTIF(View_conceptual!H:H,L32)+COUNTIF(View_conceptual!I:I,N32) -> 0 | AQ32: =IF(AN32=1,AF32,"") | AR32: =IF(AO32=2,AL32,"") | AT32: =COUNTIF(View_full!G:G,L32) -> 1 | AU32: =COUNTIF(View_full!H:H,L32)+COUNTIF(View_full!I:I,N32) -> 0 | AV32: =COUNTIFS(Property_Manual!$A$2:$A$1206,Raw!L32,Property_Manual!$B$2:$B$1206,Raw!M32,Property_Manual!$C$2:$C$1206,Raw!N32,Property_Manual!$D$2:$D$1206,Raw!O32,Property_Manual!$F$2:$F$1206,"x") -> 0 | AW32: =IF(AT32=1,AF32,"") | AX32: =IF(AU32=2,AL32,"") | AY32: =IF(AV32=1,AL32,"")
A33: Implicit | B33: Agent | C33: https://onerecord.iata.org/ns/cargo#Actor | D33: https://onerecord.iata.org/ns/cargo#associatedOrganization | E33: Agent | F33: https://onerecord.iata.org/ns/cargo#Carrier | G33: 1 | H33: https://onerecord.iata.org/ns/cargo#contactPersons | I33: Superclass: Actors are Persons or entities acting like a single person | J33: Reference to the Organization the Actor is associated with | L33: =SUBSTITUTE(SUBSTITUTE(SUBSTITUTE(C33,$B$2,$A$2),$B$3,$A$3),$B$4,$A$4) -> Actor | M33: =SUBSTITUTE(SUBSTITUTE(SUBSTITUTE(D33,$B$2,$A$2),$B$3,$A$3),$A$4,$B$4) -> associatedOrganization | N33: =SUBSTITUTE(SUBSTITUTE(SUBSTITUTE(F33,$B$2,$A$2),$B$3,$A$3),$B$4,$A$4) -> Carrier | O33: =SUBSTITUTE(SUBSTITUTE(SUBSTITUTE(H33,$B$2,$A$2),$B$3,$A$3),$B$4,$A$4) -> contactPersons | P33: =SUBSTITUTE(SUBSTITUTE(SUBSTITUTE(K33,$B$2,$A$2),$B$3,$A$3),$B$4,$A$4) | Q33: =IF(LEFT(N33,3)="xsd","Data","Object") -> Object | R33: =IF($A33="Implicit","",$F$1&B33&$F$1) | S33: =IF($A33="Implicit","",$F$1&L33&$F$1) | T33: =IF($A33="Implicit","",$F$1&M33&$F$1) | U33: =IF($A33="Implicit","",$F$1&E33&$F$1) | V33: =IF($A33="Implicit","",$F$1&N33&$F$1) | W33: =IF($A33="Implicit","",COUNTIFS($C$8:C33,C33,$A$8:A33,"Explicit")) | X33: =IF($A33="Implicit","",$F$1&SUBSTITUTE(IF(I33=0,"",I33),",",";")&$F$1) | Y33: =IF($A33="Implicit","",$F$1&SUBSTITUTE(IF(J33=0,"",J33),",",";")&$F$1) | Z33: =IF($A33="Implicit","",$F$1&IF(G33=1,"false","true")&$F$1) | AA33: =IF($A33="Implicit","",$F$1&IF(OR(E33="Enum",E33="CodeList"),"true","false")&$F$1) | AB33: =IF($A33="Implicit","",$F$1&P33&$F$1) | AC33: =IF($A33="Implicit","",$F$1&C33&$F$1) | AD33: =IF($A33="Implicit","",$F$1&D33&$F$1) | AE33: =IF($A33="Implicit","",$F$1&F33&$F$1) | AF33: =IF(A33="Implicit","",R33&","&S33&","&T33&","&U33&","&V33&","&W33&","&X33&","&Y33&","&Z33&","&AA33&","&AB33&","&AC33&","&AD33&","&AE33) | AG33: =IF(Q33="Data","",$F$1&B33&"."&L33&$F$1) -> "Agent.Actor" | AH33: =IF(Q33="Data","",$F$1&M33&$F$1) -> "associatedOrganization" | AI33: =IF(Q33="Data","",$F$1&E33&"."&N33&$F$1) -> "Agent.Carrier" | AJ33: =IF(Q33="Data","",$F$1&O33&$F$1) -> "contactPersons" | AK33: =IF(Q33="Data","",$F$1&IF(G33=1,"hasOne","hasMany")&$F$1) -> "hasOne" | AL33: =IF(Q33="Data","",AG33&","&AH33&","&AI33&","&AJ33&","&AK33) -> "Agent.Actor","associatedOrganization","Agent.Carrier","contactPersons","hasOne" | AN33: =COUNTIF(View_conceptual!G:G,L33) -> 0 | AO33: =COUNTIF(View_conceptual!H:H,L33)+COUNTIF(View_conceptual!I:I,N33) -> 0 | AQ33: =IF(AN33=1,AF33,"") | AR33: =IF(AO33=2,AL33,"") | AT33: =COUNTIF(View_full!G:G,L33) -> 1 | AU33: =COUNTIF(View_full!H:H,L33)+COUNTIF(View_full!I:I,N33) -> 0 | AV33: =COUNTIFS(Property_Manual!$A$2:$A$1206,Raw!L33,Property_Manual!$B$2:$B$1206,Raw!M33,Property_Manual!$C$2:$C$1206,Raw!N33,Property_Manual!$D$2:$D$1206,Raw!O33,Property_Manual!$F$2:$F$1206,"x") -> 0 | AW33: =IF(AT33=1,AF33,"") | AX33: =IF(AU33=2,AL33,"") | AY33: =IF(AV33=1,AL33,"")
A34: Implicit | B34: Agent | C34: https://onerecord.iata.org/ns/cargo#Actor | D34: https://onerecord.iata.org/ns/cargo#associatedOrganization | E34: Agent | F34: https://onerecord.iata.org/ns/cargo#Company | G34: 1 | H34: https://onerecord.iata.org/ns/cargo#contactPersons | I34: Superclass: Actors are Persons or entities acting like a single person | J34: Reference to the Organization the Actor is associated with | K34: https://onerecord.iata.org/ns/cargo#Carrier | L34: =SUBSTITUTE(SUBSTITUTE(SUBSTITUTE(C34,$B$2,$A$2),$B$3,$A$3),$B$4,$A$4) -> Actor | M34: =SUBSTITUTE(SUBSTITUTE(SUBSTITUTE(D34,$B$2,$A$2),$B$3,$A$3),$A$4,$B$4) -> associatedOrganization | N34: =SUBSTITUTE(SUBSTITUTE(SUBSTITUTE(F34,$B$2,$A$2),$B$3,$A$3),$B$4,$A$4) -> Company | O34: =SUBSTITUTE(SUBSTITUTE(SUBSTITUTE(H34,$B$2,$A$2),$B$3,$A$3),$B$4,$A$4) -> contactPersons | P34: =SUBSTITUTE(SUBSTITUTE(SUBSTITUTE(K34,$B$2,$A$2),$B$3,$A$3),$B$4,$A$4) -> Carrier | Q34: =IF(LEFT(N34,3)="xsd","Data","Object") -> Object | R34: =IF($A34="Implicit","",$F$1&B34&$F$1) | S34: =IF($A34="Implicit","",$F$1&L34&$F$1) | T34: =IF($A34="Implicit","",$F$1&M34&$F$1) | U34: =IF($A34="Implicit","",$F$1&E34&$F$1) | V34: =IF($A34="Implicit","",$F$1&N34&$F$1) | W34: =IF($A34="Implicit","",COUNTIFS($C$8:C34,C34,$A$8:A34,"Explicit")) | X34: =IF($A34="Implicit","",$F$1&SUBSTITUTE(IF(I34=0,"",I34),",",";")&$F$1) | Y34: =IF($A34="Implicit","",$F$1&SUBSTITUTE(IF(J34=0,"",J34),",",";")&$F$1) | Z34: =IF($A34="Implicit","",$F$1&IF(G34=1,"false","true")&$F$1) | AA34: =IF($A34="Implicit","",$F$1&IF(OR(E34="Enum",E34="CodeList"),"true","false")&$F$1) | AB34: =IF($A34="Implicit","",$F$1&P34&$F$1) | AC34: =IF($A34="Implicit","",$F$1&C34&$F$1) | AD34: =IF($A34="Implicit","",$F$1&D34&$F$1) | AE34: =IF($A34="Implicit","",$F$1&F34&$F$1) | AF34: =IF(A34="Implicit","",R34&","&S34&","&T34&","&U34&","&V34&","&W34&","&X34&","&Y34&","&Z34&","&AA34&","&AB34&","&AC34&","&AD34&","&AE34) | AG34: =IF(Q34="Data","",$F$1&B34&"."&L34&$F$1) -> "Agent.Actor" | AH34: =IF(Q34="Data","",$F$1&M34&$F$1) -> "associatedOrganization" | AI34: =IF(Q34="Data","",$F$1&E34&"."&N34&$F$1) -> "Agent.Company" | AJ34: =IF(Q34="Data","",$F$1&O34&$F$1) -> "contactPersons" | AK34: =IF(Q34="Data","",$F$1&IF(G34=1,"hasOne","hasMany")&$F$1) -> "hasOne" | AL34: =IF(Q34="Data","",AG34&","&AH34&","&AI34&","&AJ34&","&AK34) -> "Agent.Actor","associatedOrganization","Agent.Company","contactPersons","hasOne" | AN34: =COUNTIF(View_conceptual!G:G,L34) -> 0 | AO34: =COUNTIF(View_conceptual!H:H,L34)+COUNTIF(View_conceptual!I:I,N34) -> 0 | AQ34: =IF(AN34=1,AF34,"") | AR34: =IF(AO34=2,AL34,"") | AT34: =COUNTIF(View_full!G:G,L34) -> 1 | AU34: =COUNTIF(View_full!H:H,L34)+COUNTIF(View_full!I:I,N34) -> 0 | AV34: =COUNTIFS(Property_Manual!$A$2:$A$1206,Raw!L34,Property_Manual!$B$2:$B$1206,Raw!M34,Property_Manual!$C$2:$C$1206,Raw!N34,Property_Manual!$D$2:$D$1206,Raw!O34,Property_Manual!$F$2:$F$1206,"x") -> 0 | AW34: =IF(AT34=1,AF34,"") | AX34: =IF(AU34=2,AL34,"") | AY34: =IF(AV34=1,AL34,"")
A35: Implicit | B35: Agent | C35: https://onerecord.iata.org/ns/cargo#Actor | D35: https://onerecord.iata.org/ns/cargo#associatedOrganization | E35: Agent | F35: https://onerecord.iata.org/ns/cargo#PublicAuthority | G35: 1 | H35: https://onerecord.iata.org/ns/cargo#contactPersons | I35: Superclass: Actors are Persons or entities acting like a single person | J35: Reference to the Organization the Actor is associated with | L35: =SUBSTITUTE(SUBSTITUTE(SUBSTITUTE(C35,$B$2,$A$2),$B$3,$A$3),$B$4,$A$4) -> Actor | M35: =SUBSTITUTE(SUBSTITUTE(SUBSTITUTE(D35,$B$2,$A$2),$B$3,$A$3),$A$4,$B$4) -> associatedOrganization | N35: =SUBSTITUTE(SUBSTITUTE(SUBSTITUTE(F35,$B$2,$A$2),$B$3,$A$3),$B$4,$A$4) -> PublicAuthority | O35: =SUBSTITUTE(SUBSTITUTE(SUBSTITUTE(H35,$B$2,$A$2),$B$3,$A$3),$B$4,$A$4) -> contactPersons | P35: =SUBSTITUTE(SUBSTITUTE(SUBSTITUTE(K35,$B$2,$A$2),$B$3,$A$3),$B$4,$A$4) | Q35: =IF(LEFT(N35,3)="xsd","Data","Object") -> Object | R35: =IF($A35="Implicit","",$F$1&B35&$F$1) | S35: =IF($A35="Implicit","",$F$1&L35&$F$1) | T35: =IF($A35="Implicit","",$F$1&M35&$F$1) | U35: =IF($A35="Implicit","",$F$1&E35&$F$1) | V35: =IF($A35="Implicit","",$F$1&N35&$F$1) | W35: =IF($A35="Implicit","",COUNTIFS($C$8:C35,C35,$A$8:A35,"Explicit")) | X35: =IF($A35="Implicit","",$F$1&SUBSTITUTE(IF(I35=0,"",I35),",",";")&$F$1) | Y35: =IF($A35="Implicit","",$F$1&SUBSTITUTE(IF(J35=0,"",J35),",",";")&$F$1) | Z35: =IF($A35="Implicit","",$F$1&IF(G35=1,"false","true")&$F$1) | AA35: =IF($A35="Implicit","",$F$1&IF(OR(E35="Enum",E35="CodeList"),"true","false")&$F$1) | AB35: =IF($A35="Implicit","",$F$1&P35&$F$1) | AC35: =IF($A35="Implicit","",$F$1&C35&$F$1) | AD35: =IF($A35="Implicit","",$F$1&D35&$F$1) | AE35: =IF($A35="Implicit","",$F$1&F35&$F$1) | AF35: =IF(A35="Implicit","",R35&","&S35&","&T35&","&U35&","&V35&","&W35&","&X35&","&Y35&","&Z35&","&AA35&","&AB35&","&AC35&","&AD35&","&AE35) | AG35: =IF(Q35="Data","",$F$1&B35&"."&L35&$F$1) -> "Agent.Actor" | AH35: =IF(Q35="Data","",$F$1&M35&$F$1) -> "associatedOrganization" | AI35: =IF(Q35="Data","",$F$1&E35&"."&N35&$F$1) -> "Agent.PublicAuthority" | AJ35: =IF(Q35="Data","",$F$1&O35&$F$1) -> "contactPersons" | AK35: =IF(Q35="Data","",$F$1&IF(G35=1,"hasOne","hasMany")&$F$1) -> "hasOne" | AL35: =IF(Q35="Data","",AG35&","&AH35&","&AI35&","&AJ35&","&AK35) -> "Agent.Actor","associatedOrganization","Agent.PublicAuthority","contactPersons","hasOne" | AN35: =COUNTIF(View_conceptual!G:G,L35) -> 0 | AO35: =COUNTIF(View_conceptual!H:H,L35)+COUNTIF(View_conceptual!I:I,N35) -> 0 | AQ35: =IF(AN35=1,AF35,"") | AR35: =IF(AO35=2,AL35,"") | AT35: =COUNTIF(View_full!G:G,L35) -> 1 | AU35: =COUNTIF(View_full!H:H,L35)+COUNTIF(View_full!I:I,N35) -> 0 | AV35: =COUNTIFS(Property_Manual!$A$2:$A$1206,Raw!L35,Property_Manual!$B$2:$B$1206,Raw!M35,Property_Manual!$C$2:$C$1206,Raw!N35,Property_Manual!$D$2:$D$1206,Raw!O35,Property_Manual!$F$2:$F$1206,"x") -> 0 | AW35: =IF(AT35=1,AF35,"") | AX35: =IF(AU35=2,AL35,"") | AY35: =IF(AV35=1,AL35,"")
A36: Explicit | B36: Agent | C36: https://onerecord.iata.org/ns/cargo#Actor | D36: https://onerecord.iata.org/ns/cargo#checks | E36: Action | F36: https://onerecord.iata.org/ns/cargo#Check | H36: https://onerecord.iata.org/ns/cargo#checkedObject | I36: Superclass: Actors are Persons or entities acting like a single person | J36: References to the CheckActions performed on the object | L36: =SUBSTITUTE(SUBSTITUTE(SUBSTITUTE(C36,$B$2,$A$2),$B$3,$A$3),$B$4,$A$4) -> Actor | M36: =SUBSTITUTE(SUBSTITUTE(SUBSTITUTE(D36,$B$2,$A$2),$B$3,$A$3),$A$4,$B$4) -> checks | N36: =SUBSTITUTE(SUBSTITUTE(SUBSTITUTE(F36,$B$2,$A$2),$B$3,$A$3),$B$4,$A$4) -> Check | O36: =SUBSTITUTE(SUBSTITUTE(SUBSTITUTE(H36,$B$2,$A$2),$B$3,$A$3),$B$4,$A$4) -> checkedObject | P36: =SUBSTITUTE(SUBSTITUTE(SUBSTITUTE(K36,$B$2,$A$2),$B$3,$A$3),$B$4,$A$4) | Q36: =IF(LEFT(N36,3)="xsd","Data","Object") -> Object | R36: =IF($A36="Implicit","",$F$1&B36&$F$1) -> "Agent" | S36: =IF($A36="Implicit","",$F$1&L36&$F$1) -> "Actor" | T36: =IF($A36="Implicit","",$F$1&M36&$F$1) -> "checks" | U36: =IF($A36="Implicit","",$F$1&E36&$F$1) -> "Action" | V36: =IF($A36="Implicit","",$F$1&N36&$F$1) -> "Check" | W36: =IF($A36="Implicit","",COUNTIFS($C$8:C36,C36,$A$8:A36,"Explicit")) -> 2 | X36: =IF($A36="Implicit","",$F$1&SUBSTITUTE(IF(I36=0,"",I36),",",";")&$F$1) -> "Superclass: Actors are Persons or entities acting like a single person" | Y36: =IF($A36="Implicit","",$F$1&SUBSTITUTE(IF(J36=0,"",J36),",",";")&$F$1) -> "References to the CheckActions performed on the object" | Z36: =IF($A36="Implicit","",$F$1&IF(G36=1,"false","true")&$F$1) -> "true" | AA36: =IF($A36="Implicit","",$F$1&IF(OR(E36="Enum",E36="CodeList"),"true","false")&$F$1) -> "false" | AB36: =IF($A36="Implicit","",$F$1&P36&$F$1) -> "" | AC36: =IF($A36="Implicit","",$F$1&C36&$F$1) -> "https://onerecord.iata.org/ns/cargo#Actor" | AD36: =IF($A36="Implicit","",$F$1&D36&$F$1) -> "https://onerecord.iata.org/ns/cargo#checks" | AE36: =IF($A36="Implicit","",$F$1&F36&$F$1) -> "https://onerecord.iata.org/ns/cargo#Check" | AF36: =IF(A36="Implicit","",R36&","&S36&","&T36&","&U36&","&V36&","&W36&","&X36&","&Y36&","&Z36&","&AA36&","&AB36&","&AC36&","&AD36&","&AE36) -> "Agent","Actor","checks","Action","Check",2,"Superclass: Actors are Persons or entities acting like a single person","References to the CheckActions performed on the object","true","false","","https://onerecord.iata.org/ns/cargo#Actor","https://onerecord.iata.org/ns/cargo#checks","https://onerecord.iata.org/ns/cargo#Check" | AG36: =IF(Q36="Data","",$F$1&B36&"."&L36&$F$1) -> "Agent.Actor" | AH36: =IF(Q36="Data","",$F$1&M36&$F$1) -> "checks" | AI36: =IF(Q36="Data","",$F$1&E36&"."&N36&$F$1) -> "Action.Check" | AJ36: =IF(Q36="Data","",$F$1&O36&$F$1) -> "checkedObject" | AK36: =IF(Q36="Data","",$F$1&IF(G36=1,"hasOne","hasMany")&$F$1) -> "hasMany" | AL36: =IF(Q36="Data","",AG36&","&AH36&","&AI36&","&AJ36&","&AK36) -> "Agent.Actor","checks","Action.Check","checkedObject","hasMany" | AN36: =COUNTIF(View_conceptual!G:G,L36) -> 0 | AO36: =COUNTIF(View_conceptual!H:H,L36)+COUNTIF(View_conceptual!I:I,N36) -> 0 | AQ36: =IF(AN36=1,AF36,"") | AR36: =IF(AO36=2,AL36,"") | AT36: =COUNTIF(View_full!G:G,L36) -> 1 | AU36: =COUNTIF(View_full!H:H,L36)+COUNTIF(View_full!I:I,N36) -> 0 | AV36: =COUNTIFS(Property_Manual!$A$2:$A$1206,Raw!L36,Property_Manual!$B$2:$B$1206,Raw!M36,Property_Manual!$C$2:$C$1206,Raw!N36,Property_Manual!$D$2:$D$1206,Raw!O36,Property_Manual!$F$2:$F$1206,"x") -> 0 | AW36: =IF(AT36=1,AF36,"") -> "Agent","Actor","checks","Action","Check",2,"Superclass: Actors are Persons or entities acting like a single person","References to the CheckActions performed on the object","true","false","","https://onerecord.iata.org/ns/cargo#Actor","https://onerecord.iata.org/ns/cargo#checks","https://onerecord.iata.org/ns/cargo#Check" | AX36: =IF(AU36=2,AL36,"") | AY36: =IF(AV36=1,AL36,"")
A37: Explicit | B37: Agent | C37: https://onerecord.iata.org/ns/cargo#Actor | D37: https://onerecord.iata.org/ns/cargo#externalReferences | E37: Common | F37: https://onerecord.iata.org/ns/cargo#ExternalReference | H37: https://onerecord.iata.org/ns/cargo#referenceForObjects | I37: Superclass: Actors are Persons or entities acting like a single person | J37: References to all associated ExternalReferences | L37: =SUBSTITUTE(SUBSTITUTE(SUBSTITUTE(C37,$B$2,$A$2),$B$3,$A$3),$B$4,$A$4) -> Actor | M37: =SUBSTITUTE(SUBSTITUTE(SUBSTITUTE(D37,$B$2,$A$2),$B$3,$A$3),$A$4,$B$4) -> externalReferences | N37: =SUBSTITUTE(SUBSTITUTE(SUBSTITUTE(F37,$B$2,$A$2),$B$3,$A$3),$B$4,$A$4) -> ExternalReference | O37: =SUBSTITUTE(SUBSTITUTE(SUBSTITUTE(H37,$B$2,$A$2),$B$3,$A$3),$B$4,$A$4) -> referenceForObjects | P37: =SUBSTITUTE(SUBSTITUTE(SUBSTITUTE(K37,$B$2,$A$2),$B$3,$A$3),$B$4,$A$4) | Q37: =IF(LEFT(N37,3)="xsd","Data","Object") -> Object | R37: =IF($A37="Implicit","",$F$1&B37&$F$1) -> "Agent" | S37: =IF($A37="Implicit","",$F$1&L37&$F$1) -> "Actor" | T37: =IF($A37="Implicit","",$F$1&M37&$F$1) -> "externalReferences" | U37: =IF($A37="Implicit","",$F$1&E37&$F$1) -> "Common" | V37: =IF($A37="Implicit","",$F$1&N37&$F$1) -> "ExternalReference" | W37: =IF($A37="Implicit","",COUNTIFS($C$8:C37,C37,$A$8:A37,"Explicit")) -> 3 | X37: =IF($A37="Implicit","",$F$1&SUBSTITUTE(IF(I37=0,"",I37),",",";")&$F$1) -> "Superclass: Actors are Persons or entities acting like a single person" | Y37: =IF($A37="Implicit","",$F$1&SUBSTITUTE(IF(J37=0,"",J37),",",";")&$F$1) -> "References to all associated ExternalReferences" | Z37: =IF($A37="Implicit","",$F$1&IF(G37=1,"false","true")&$F$1) -> "true" | AA37: =IF($A37="Implicit","",$F$1&IF(OR(E37="Enum",E37="CodeList"),"true","false")&$F$1) -> "false" | AB37: =IF($A37="Implicit","",$F$1&P37&$F$1) -> "" | AC37: =IF($A37="Implicit","",$F$1&C37&$F$1) -> "https://onerecord.iata.org/ns/cargo#Actor" | AD37: =IF($A37="Implicit","",$F$1&D37&$F$1) -> "https://onerecord.iata.org/ns/cargo#externalReferences" | AE37: =IF($A37="Implicit","",$F$1&F37&$F$1) -> "https://onerecord.iata.org/ns/cargo#ExternalReference" | AF37: =IF(A37="Implicit","",R37&","&S37&","&T37&","&U37&","&V37&","&W37&","&X37&","&Y37&","&Z37&","&AA37&","&AB37&","&AC37&","&AD37&","&AE37) -> "Agent","Actor","externalReferences","Common","ExternalReference",3,"Superclass: Actors are Persons or entities acting like a single person","References to all associated ExternalReferences","true","false","","https://onerecord.iata.org/ns/cargo#Actor","https://onerecord.iata.org/ns/cargo#externalReferences","https://onerecord.iata.org/ns/cargo#ExternalReference" | AG37: =IF(Q37="Data","",$F$1&B37&"."&L37&$F$1) -> "Agent.Actor" | AH37: =IF(Q37="Data","",$F$1&M37&$F$1) -> "externalReferences" | AI37: =IF(Q37="Data","",$F$1&E37&"."&N37&$F$1) -> "Common.ExternalReference" | AJ37: =IF(Q37="Data","",$F$1&O37&$F$1) -> "referenceForObjects" | AK37: =IF(Q37="Data","",$F$1&IF(G37=1,"hasOne","hasMany")&$F$1) -> "hasMany" | AL37: =IF(Q37="Data","",AG37&","&AH37&","&AI37&","&AJ37&","&AK37) -> "Agent.Actor","externalReferences","Common.ExternalReference","referenceForObjects","hasMany" | AN37: =COUNTIF(View_conceptual!G:G,L37) -> 0 | AO37: =COUNTIF(View_conceptual!H:H,L37)+COUNTIF(View_conceptual!I:I,N37) -> 0 | AQ37: =IF(AN37=1,AF37,"") | AR37: =IF(AO37=2,AL37,"") | AT37: =COUNTIF(View_full!G:G,L37) -> 1 | AU37: =COUNTIF(View_full!H:H,L37)+COUNTIF(View_full!I:I,N37) -> 0 | AV37: =COUNTIFS(Property_Manual!$A$2:$A$1206,Raw!L37,Property_Manual!$B$2:$B$1206,Raw!M37,Property_Manual!$C$2:$C$1206,Raw!N37,Property_Manual!$D$2:$D$1206,Raw!O37,Property_Manual!$F$2:$F$1206,"x") -> 0 | AW37: =IF(AT37=1,AF37,"") -> "Agent","Actor","externalReferences","Common","ExternalReference",3,"Superclass: Actors are Persons or entities acting like a single person","References to all associated ExternalReferences","true","false","","https://onerecord.iata.org/ns/cargo#Actor","https://onerecord.iata.org/ns/cargo#externalReferences","https://onerecord.iata.org/ns/cargo#ExternalReference" | AX37: =IF(AU37=2,AL37,"") | AY37: =IF(AV37=1,AL37,"")
A38: Implicit | B38: Agent | C38: https://onerecord.iata.org/ns/cargo#Actor | D38: https://onerecord.iata.org/ns/cargo#checks | E38: Action | F38: https://onerecord.iata.org/ns/cargo#Check | H38: https://onerecord.iata.org/ns/cargo#checkedObject | I38: Superclass: Actors are Persons or entities acting like a single person | J38: References to the CheckActions performed on the object | L38: =SUBSTITUTE(SUBSTITUTE(SUBSTITUTE(C38,$B$2,$A$2),$B$3,$A$3),$B$4,$A$4) -> Actor | M38: =SUBSTITUTE(SUBSTITUTE(SUBSTITUTE(D38,$B$2,$A$2),$B$3,$A$3),$A$4,$B$4) -> checks | N38: =SUBSTITUTE(SUBSTITUTE(SUBSTITUTE(F38,$B$2,$A$2),$B$3,$A$3),$B$4,$A$4) -> Check | O38: =SUBSTITUTE(SUBSTITUTE(SUBSTITUTE(H38,$B$2,$A$2),$B$3,$A$3),$B$4,$A$4) -> checkedObject | P38: =SUBSTITUTE(SUBSTITUTE(SUBSTITUTE(K38,$B$2,$A$2),$B$3,$A$3),$B$4,$A$4) | Q38: =IF(LEFT(N38,3)="xsd","Data","Object") -> Object | R38: =IF($A38="Implicit","",$F$1&B38&$F$1) | S38: =IF($A38="Implicit","",$F$1&L38&$F$1) | T38: =IF($A38="Implicit","",$F$1&M38&$F$1) | U38: =IF($A38="Implicit","",$F$1&E38&$F$1) | V38: =IF($A38="Implicit","",$F$1&N38&$F$1) | W38: =IF($A38="Implicit","",COUNTIFS($C$8:C38,C38,$A$8:A38,"Explicit")) | X38: =IF($A38="Implicit","",$F$1&SUBSTITUTE(IF(I38=0,"",I38),",",";")&$F$1) | Y38: =IF($A38="Implicit","",$F$1&SUBSTITUTE(IF(J38=0,"",J38),",",";")&$F$1) | Z38: =IF($A38="Implicit","",$F$1&IF(G38=1,"false","true")&$F$1) | AA38: =IF($A38="Implicit","",$F$1&IF(OR(E38="Enum",E38="CodeList"),"true","false")&$F$1) | AB38: =IF($A38="Implicit","",$F$1&P38&$F$1) | AC38: =IF($A38="Implicit","",$F$1&C38&$F$1) | AD38: =IF($A38="Implicit","",$F$1&D38&$F$1) | AE38: =IF($A38="Implicit","",$F$1&F38&$F$1) | AF38: =IF(A38="Implicit","",R38&","&S38&","&T38&","&U38&","&V38&","&W38&","&X38&","&Y38&","&Z38&","&AA38&","&AB38&","&AC38&","&AD38&","&AE38) | AG38: =IF(Q38="Data","",$F$1&B38&"."&L38&$F$1) -> "Agent.Actor" | AH38: =IF(Q38="Data","",$F$1&M38&$F$1) -> "checks" | AI38: =IF(Q38="Data","",$F$1&E38&"."&N38&$F$1) -> "Action.Check" | AJ38: =IF(Q38="Data","",$F$1&O38&$F$1) -> "checkedObject" | AK38: =IF(Q38="Data","",$F$1&IF(G38=1,"hasOne","hasMany")&$F$1) -> "hasMany" | AL38: =IF(Q38="Data","",AG38&","&AH38&","&AI38&","&AJ38&","&AK38) -> "Agent.Actor","checks","Action.Check","checkedObject","hasMany" | AN38: =COUNTIF(View_conceptual!G:G,L38) -> 0 | AO38: =COUNTIF(View_conceptual!H:H,L38)+COUNTIF(View_conceptual!I:I,N38) -> 0 | AQ38: =IF(AN38=1,AF38,"") | AR38: =IF(AO38=2,AL38,"") | AT38: =COUNTIF(View_full!G:G,L38) -> 1 | AU38: =COUNTIF(View_full!H:H,L38)+COUNTIF(View_full!I:I,N38) -> 0 | AV38: =COUNTIFS(Property_Manual!$A$2:$A$1206,Raw!L38,Property_Manual!$B$2:$B$1206,Raw!M38,Property_Manual!$C$2:$C$1206,Raw!N38,Property_Manual!$D$2:$D$1206,Raw!O38,Property_Manual!$F$2:$F$1206,"x") -> 0 | AW38: =IF(AT38=1,AF38,"") | AX38: =IF(AU38=2,AL38,"") | AY38: =IF(AV38=1,AL38,"")
A39: Implicit | B39: Agent | C39: https://onerecord.iata.org/ns/cargo#Actor | D39: https://onerecord.iata.org/ns/cargo#externalReferences | E39: Common | F39: https://onerecord.iata.org/ns/cargo#ExternalReference | H39: https://onerecord.iata.org/ns/cargo#referenceForObjects | I39: Superclass: Actors are Persons or entities acting like a single person | J39: References to all associated ExternalReferences | L39: =SUBSTITUTE(SUBSTITUTE(SUBSTITUTE(C39,$B$2,$A$2),$B$3,$A$3),$B$4,$A$4) -> Actor | M39: =SUBSTITUTE(SUBSTITUTE(SUBSTITUTE(D39,$B$2,$A$2),$B$3,$A$3),$A$4,$B$4) -> externalReferences | N39: =SUBSTITUTE(SUBSTITUTE(SUBSTITUTE(F39,$B$2,$A$2),$B$3,$A$3),$B$4,$A$4) -> ExternalReference | O39: =SUBSTITUTE(SUBSTITUTE(SUBSTITUTE(H39,$B$2,$A$2),$B$3,$A$3),$B$4,$A$4) -> referenceForObjects | P39: =SUBSTITUTE(SUBSTITUTE(SUBSTITUTE(K39,$B$2,$A$2),$B$3,$A$3),$B$4,$A$4) | Q39: =IF(LEFT(N39,3)="xsd","Data","Object") -> Object | R39: =IF($A39="Implicit","",$F$1&B39&$F$1) | S39: =IF($A39="Implicit","",$F$1&L39&$F$1) | T39: =IF($A39="Implicit","",$F$1&M39&$F$1) | U39: =IF($A39="Implicit","",$F$1&E39&$F$1) | V39: =IF($A39="Implicit","",$F$1&N39&$F$1) | W39: =IF($A39="Implicit","",COUNTIFS($C$8:C39,C39,$A$8:A39,"Explicit")) | X39: =IF($A39="Implicit","",$F$1&SUBSTITUTE(IF(I39=0,"",I39),",",";")&$F$1) | Y39: =IF($A39="Implicit","",$F$1&SUBSTITUTE(IF(J39=0,"",J39),",",";")&$F$1) | Z39: =IF($A39="Implicit","",$F$1&IF(G39=1,"false","true")&$F$1) | AA39: =IF($A39="Implicit","",$F$1&IF(OR(E39="Enum",E39="CodeList"),"true","false")&$F$1) | AB39: =IF($A39="Implicit","",$F$1&P39&$F$1) | AC39: =IF($A39="Implicit","",$F$1&C39&$F$1) | AD39: =IF($A39="Implicit","",$F$1&D39&$F$1) | AE39: =IF($A39="Implicit","",$F$1&F39&$F$1) | AF39: =IF(A39="Implicit","",R39&","&S39&","&T39&","&U39&","&V39&","&W39&","&X39&","&Y39&","&Z39&","&AA39&","&AB39&","&AC39&","&AD39&","&AE39) | AG39: =IF(Q39="Data","",$F$1&B39&"."&L39&$F$1) -> "Agent.Actor" | AH39: =IF(Q39="Data","",$F$1&M39&$F$1) -> "externalReferences" | AI39: =IF(Q39="Data","",$F$1&E39&"."&N39&$F$1) -> "Common.ExternalReference" | AJ39: =IF(Q39="Data","",$F$1&O39&$F$1) -> "referenceForObjects" | AK39: =IF(Q39="Data","",$F$1&IF(G39=1,"hasOne","hasMany")&$F$1) -> "hasMany" | AL39: =IF(Q39="Data","",AG39&","&AH39&","&AI39&","&AJ39&","&AK39) -> "Agent.Actor","externalReferences","Common.ExternalReference","referenceForObjects","hasMany" | AN39: =COUNTIF(View_conceptual!G:G,L39) -> 0 | AO39: =COUNTIF(View_conceptual!H:H,L39)+COUNTIF(View_conceptual!I:I,N39) -> 0 | AQ39: =IF(AN39=1,AF39,"") | AR39: =IF(AO39=2,AL39,"") | AT39: =COUNTIF(View_full!G:G,L39) -> 1 | AU39: =COUNTIF(View_full!H:H,L39)+COUNTIF(View_full!I:I,N39) -> 0 | AV39: =COUNTIFS(Property_Manual!$A$2:$A$1206,Raw!L39,Property_Manual!$B$2:$B$1206,Raw!M39,Property_Manual!$C$2:$C$1206,Raw!N39,Property_Manual!$D$2:$D$1206,Raw!O39,Property_Manual!$F$2:$F$1206,"x") -> 0 | AW39: =IF(AT39=1,AF39,"") | AX39: =IF(AU39=2,AL39,"") | AY39: =IF(AV39=1,AL39,"")
A40: Explicit | B40: Agent | C40: https://onerecord.iata.org/ns/cargo#Actor | D40: https://onerecord.iata.org/ns/cargo#events | E40: Event | F40: https://onerecord.iata.org/ns/cargo#LogisticsEvent | I40: Superclass: Actors are Persons or entities acting like a single person | J40: Events object | L40: =SUBSTITUTE(SUBSTITUTE(SUBSTITUTE(C40,$B$2,$A$2),$B$3,$A$3),$B$4,$A$4) -> Actor | M40: =SUBSTITUTE(SUBSTITUTE(SUBSTITUTE(D40,$B$2,$A$2),$B$3,$A$3),$A$4,$B$4) -> events | N40: =SUBSTITUTE(SUBSTITUTE(SUBSTITUTE(F40,$B$2,$A$2),$B$3,$A$3),$B$4,$A$4) -> LogisticsEvent | O40: =SUBSTITUTE(SUBSTITUTE(SUBSTITUTE(H40,$B$2,$A$2),$B$3,$A$3),$B$4,$A$4) | P40: =SUBSTITUTE(SUBSTITUTE(SUBSTITUTE(K40,$B$2,$A$2),$B$3,$A$3),$B$4,$A$4) | Q40: =IF(LEFT(N40,3)="xsd","Data","Object") -> Object | R40: =IF($A40="Implicit","",$F$1&B40&$F$1) -> "Agent" | S40: =IF($A40="Implicit","",$F$1&L40&$F$1) -> "Actor" | T40: =IF($A40="Implicit","",$F$1&M40&$F$1) -> "events" | U40: =IF($A40="Implicit","",$F$1&E40&$F$1) -> "Event" | V40: =IF($A40="Implicit","",$F$1&N40&$F$1) -> "LogisticsEvent" | W40: =IF($A40="Implicit","",COUNTIFS($C$8:C40,C40,$A$8:A40,"Explicit")) -> 4 | X40: =IF($A40="Implicit","",$F$1&SUBSTITUTE(IF(I40=0,"",I40),",",";")&$F$1) -> "Superclass: Actors are Persons or entities acting like a single person" | Y40: =IF($A40="Implicit","",$F$1&SUBSTITUTE(IF(J40=0,"",J40),",",";")&$F$1) -> "Events object" | Z40: =IF($A40="Implicit","",$F$1&IF(G40=1,"false","true")&$F$1) -> "true" | AA40: =IF($A40="Implicit","",$F$1&IF(OR(E40="Enum",E40="CodeList"),"true","false")&$F$1) -> "false" | AB40: =IF($A40="Implicit","",$F$1&P40&$F$1) -> "" | AC40: =IF($A40="Implicit","",$F$1&C40&$F$1) -> "https://onerecord.iata.org/ns/cargo#Actor" | AD40: =IF($A40="Implicit","",$F$1&D40&$F$1) -> "https://onerecord.iata.org/ns/cargo#events" | AE40: =IF($A40="Implicit","",$F$1&F40&$F$1) -> "https://onerecord.iata.org/ns/cargo#LogisticsEvent" | AF40: =IF(A40="Implicit","",R40&","&S40&","&T40&","&U40&","&V40&","&W40&","&X40&","&Y40&","&Z40&","&AA40&","&AB40&","&AC40&","&AD40&","&AE40) -> "Agent","Actor","events","Event","LogisticsEvent",4,"Superclass: Actors are Persons or entities acting like a single person","Events object","true","false","","https://onerecord.iata.org/ns/cargo#Actor","https://onerecord.iata.org/ns/cargo#events","https://onerecord.iata.org/ns/cargo#LogisticsEvent" | AG40: =IF(Q40="Data","",$F$1&B40&"."&L40&$F$1) -> "Agent.Actor" | AH40: =IF(Q40="Data","",$F$1&M40&$F$1) -> "events" | AI40: =IF(Q40="Data","",$F$1&E40&"."&N40&$F$1) -> "Event.LogisticsEvent" | AJ40: =IF(Q40="Data","",$F$1&O40&$F$1) -> "" | AK40: =IF(Q40="Data","",$F$1&IF(G40=1,"hasOne","hasMany")&$F$1) -> "hasMany" | AL40: =IF(Q40="Data","",AG40&","&AH40&","&AI40&","&AJ40&","&AK40) -> "Agent.Actor","events","Event.LogisticsEvent","","hasMany" | AN40: =COUNTIF(View_conceptual!G:G,L40) -> 0 | AO40: =COUNTIF(View_conceptual!H:H,L40)+COUNTIF(View_conceptual!I:I,N40) -> 0 | AQ40: =IF(AN40=1,AF40,"") | AR40: =IF(AO40=2,AL40,"") | AT40: =COUNTIF(View_full!G:G,L40) -> 1 | AU40: =COUNTIF(View_full!H:H,L40)+COUNTIF(View_full!I:I,N40) -> 0 | AV40: =COUNTIFS(Property_Manual!$A$2:$A$1206,Raw!L40,Property_Manual!$B$2:$B$1206,Raw!M40,Property_Manual!$C$2:$C$1206,Raw!N40,Property_Manual!$D$2:$D$1206,Raw!O40,Property_Manual!$F$2:$F$1206,"x") -> 0 | AW40: =IF(AT40=1,AF40,"") -> "Agent","Actor","events","Event","LogisticsEvent",4,"Superclass: Actors are Persons or entities acting like a single person","Events object","true","false","","https://onerecord.iata.org/ns/cargo#Actor","https://onerecord.iata.org/ns/cargo#events","https://onerecord.iata.org/ns/cargo#LogisticsEvent" | AX40: =IF(AU40=2,AL40,"") | AY40: =IF(AV40=1,AL40,"")
A41: Explicit | B41: Agent | C41: https://onerecord.iata.org/ns/cargo#Actor | D41: https://onerecord.iata.org/ns/cargo#skeletonIndicator | F41: http://www.w3.org/2001/XMLSchema#boolean | G41: 1 | I41: Superclass: Actors are Persons or entities acting like a single person | J41: Indicator whether a logistics object is a skeleton object | L41: =SUBSTITUTE(SUBSTITUTE(SUBSTITUTE(C41,$B$2,$A$2),$B$3,$A$3),$B$4,$A$4) -> Actor | M41: =SUBSTITUTE(SUBSTITUTE(SUBSTITUTE(D41,$B$2,$A$2),$B$3,$A$3),$A$4,$B$4) -> skeletonIndicator | N41: =SUBSTITUTE(SUBSTITUTE(SUBSTITUTE(F41,$B$2,$A$2),$B$3,$A$3),$B$4,$A$4) -> boolean | O41: =SUBSTITUTE(SUBSTITUTE(SUBSTITUTE(H41,$B$2,$A$2),$B$3,$A$3),$B$4,$A$4) | P41: =SUBSTITUTE(SUBSTITUTE(SUBSTITUTE(K41,$B$2,$A$2),$B$3,$A$3),$B$4,$A$4) | Q41: =IF(LEFT(N41,3)="xsd","Data","Object") -> Object | R41: =IF($A41="Implicit","",$F$1&B41&$F$1) -> "Agent" | S41: =IF($A41="Implicit","",$F$1&L41&$F$1) -> "Actor" | T41: =IF($A41="Implicit","",$F$1&M41&$F$1) -> "skeletonIndicator" | U41: =IF($A41="Implicit","",$F$1&E41&$F$1) -> "" | V41: =IF($A41="Implicit","",$F$1&N41&$F$1) -> "boolean" | W41: =IF($A41="Implicit","",COUNTIFS($C$8:C41,C41,$A$8:A41,"Explicit")) -> 5 | X41: =IF($A41="Implicit","",$F$1&SUBSTITUTE(IF(I41=0,"",I41),",",";")&$F$1) -> "Superclass: Actors are Persons or entities acting like a single person" | Y41: =IF($A41="Implicit","",$F$1&SUBSTITUTE(IF(J41=0,"",J41),",",";")&$F$1) -> "Indicator whether a logistics object is a skeleton object" | Z41: =IF($A41="Implicit","",$F$1&IF(G41=1,"false","true")&$F$1) -> "false" | AA41: =IF($A41="Implicit","",$F$1&IF(OR(E41="Enum",E41="CodeList"),"true","false")&$F$1) -> "false" | AB41: =IF($A41="Implicit","",$F$1&P41&$F$1) -> "" | AC41: =IF($A41="Implicit","",$F$1&C41&$F$1) -> "https://onerecord.iata.org/ns/cargo#Actor" | AD41: =IF($A41="Implicit","",$F$1&D41&$F$1) -> "https://onerecord.iata.org/ns/cargo#skeletonIndicator" | AE41: =IF($A41="Implicit","",$F$1&F41&$F$1) -> "http://www.w3.org/2001/XMLSchema#boolean" | AF41: =IF(A41="Implicit","",R41&","&S41&","&T41&","&U41&","&V41&","&W41&","&X41&","&Y41&","&Z41&","&AA41&","&AB41&","&AC41&","&AD41&","&AE41) -> "Agent","Actor","skeletonIndicator","","boolean",5,"Superclass: Actors are Persons or entities acting like a single person","Indicator whether a logistics object is a skeleton object","false","false","","https://onerecord.iata.org/ns/cargo#Actor","https://onerecord.iata.org/ns/cargo#skeletonIndicator","http://www.w3.org/2001/XMLSchema#boolean" | AG41: =IF(Q41="Data","",$F$1&B41&"."&L41&$F$1) -> "Agent.Actor" | AH41: =IF(Q41="Data","",$F$1&M41&$F$1) -> "skeletonIndicator" | AI41: =IF(Q41="Data","",$F$1&E41&"."&N41&$F$1) -> ".boolean" | AJ41: =IF(Q41="Data","",$F$1&O41&$F$1) -> "" | AK41: =IF(Q41="Data","",$F$1&IF(G41=1,"hasOne","hasMany")&$F$1) -> "hasOne" | AL41: =IF(Q41="Data","",AG41&","&AH41&","&AI41&","&AJ41&","&AK41) -> "Agent.Actor","skeletonIndicator",".boolean","","hasOne" | AN41: =COUNTIF(View_conceptual!G:G,L41) -> 0 | AO41: =COUNTIF(View_conceptual!H:H,L41)+COUNTIF(View_conceptual!I:I,N41) -> 0 | AQ41: =IF(AN41=1,AF41,"") | AR41: =IF(AO41=2,AL41,"") | AT41: =COUNTIF(View_full!G:G,L41) -> 1 | AU41: =COUNTIF(View_full!H:H,L41)+COUNTIF(View_full!I:I,N41) -> 0 | AV41: =COUNTIFS(Property_Manual!$A$2:$A$1206,Raw!L41,Property_Manual!$B$2:$B$1206,Raw!M41,Property_Manual!$C$2:$C$1206,Raw!N41,Property_Manual!$D$2:$D$1206,Raw!O41,Property_Manual!$F$2:$F$1206,"x") -> 0 | AW41: =IF(AT41=1,AF41,"") -> "Agent","Actor","skeletonIndicator","","boolean",5,"Superclass: Actors are Persons or entities acting like a single person","Indicator whether a logistics object is a skeleton object","false","false","","https://onerecord.iata.org/ns/cargo#Actor","https://onerecord.iata.org/ns/cargo#skeletonIndicator","http://www.w3.org/2001/XMLSchema#boolean" | AX41: =IF(AU41=2,AL41,"") | AY41: =IF(AV41=1,AL41,"")
A42: Implicit | B42: Agent | C42: https://onerecord.iata.org/ns/cargo#Actor | D42: https://onerecord.iata.org/ns/cargo#events | E42: Event | F42: https://onerecord.iata.org/ns/cargo#LogisticsEvent | I42: Superclass: Actors are Persons or entities acting like a single person | J42: Events object | L42: =SUBSTITUTE(SUBSTITUTE(SUBSTITUTE(C42,$B$2,$A$2),$B$3,$A$3),$B$4,$A$4) -> Actor | M42: =SUBSTITUTE(SUBSTITUTE(SUBSTITUTE(D42,$B$2,$A$2),$B$3,$A$3),$A$4,$B$4) -> events | N42: =SUBSTITUTE(SUBSTITUTE(SUBSTITUTE(F42,$B$2,$A$2),$B$3,$A$3),$B$4,$A$4) -> LogisticsEvent | O42: =SUBSTITUTE(SUBSTITUTE(SUBSTITUTE(H42,$B$2,$A$2),$B$3,$A$3),$B$4,$A$4) | P42: =SUBSTITUTE(SUBSTITUTE(SUBSTITUTE(K42,$B$2,$A$2),$B$3,$A$3),$B$4,$A$4) | Q42: =IF(LEFT(N42,3)="xsd","Data","Object") -> Object | R42: =IF($A42="Implicit","",$F$1&B42&$F$1) | S42: =IF($A42="Implicit","",$F$1&L42&$F$1) | T42: =IF($A42="Implicit","",$F$1&M42&$F$1) | U42: =IF($A42="Implicit","",$F$1&E42&$F$1) | V42: =IF($A42="Implicit","",$F$1&N42&$F$1) | W42: =IF($A42="Implicit","",COUNTIFS($C$8:C42,C42,$A$8:A42,"Explicit")) | X42: =IF($A42="Implicit","",$F$1&SUBSTITUTE(IF(I42=0,"",I42),",",";")&$F$1) | Y42: =IF($A42="Implicit","",$F$1&SUBSTITUTE(IF(J42=0,"",J42),",",";")&$F$1) | Z42: =IF($A42="Implicit","",$F$1&IF(G42=1,"false","true")&$F$1) | AA42: =IF($A42="Implicit","",$F$1&IF(OR(E42="Enum",E42="CodeList"),"true","false")&$F$1) | AB42: =IF($A42="Implicit","",$F$1&P42&$F$1) | AC42: =IF($A42="Implicit","",$F$1&C42&$F$1) | AD42: =IF($A42="Implicit","",$F$1&D42&$F$1) | AE42: =IF($A42="Implicit","",$F$1&F42&$F$1) | AF42: =IF(A42="Implicit","",R42&","&S42&","&T42&","&U42&","&V42&","&W42&","&X42&","&Y42&","&Z42&","&AA42&","&AB42&","&AC42&","&AD42&","&AE42) | AG42: =IF(Q42="Data","",$F$1&B42&"."&L42&$F$1) -> "Agent.Actor" | AH42: =IF(Q42="Data","",$F$1&M42&$F$1) -> "events" | AI42: =IF(Q42="Data","",$F$1&E42&"."&N42&$F$1) -> "Event.LogisticsEvent" | AJ42: =IF(Q42="Data","",$F$1&O42&$F$1) -> "" | AK42: =IF(Q42="Data","",$F$1&IF(G42=1,"hasOne","hasMany")&$F$1) -> "hasMany" | AL42: =IF(Q42="Data","",AG42&","&AH42&","&AI42&","&AJ42&","&AK42) -> "Agent.Actor","events","Event.LogisticsEvent","","hasMany" | AN42: =COUNTIF(View_conceptual!G:G,L42) -> 0 | AO42: =COUNTIF(View_conceptual!H:H,L42)+COUNTIF(View_conceptual!I:I,N42) -> 0 | AQ42: =IF(AN42=1,AF42,"") | AR42: =IF(AO42=2,AL42,"") | AT42: =COUNTIF(View_full!G:G,L42) -> 1 | AU42: =COUNTIF(View_full!H:H,L42)+COUNTIF(View_full!I:I,N42) -> 0 | AV42: =COUNTIFS(Property_Manual!$A$2:$A$1206,Raw!L42,Property_Manual!$B$2:$B$1206,Raw!M42,Property_Manual!$C$2:$C$1206,Raw!N42,Property_Manual!$D$2:$D$1206,Raw!O42,Property_Manual!$F$2:$F$1206,"x") -> 0 | AW42: =IF(AT42=1,AF42,"") | AX42: =IF(AU42=2,AL42,"") | AY42: =IF(AV42=1,AL42,"")
A43: Explicit | B43: Embedded | C43: https://onerecord.iata.org/ns/cargo#Address | D43: https://onerecord.iata.org/ns/cargo#addressCode | E43: Embedded | F43: https://onerecord.iata.org/ns/cargo#CodeListElement | G43: 1 | I43: Address details | J43: Address identifier using special coding systems e.g. US CBP FIRMS code | L43: =SUBSTITUTE(SUBSTITUTE(SUBSTITUTE(C43,$B$2,$A$2),$B$3,$A$3),$B$4,$A$4) -> Address | M43: =SUBSTITUTE(SUBSTITUTE(SUBSTITUTE(D43,$B$2,$A$2),$B$3,$A$3),$A$4,$B$4) -> addressCode | N43: =SUBSTITUTE(SUBSTITUTE(SUBSTITUTE(F43,$B$2,$A$2),$B$3,$A$3),$B$4,$A$4) -> CodeListElement | O43: =SUBSTITUTE(SUBSTITUTE(SUBSTITUTE(H43,$B$2,$A$2),$B$3,$A$3),$B$4,$A$4) | P43: =SUBSTITUTE(SUBSTITUTE(SUBSTITUTE(K43,$B$2,$A$2),$B$3,$A$3),$B$4,$A$4) | Q43: =IF(LEFT(N43,3)="xsd","Data","Object") -> Object | R43: =IF($A43="Implicit","",$F$1&B43&$F$1) -> "Embedded" | S43: =IF($A43="Implicit","",$F$1&L43&$F$1) -> "Address" | T43: =IF($A43="Implicit","",$F$1&M43&$F$1) -> "addressCode" | U43: =IF($A43="Implicit","",$F$1&E43&$F$1) -> "Embedded" | V43: =IF($A43="Implicit","",$F$1&N43&$F$1) -> "CodeListElement" | W43: =IF($A43="Implicit","",COUNTIFS($C$8:C43,C43,$A$8:A43,"Explicit")) -> 1 | X43: =IF($A43="Implicit","",$F$1&SUBSTITUTE(IF(I43=0,"",I43),",",";")&$F$1) -> "Address details" | Y43: =IF($A43="Implicit","",$F$1&SUBSTITUTE(IF(J43=0,"",J43),",",";")&$F$1) -> "Address identifier using special coding systems e.g. US CBP FIRMS code" | Z43: =IF($A43="Implicit","",$F$1&IF(G43=1,"false","true")&$F$1) -> "false" | AA43: =IF($A43="Implicit","",$F$1&IF(OR(E43="Enum",E43="CodeList"),"true","false")&$F$1) -> "false" | AB43: =IF($A43="Implicit","",$F$1&P43&$F$1) -> "" | AC43: =IF($A43="Implicit","",$F$1&C43&$F$1) -> "https://onerecord.iata.org/ns/cargo#Address" | AD43: =IF($A43="Implicit","",$F$1&D43&$F$1) -> "https://onerecord.iata.org/ns/cargo#addressCode" | AE43: =IF($A43="Implicit","",$F$1&F43&$F$1) -> "https://onerecord.iata.org/ns/cargo#CodeListElement" | AF43: =IF(A43="Implicit","",R43&","&S43&","&T43&","&U43&","&V43&","&W43&","&X43&","&Y43&","&Z43&","&AA43&","&AB43&","&AC43&","&AD43&","&AE43) -> "Embedded","Address","addressCode","Embedded","CodeListElement",1,"Address details","Address identifier using special coding systems e.g. US CBP FIRMS code","false","false","","https://onerecord.iata.org/ns/cargo#Address","https://onerecord.iata.org/ns/cargo#addressCode","https://onerecord.iata.org/ns/cargo#CodeListElement" | AG43: =IF(Q43="Data","",$F$1&B43&"."&L43&$F$1) -> "Embedded.Address" | AH43: =IF(Q43="Data","",$F$1&M43&$F$1) -> "addressCode" | AI43: =IF(Q43="Data","",$F$1&E43&"."&N43&$F$1) -> "Embedded.CodeListElement" | AJ43: =IF(Q43="Data","",$F$1&O43&$F$1) -> "" | AK43: =IF(Q43="Data","",$F$1&IF(G43=1,"hasOne","hasMany")&$F$1) -> "hasOne" | AL43: =IF(Q43="Data","",AG43&","&AH43&","&AI43&","&AJ43&","&AK43) -> "Embedded.Address","addressCode","Embedded.CodeListElement","","hasOne" | AN43: =COUNTIF(View_conceptual!G:G,L43) -> 0 | AO43: =COUNTIF(View_conceptual!H:H,L43)+COUNTIF(View_conceptual!I:I,N43) -> 0 | AQ43: =IF(AN43=1,AF43,"") | AR43: =IF(AO43=2,AL43,"") | AT43: =COUNTIF(View_full!G:G,L43) -> 1 | AU43: =COUNTIF(View_full!H:H,L43)+COUNTIF(View_full!I:I,N43) -> 0 | AV43: =COUNTIFS(Property_Manual!$A$2:$A$1206,Raw!L43,Property_Manual!$B$2:$B$1206,Raw!M43,Property_Manual!$C$2:$C$1206,Raw!N43,Property_Manual!$D$2:$D$1206,Raw!O43,Property_Manual!$F$2:$F$1206,"x") -> 0 | AW43: =IF(AT43=1,AF43,"") -> "Embedded","Address","addressCode","Embedded","CodeListElement",1,"Address details","Address identifier using special coding systems e.g. US CBP FIRMS code","false","false","","https://onerecord.iata.org/ns/cargo#Address","https://onerecord.iata.org/ns/cargo#addressCode","https://onerecord.iata.org/ns/cargo#CodeListElement" | AX43: =IF(AU43=2,AL43,"") | AY43: =IF(AV43=1,AL43,"")
A44: Explicit | B44: Embedded | C44: https://onerecord.iata.org/ns/cargo#Address | D44: https://onerecord.iata.org/ns/cargo#cityCode | E44: Embedded | F44: https://onerecord.iata.org/ns/cargo#CodeListElement | G44: 1 | I44: Address details | J44: UN/LOCODE city code (5 letter) or IATA city code (3 letter) | L44: =SUBSTITUTE(SUBSTITUTE(SUBSTITUTE(C44,$B$2,$A$2),$B$3,$A$3),$B$4,$A$4) -> Address | M44: =SUBSTITUTE(SUBSTITUTE(SUBSTITUTE(D44,$B$2,$A$2),$B$3,$A$3),$A$4,$B$4) -> cityCode | N44: =SUBSTITUTE(SUBSTITUTE(SUBSTITUTE(F44,$B$2,$A$2),$B$3,$A$3),$B$4,$A$4) -> CodeListElement | O44: =SUBSTITUTE(SUBSTITUTE(SUBSTITUTE(H44,$B$2,$A$2),$B$3,$A$3),$B$4,$A$4) | P44: =SUBSTITUTE(SUBSTITUTE(SUBSTITUTE(K44,$B$2,$A$2),$B$3,$A$3),$B$4,$A$4) | Q44: =IF(LEFT(N44,3)="xsd","Data","Object") -> Object | R44: =IF($A44="Implicit","",$F$1&B44&$F$1) -> "Embedded" | S44: =IF($A44="Implicit","",$F$1&L44&$F$1) -> "Address" | T44: =IF($A44="Implicit","",$F$1&M44&$F$1) -> "cityCode" | U44: =IF($A44="Implicit","",$F$1&E44&$F$1) -> "Embedded" | V44: =IF($A44="Implicit","",$F$1&N44&$F$1) -> "CodeListElement" | W44: =IF($A44="Implicit","",COUNTIFS($C$8:C44,C44,$A$8:A44,"Explicit")) -> 2 | X44: =IF($A44="Implicit","",$F$1&SUBSTITUTE(IF(I44=0,"",I44),",",";")&$F$1) -> "Address details" | Y44: =IF($A44="Implicit","",$F$1&SUBSTITUTE(IF(J44=0,"",J44),",",";")&$F$1) -> "UN/LOCODE city code (5 letter) or IATA city code (3 letter)" | Z44: =IF($A44="Implicit","",$F$1&IF(G44=1,"false","true")&$F$1) -> "false" | AA44: =IF($A44="Implicit","",$F$1&IF(OR(E44="Enum",E44="CodeList"),"true","false")&$F$1) -> "false" | AB44: =IF($A44="Implicit","",$F$1&P44&$F$1) -> "" | AC44: =IF($A44="Implicit","",$F$1&C44&$F$1) -> "https://onerecord.iata.org/ns/cargo#Address" | AD44: =IF($A44="Implicit","",$F$1&D44&$F$1) -> "https://onerecord.iata.org/ns/cargo#cityCode" | AE44: =IF($A44="Implicit","",$F$1&F44&$F$1) -> "https://onerecord.iata.org/ns/cargo#CodeListElement" | AF44: =IF(A44="Implicit","",R44&","&S44&","&T44&","&U44&","&V44&","&W44&","&X44&","&Y44&","&Z44&","&AA44&","&AB44&","&AC44&","&AD44&","&AE44) -> "Embedded","Address","cityCode","Embedded","CodeListElement",2,"Address details","UN/LOCODE city code (5 letter) or IATA city code (3 letter)","false","false","","https://onerecord.iata.org/ns/cargo#Address","https://onerecord.iata.org/ns/cargo#cityCode","https://onerecord.iata.org/ns/cargo#CodeListElement" | AG44: =IF(Q44="Data","",$F$1&B44&"."&L44&$F$1) -> "Embedded.Address" | AH44: =IF(Q44="Data","",$F$1&M44&$F$1) -> "cityCode" | AI44: =IF(Q44="Data","",$F$1&E44&"."&N44&$F$1) -> "Embedded.CodeListElement" | AJ44: =IF(Q44="Data","",$F$1&O44&$F$1) -> "" | AK44: =IF(Q44="Data","",$F$1&IF(G44=1,"hasOne","hasMany")&$F$1) -> "hasOne" | AL44: =IF(Q44="Data","",AG44&","&AH44&","&AI44&","&AJ44&","&AK44) -> "Embedded.Address","cityCode","Embedded.CodeListElement","","hasOne" | AN44: =COUNTIF(View_conceptual!G:G,L44) -> 0 | AO44: =COUNTIF(View_conceptual!H:H,L44)+COUNTIF(View_conceptual!I:I,N44) -> 0 | AQ44: =IF(AN44=1,AF44,"") | AR44: =IF(AO44=2,AL44,"") | AT44: =COUNTIF(View_full!G:G,L44) -> 1 | AU44: =COUNTIF(View_full!H:H,L44)+COUNTIF(View_full!I:I,N44) -> 0 | AV44: =COUNTIFS(Property_Manual!$A$2:$A$1206,Raw!L44,Property_Manual!$B$2:$B$1206,Raw!M44,Property_Manual!$C$2:$C$1206,Raw!N44,Property_Manual!$D$2:$D$1206,Raw!O44,Property_Manual!$F$2:$F$1206,"x") -> 0 | AW44: =IF(AT44=1,AF44,"") -> "Embedded","Address","cityCode","Embedded","CodeListElement",2,"Address details","UN/LOCODE city code (5 letter) or IATA city code (3 letter)","false","false","","https://onerecord.iata.org/ns/cargo#Address","https://onerecord.iata.org/ns/cargo#cityCode","https://onerecord.iata.org/ns/cargo#CodeListElement" | AX44: =IF(AU44=2,AL44,"") | AY44: =IF(AV44=1,AL44,"")
A45: Explicit | B45: Embedded | C45: https://onerecord.iata.org/ns/cargo#Address | D45: https://onerecord.iata.org/ns/cargo#country | E45: Embedded | F45: https://onerecord.iata.org/ns/cargo#CodeListElement | G45: 1 | I45: Address details | J45: Country details. Refer ISO 3166-2 | L45: =SUBSTITUTE(SUBSTITUTE(SUBSTITUTE(C45,$B$2,$A$2),$B$3,$A$3),$B$4,$A$4) -> Address | M45: =SUBSTITUTE(SUBSTITUTE(SUBSTITUTE(D45,$B$2,$A$2),$B$3,$A$3),$A$4,$B$4) -> country | N45: =SUBSTITUTE(SUBSTITUTE(SUBSTITUTE(F45,$B$2,$A$2),$B$3,$A$3),$B$4,$A$4) -> CodeListElement | O45: =SUBSTITUTE(SUBSTITUTE(SUBSTITUTE(H45,$B$2,$A$2),$B$3,$A$3),$B$4,$A$4) | P45: =SUBSTITUTE(SUBSTITUTE(SUBSTITUTE(K45,$B$2,$A$2),$B$3,$A$3),$B$4,$A$4) | Q45: =IF(LEFT(N45,3)="xsd","Data","Object") -> Object | R45: =IF($A45="Implicit","",$F$1&B45&$F$1) -> "Embedded" | S45: =IF($A45="Implicit","",$F$1&L45&$F$1) -> "Address" | T45: =IF($A45="Implicit","",$F$1&M45&$F$1) -> "country" | U45: =IF($A45="Implicit","",$F$1&E45&$F$1) -> "Embedded" | V45: =IF($A45="Implicit","",$F$1&N45&$F$1) -> "CodeListElement" | W45: =IF($A45="Implicit","",COUNTIFS($C$8:C45,C45,$A$8:A45,"Explicit")) -> 3 | X45: =IF($A45="Implicit","",$F$1&SUBSTITUTE(IF(I45=0,"",I45),",",";")&$F$1) -> "Address details" | Y45: =IF($A45="Implicit","",$F$1&SUBSTITUTE(IF(J45=0,"",J45),",",";")&$F$1) -> "Country details. Refer ISO 3166-2" | Z45: =IF($A45="Implicit","",$F$1&IF(G45=1,"false","true")&$F$1) -> "false" | AA45: =IF($A45="Implicit","",$F$1&IF(OR(E45="Enum",E45="CodeList"),"true","false")&$F$1) -> "false" | AB45: =IF($A45="Implicit","",$F$1&P45&$F$1) -> "" | AC45: =IF($A45="Implicit","",$F$1&C45&$F$1) -> "https://onerecord.iata.org/ns/cargo#Address" | AD45: =IF($A45="Implicit","",$F$1&D45&$F$1) -> "https://onerecord.iata.org/ns/cargo#country" | AE45: =IF($A45="Implicit","",$F$1&F45&$F$1) -> "https://onerecord.iata.org/ns/cargo#CodeListElement" | AF45: =IF(A45="Implicit","",R45&","&S45&","&T45&","&U45&","&V45&","&W45&","&X45&","&Y45&","&Z45&","&AA45&","&AB45&","&AC45&","&AD45&","&AE45) -> "Embedded","Address","country","Embedded","CodeListElement",3,"Address details","Country details. Refer ISO 3166-2","false","false","","https://onerecord.iata.org/ns/cargo#Address","https://onerecord.iata.org/ns/cargo#country","https://onerecord.iata.org/ns/cargo#CodeListElement" | AG45: =IF(Q45="Data","",$F$1&B45&"."&L45&$F$1) -> "Embedded.Address" | AH45: =IF(Q45="Data","",$F$1&M45&$F$1) -> "country" | AI45: =IF(Q45="Data","",$F$1&E45&"."&N45&$F$1) -> "Embedded.CodeListElement" | AJ45: =IF(Q45="Data","",$F$1&O45&$F$1) -> "" | AK45: =IF(Q45="Data","",$F$1&IF(G45=1,"hasOne","hasMany")&$F$1) -> "hasOne" | AL45: =IF(Q45="Data","",AG45&","&AH45&","&AI45&","&AJ45&","&AK45) -> "Embedded.Address","country","Embedded.CodeListElement","","hasOne" | AN45: =COUNTIF(View_conceptual!G:G,L45) -> 0 | AO45: =COUNTIF(View_conceptual!H:H,L45)+COUNTIF(View_conceptual!I:I,N45) -> 0 | AQ45: =IF(AN45=1,AF45,"") | AR45: =IF(AO45=2,AL45,"") | AT45: =COUNTIF(View_full!G:G,L45) -> 1 | AU45: =COUNTIF(View_full!H:H,L45)+COUNTIF(View_full!I:I,N45) -> 0 | AV45: =COUNTIFS(Property_Manual!$A$2:$A$1206,Raw!L45,Property_Manual!$B$2:$B$1206,Raw!M45,Property_Manual!$C$2:$C$1206,Raw!N45,Property_Manual!$D$2:$D$1206,Raw!O45,Property_Manual!$F$2:$F$1206,"x") -> 0 | AW45: =IF(AT45=1,AF45,"") -> "Embedded","Address","country","Embedded","CodeListElement",3,"Address details","Country details. Refer ISO 3166-2","false","false","","https://onerecord.iata.org/ns/cargo#Address","https://onerecord.iata.org/ns/cargo#country","https://onerecord.iata.org/ns/cargo#CodeListElement" | AX45: =IF(AU45=2,AL45,"") | AY45: =IF(AV45=1,AL45,"")
A46: Explicit | B46: Embedded | C46: https://onerecord.iata.org/ns/cargo#Address | D46: https://onerecord.iata.org/ns/cargo#postalCode | E46: Embedded | F46: https://onerecord.iata.org/ns/cargo#CodeListElement | G46: 1 | I46: Address details | J46: Postal / ZIP code | L46: =SUBSTITUTE(SUBSTITUTE(SUBSTITUTE(C46,$B$2,$A$2),$B$3,$A$3),$B$4,$A$4) -> Address | M46: =SUBSTITUTE(SUBSTITUTE(SUBSTITUTE(D46,$B$2,$A$2),$B$3,$A$3),$A$4,$B$4) -> postalCode | N46: =SUBSTITUTE(SUBSTITUTE(SUBSTITUTE(F46,$B$2,$A$2),$B$3,$A$3),$B$4,$A$4) -> CodeListElement | O46: =SUBSTITUTE(SUBSTITUTE(SUBSTITUTE(H46,$B$2,$A$2),$B$3,$A$3),$B$4,$A$4) | P46: =SUBSTITUTE(SUBSTITUTE(SUBSTITUTE(K46,$B$2,$A$2),$B$3,$A$3),$B$4,$A$4) | Q46: =IF(LEFT(N46,3)="xsd","Data","Object") -> Object | R46: =IF($A46="Implicit","",$F$1&B46&$F$1) -> "Embedded" | S46: =IF($A46="Implicit","",$F$1&L46&$F$1) -> "Address" | T46: =IF($A46="Implicit","",$F$1&M46&$F$1) -> "postalCode" | U46: =IF($A46="Implicit","",$F$1&E46&$F$1) -> "Embedded" | V46: =IF($A46="Implicit","",$F$1&N46&$F$1) -> "CodeListElement" | W46: =IF($A46="Implicit","",COUNTIFS($C$8:C46,C46,$A$8:A46,"Explicit")) -> 4 | X46: =IF($A46="Implicit","",$F$1&SUBSTITUTE(IF(I46=0,"",I46),",",";")&$F$1) -> "Address details" | Y46: =IF($A46="Implicit","",$F$1&SUBSTITUTE(IF(J46=0,"",J46),",",";")&$F$1) -> "Postal / ZIP code" | Z46: =IF($A46="Implicit","",$F$1&IF(G46=1,"false","true")&$F$1) -> "false" | AA46: =IF($A46="Implicit","",$F$1&IF(OR(E46="Enum",E46="CodeList"),"true","false")&$F$1) -> "false" | AB46: =IF($A46="Implicit","",$F$1&P46&$F$1) -> "" | AC46: =IF($A46="Implicit","",$F$1&C46&$F$1) -> "https://onerecord.iata.org/ns/cargo#Address" | AD46: =IF($A46="Implicit","",$F$1&D46&$F$1) -> "https://onerecord.iata.org/ns/cargo#postalCode" | AE46: =IF($A46="Implicit","",$F$1&F46&$F$1) -> "https://onerecord.iata.org/ns/cargo#CodeListElement" | AF46: =IF(A46="Implicit","",R46&","&S46&","&T46&","&U46&","&V46&","&W46&","&X46&","&Y46&","&Z46&","&AA46&","&AB46&","&AC46&","&AD46&","&AE46) -> "Embedded","Address","postalCode","Embedded","CodeListElement",4,"Address details","Postal / ZIP code","false","false","","https://onerecord.iata.org/ns/cargo#Address","https://onerecord.iata.org/ns/cargo#postalCode","https://onerecord.iata.org/ns/cargo#CodeListElement" | AG46: =IF(Q46="Data","",$F$1&B46&"."&L46&$F$1) -> "Embedded.Address" | AH46: =IF(Q46="Data","",$F$1&M46&$F$1) -> "postalCode" | AI46: =IF(Q46="Data","",$F$1&E46&"."&N46&$F$1) -> "Embedded.CodeListElement" | AJ46: =IF(Q46="Data","",$F$1&O46&$F$1) -> "" | AK46: =IF(Q46="Data","",$F$1&IF(G46=1,"hasOne","hasMany")&$F$1) -> "hasOne" | AL46: =IF(Q46="Data","",AG46&","&AH46&","&AI46&","&AJ46&","&AK46) -> "Embedded.Address","postalCode","Embedded.CodeListElement","","hasOne" | AN46: =COUNTIF(View_conceptual!G:G,L46) -> 0 | AO46: =COUNTIF(View_conceptual!H:H,L46)+COUNTIF(View_conceptual!I:I,N46) -> 0 | AQ46: =IF(AN46=1,AF46,"") | AR46: =IF(AO46=2,AL46,"") | AT46: =COUNTIF(View_full!G:G,L46) -> 1 | AU46: =COUNTIF(View_full!H:H,L46)+COUNTIF(View_full!I:I,N46) -> 0 | AV46: =COUNTIFS(Property_Manual!$A$2:$A$1206,Raw!L46,Property_Manual!$B$2:$B$1206,Raw!M46,Property_Manual!$C$2:$C$1206,Raw!N46,Property_Manual!$D$2:$D$1206,Raw!O46,Property_Manual!$F$2:$F$1206,"x") -> 0 | AW46: =IF(AT46=1,AF46,"") -> "Embedded","Address","postalCode","Embedded","CodeListElement",4,"Address details","Postal / ZIP code","false","false","","https://onerecord.iata.org/ns/cargo#Address","https://onerecord.iata.org/ns/cargo#postalCode","https://onerecord.iata.org/ns/cargo#CodeListElement" | AX46: =IF(AU46=2,AL46,"") | AY46: =IF(AV46=1,AL46,"")
A47: Explicit | B47: Embedded | C47: https://onerecord.iata.org/ns/cargo#Address | D47: https://onerecord.iata.org/ns/cargo#regionCode | E47: Embedded | F47: https://onerecord.iata.org/ns/cargo#CodeListElement | G47: 1 | I47: Address details | J47: Region/ State / Department. Refer ISO 3166-2 | L47: =SUBSTITUTE(SUBSTITUTE(SUBSTITUTE(C47,$B$2,$A$2),$B$3,$A$3),$B$4,$A$4) -> Address | M47: =SUBSTITUTE(SUBSTITUTE(SUBSTITUTE(D47,$B$2,$A$2),$B$3,$A$3),$A$4,$B$4) -> regionCode | N47: =SUBSTITUTE(SUBSTITUTE(SUBSTITUTE(F47,$B$2,$A$2),$B$3,$A$3),$B$4,$A$4) -> CodeListElement | O47: =SUBSTITUTE(SUBSTITUTE(SUBSTITUTE(H47,$B$2,$A$2),$B$3,$A$3),$B$4,$A$4) | P47: =SUBSTITUTE(SUBSTITUTE(SUBSTITUTE(K47,$B$2,$A$2),$B$3,$A$3),$B$4,$A$4) | Q47: =IF(LEFT(N47,3)="xsd","Data","Object") -> Object | R47: =IF($A47="Implicit","",$F$1&B47&$F$1) -> "Embedded" | S47: =IF($A47="Implicit","",$F$1&L47&$F$1) -> "Address" | T47: =IF($A47="Implicit","",$F$1&M47&$F$1) -> "regionCode" | U47: =IF($A47="Implicit","",$F$1&E47&$F$1) -> "Embedded" | V47: =IF($A47="Implicit","",$F$1&N47&$F$1) -> "CodeListElement" | W47: =IF($A47="Implicit","",COUNTIFS($C$8:C47,C47,$A$8:A47,"Explicit")) -> 5 | X47: =IF($A47="Implicit","",$F$1&SUBSTITUTE(IF(I47=0,"",I47),",",";")&$F$1) -> "Address details" | Y47: =IF($A47="Implicit","",$F$1&SUBSTITUTE(IF(J47=0,"",J47),",",";")&$F$1) -> "Region/ State / Department. Refer ISO 3166-2" | Z47: =IF($A47="Implicit","",$F$1&IF(G47=1,"false","true")&$F$1) -> "false" | AA47: =IF($A47="Implicit","",$F$1&IF(OR(E47="Enum",E47="CodeList"),"true","false")&$F$1) -> "false" | AB47: =IF($A47="Implicit","",$F$1&P47&$F$1) -> "" | AC47: =IF($A47="Implicit","",$F$1&C47&$F$1) -> "https://onerecord.iata.org/ns/cargo#Address" | AD47: =IF($A47="Implicit","",$F$1&D47&$F$1) -> "https://onerecord.iata.org/ns/cargo#regionCode" | AE47: =IF($A47="Implicit","",$F$1&F47&$F$1) -> "https://onerecord.iata.org/ns/cargo#CodeListElement" | AF47: =IF(A47="Implicit","",R47&","&S47&","&T47&","&U47&","&V47&","&W47&","&X47&","&Y47&","&Z47&","&AA47&","&AB47&","&AC47&","&AD47&","&AE47) -> "Embedded","Address","regionCode","Embedded","CodeListElement",5,"Address details","Region/ State / Department. Refer ISO 3166-2","false","false","","https://onerecord.iata.org/ns/cargo#Address","https://onerecord.iata.org/ns/cargo#regionCode","https://onerecord.iata.org/ns/cargo#CodeListElement" | AG47: =IF(Q47="Data","",$F$1&B47&"."&L47&$F$1) -> "Embedded.Address" | AH47: =IF(Q47="Data","",$F$1&M47&$F$1) -> "regionCode" | AI47: =IF(Q47="Data","",$F$1&E47&"."&N47&$F$1) -> "Embedded.CodeListElement" | AJ47: =IF(Q47="Data","",$F$1&O47&$F$1) -> "" | AK47: =IF(Q47="Data","",$F$1&IF(G47=1,"hasOne","hasMany")&$F$1) -> "hasOne" | AL47: =IF(Q47="Data","",AG47&","&AH47&","&AI47&","&AJ47&","&AK47) -> "Embedded.Address","regionCode","Embedded.CodeListElement","","hasOne" | AN47: =COUNTIF(View_conceptual!G:G,L47) -> 0 | AO47: =COUNTIF(View_conceptual!H:H,L47)+COUNTIF(View_conceptual!I:I,N47) -> 0 | AQ47: =IF(AN47=1,AF47,"") | AR47: =IF(AO47=2,AL47,"") | AT47: =COUNTIF(View_full!G:G,L47) -> 1 | AU47: =COUNTIF(View_full!H:H,L47)+COUNTIF(View_full!I:I,N47) -> 0 | AV47: =COUNTIFS(Property_Manual!$A$2:$A$1206,Raw!L47,Property_Manual!$B$2:$B$1206,Raw!M47,Property_Manual!$C$2:$C$1206,Raw!N47,Property_Manual!$D$2:$D$1206,Raw!O47,Property_Manual!$F$2:$F$1206,"x") -> 0 | AW47: =IF(AT47=1,AF47,"") -> "Embedded","Address","regionCode","Embedded","CodeListElement",5,"Address details","Region/ State / Department. Refer ISO 3166-2","false","false","","https://onerecord.iata.org/ns/cargo#Address","https://onerecord.iata.org/ns/cargo#regionCode","https://onerecord.iata.org/ns/cargo#CodeListElement" | AX47: =IF(AU47=2,AL47,"") | AY47: =IF(AV47=1,AL47,"")
A48: Explicit | B48: Embedded | C48: https://onerecord.iata.org/ns/cargo#Address | D48: https://onerecord.iata.org/ns/cargo#cityName | F48: http://www.w3.org/2001/XMLSchema#string | G48: 1 | I48: Address details | J48: String holding a city name | L48: =SUBSTITUTE(SUBSTITUTE(SUBSTITUTE(C48,$B$2,$A$2),$B$3,$A$3),$B$4,$A$4) -> Address | M48: =SUBSTITUTE(SUBSTITUTE(SUBSTITUTE(D48,$B$2,$A$2),$B$3,$A$3),$A$4,$B$4) -> cityName | N48: =SUBSTITUTE(SUBSTITUTE(SUBSTITUTE(F48,$B$2,$A$2),$B$3,$A$3),$B$4,$A$4) -> string | O48: =SUBSTITUTE(SUBSTITUTE(SUBSTITUTE(H48,$B$2,$A$2),$B$3,$A$3),$B$4,$A$4) | P48: =SUBSTITUTE(SUBSTITUTE(SUBSTITUTE(K48,$B$2,$A$2),$B$3,$A$3),$B$4,$A$4) | Q48: =IF(LEFT(N48,3)="xsd","Data","Object") -> Object | R48: =IF($A48="Implicit","",$F$1&B48&$F$1) -> "Embedded" | S48: =IF($A48="Implicit","",$F$1&L48&$F$1) -> "Address" | T48: =IF($A48="Implicit","",$F$1&M48&$F$1) -> "cityName" | U48: =IF($A48="Implicit","",$F$1&E48&$F$1) -> "" | V48: =IF($A48="Implicit","",$F$1&N48&$F$1) -> "string" | W48: =IF($A48="Implicit","",COUNTIFS($C$8:C48,C48,$A$8:A48,"Explicit")) -> 6 | X48: =IF($A48="Implicit","",$F$1&SUBSTITUTE(IF(I48=0,"",I48),",",";")&$F$1) -> "Address details" | Y48: =IF($A48="Implicit","",$F$1&SUBSTITUTE(IF(J48=0,"",J48),",",";")&$F$1) -> "String holding a city name" | Z48: =IF($A48="Implicit","",$F$1&IF(G48=1,"false","true")&$F$1) -> "false" | AA48: =IF($A48="Implicit","",$F$1&IF(OR(E48="Enum",E48="CodeList"),"true","false")&$F$1) -> "false" | AB48: =IF($A48="Implicit","",$F$1&P48&$F$1) -> "" | AC48: =IF($A48="Implicit","",$F$1&C48&$F$1) -> "https://onerecord.iata.org/ns/cargo#Address" | AD48: =IF($A48="Implicit","",$F$1&D48&$F$1) -> "https://onerecord.iata.org/ns/cargo#cityName" | AE48: =IF($A48="Implicit","",$F$1&F48&$F$1) -> "http://www.w3.org/2001/XMLSchema#string" | AF48: =IF(A48="Implicit","",R48&","&S48&","&T48&","&U48&","&V48&","&W48&","&X48&","&Y48&","&Z48&","&AA48&","&AB48&","&AC48&","&AD48&","&AE48) -> "Embedded","Address","cityName","","string",6,"Address details","String holding a city name","false","false","","https://onerecord.iata.org/ns/cargo#Address","https://onerecord.iata.org/ns/cargo#cityName","http://www.w3.org/2001/XMLSchema#string" | AG48: =IF(Q48="Data","",$F$1&B48&"."&L48&$F$1) -> "Embedded.Address" | AH48: =IF(Q48="Data","",$F$1&M48&$F$1) -> "cityName" | AI48: =IF(Q48="Data","",$F$1&E48&"."&N48&$F$1) -> ".string" | AJ48: =IF(Q48="Data","",$F$1&O48&$F$1) -> "" | AK48: =IF(Q48="Data","",$F$1&IF(G48=1,"hasOne","hasMany")&$F$1) -> "hasOne" | AL48: =IF(Q48="Data","",AG48&","&AH48&","&AI48&","&AJ48&","&AK48) -> "Embedded.Address","cityName",".string","","hasOne" | AN48: =COUNTIF(View_conceptual!G:G,L48) -> 0 | AO48: =COUNTIF(View_conceptual!H:H,L48)+COUNTIF(View_conceptual!I:I,N48) -> 0 | AQ48: =IF(AN48=1,AF48,"") | AR48: =IF(AO48=2,AL48,"") | AT48: =COUNTIF(View_full!G:G,L48) -> 1 | AU48: =COUNTIF(View_full!H:H,L48)+COUNTIF(View_full!I:I,N48) -> 0 | AV48: =COUNTIFS(Property_Manual!$A$2:$A$1206,Raw!L48,Property_Manual!$B$2:$B$1206,Raw!M48,Property_Manual!$C$2:$C$1206,Raw!N48,Property_Manual!$D$2:$D$1206,Raw!O48,Property_Manual!$F$2:$F$1206,"x") -> 0 | AW48: =IF(AT48=1,AF48,"") -> "Embedded","Address","cityName","","string",6,"Address details","String holding a city name","false","false","","https://onerecord.iata.org/ns/cargo#Address","https://onerecord.iata.org/ns/cargo#cityName","http://www.w3.org/2001/XMLSchema#string" | AX48: =IF(AU48=2,AL48,"") | AY48: =IF(AV48=1,AL48,"")
A49: Explicit | B49: Embedded | C49: https://onerecord.iata.org/ns/cargo#Address | D49: https://onerecord.iata.org/ns/cargo#postOfficeBox | F49: http://www.w3.org/2001/XMLSchema#string | G49: 1 | I49: Address details | J49: Post Office box number / code | L49: =SUBSTITUTE(SUBSTITUTE(SUBSTITUTE(C49,$B$2,$A$2),$B$3,$A$3),$B$4,$A$4) -> Address | M49: =SUBSTITUTE(SUBSTITUTE(SUBSTITUTE(D49,$B$2,$A$2),$B$3,$A$3),$A$4,$B$4) -> postOfficeBox | N49: =SUBSTITUTE(SUBSTITUTE(SUBSTITUTE(F49,$B$2,$A$2),$B$3,$A$3),$B$4,$A$4) -> string | O49: =SUBSTITUTE(SUBSTITUTE(SUBSTITUTE(H49,$B$2,$A$2),$B$3,$A$3),$B$4,$A$4) | P49: =SUBSTITUTE(SUBSTITUTE(SUBSTITUTE(K49,$B$2,$A$2),$B$3,$A$3),$B$4,$A$4) | Q49: =IF(LEFT(N49,3)="xsd","Data","Object") -> Object | R49: =IF($A49="Implicit","",$F$1&B49&$F$1) -> "Embedded" | S49: =IF($A49="Implicit","",$F$1&L49&$F$1) -> "Address" | T49: =IF($A49="Implicit","",$F$1&M49&$F$1) -> "postOfficeBox" | U49: =IF($A49="Implicit","",$F$1&E49&$F$1) -> "" | V49: =IF($A49="Implicit","",$F$1&N49&$F$1) -> "string" | W49: =IF($A49="Implicit","",COUNTIFS($C$8:C49,C49,$A$8:A49,"Explicit")) -> 7 | X49: =IF($A49="Implicit","",$F$1&SUBSTITUTE(IF(I49=0,"",I49),",",";")&$F$1) -> "Address details" | Y49: =IF($A49="Implicit","",$F$1&SUBSTITUTE(IF(J49=0,"",J49),",",";")&$F$1) -> "Post Office box number / code" | Z49: =IF($A49="Implicit","",$F$1&IF(G49=1,"false","true")&$F$1) -> "false" | AA49: =IF($A49="Implicit","",$F$1&IF(OR(E49="Enum",E49="CodeList"),"true","false")&$F$1) -> "false" | AB49: =IF($A49="Implicit","",$F$1&P49&$F$1) -> "" | AC49: =IF($A49="Implicit","",$F$1&C49&$F$1) -> "https://onerecord.iata.org/ns/cargo#Address" | AD49: =IF($A49="Implicit","",$F$1&D49&$F$1) -> "https://onerecord.iata.org/ns/cargo#postOfficeBox" | AE49: =IF($A49="Implicit","",$F$1&F49&$F$1) -> "http://www.w3.org/2001/XMLSchema#string" | AF49: =IF(A49="Implicit","",R49&","&S49&","&T49&","&U49&","&V49&","&W49&","&X49&","&Y49&","&Z49&","&AA49&","&AB49&","&AC49&","&AD49&","&AE49) -> "Embedded","Address","postOfficeBox","","string",7,"Address details","Post Office box number / code","false","false","","https://onerecord.iata.org/ns/cargo#Address","https://onerecord.iata.org/ns/cargo#postOfficeBox","http://www.w3.org/2001/XMLSchema#string" | AG49: =IF(Q49="Data","",$F$1&B49&"."&L49&$F$1) -> "Embedded.Address" | AH49: =IF(Q49="Data","",$F$1&M49&$F$1) -> "postOfficeBox" | AI49: =IF(Q49="Data","",$F$1&E49&"."&N49&$F$1) -> ".string" | AJ49: =IF(Q49="Data","",$F$1&O49&$F$1) -> "" | AK49: =IF(Q49="Data","",$F$1&IF(G49=1,"hasOne","hasMany")&$F$1) -> "hasOne" | AL49: =IF(Q49="Data","",AG49&","&AH49&","&AI49&","&AJ49&","&AK49) -> "Embedded.Address","postOfficeBox",".string","","hasOne" | AN49: =COUNTIF(View_conceptual!G:G,L49) -> 0 | AO49: =COUNTIF(View_conceptual!H:H,L49)+COUNTIF(View_conceptual!I:I,N49) -> 0 | AQ49: =IF(AN49=1,AF49,"") | AR49: =IF(AO49=2,AL49,"") | AT49: =COUNTIF(View_full!G:G,L49) -> 1 | AU49: =COUNTIF(View_full!H:H,L49)+COUNTIF(View_full!I:I,N49) -> 0 | AV49: =COUNTIFS(Property_Manual!$A$2:$A$1206,Raw!L49,Property_Manual!$B$2:$B$1206,Raw!M49,Property_Manual!$C$2:$C$1206,Raw!N49,Property_Manual!$D$2:$D$1206,Raw!O49,Property_Manual!$F$2:$F$1206,"x") -> 0 | AW49: =IF(AT49=1,AF49,"") -> "Embedded","Address","postOfficeBox","","string",7,"Address details","Post Office box number / code","false","false","","https://onerecord.iata.org/ns/cargo#Address","https://onerecord.iata.org/ns/cargo#postOfficeBox","http://www.w3.org/2001/XMLSchema#string" | AX49: =IF(AU49=2,AL49,"") | AY49: =IF(AV49=1,AL49,"")
A50: Explicit | B50: Embedded | C50: https://onerecord.iata.org/ns/cargo#Address | D50: https://onerecord.iata.org/ns/cargo#textualPostCode | F50: http://www.w3.org/2001/XMLSchema#string | G50: 1 | I50: Address details | J50: Postal / ZIP code | L50: =SUBSTITUTE(SUBSTITUTE(SUBSTITUTE(C50,$B$2,$A$2),$B$3,$A$3),$B$4,$A$4) -> Address | M50: =SUBSTITUTE(SUBSTITUTE(SUBSTITUTE(D50,$B$2,$A$2),$B$3,$A$3),$A$4,$B$4) -> textualPostCode | N50: =SUBSTITUTE(SUBSTITUTE(SUBSTITUTE(F50,$B$2,$A$2),$B$3,$A$3),$B$4,$A$4) -> string | O50: =SUBSTITUTE(SUBSTITUTE(SUBSTITUTE(H50,$B$2,$A$2),$B$3,$A$3),$B$4,$A$4) | P50: =SUBSTITUTE(SUBSTITUTE(SUBSTITUTE(K50,$B$2,$A$2),$B$3,$A$3),$B$4,$A$4) | Q50: =IF(LEFT(N50,3)="xsd","Data","Object") -> Object | R50: =IF($A50="Implicit","",$F$1&B50&$F$1) -> "Embedded" | S50: =IF($A50="Implicit","",$F$1&L50&$F$1) -> "Address" | T50: =IF($A50="Implicit","",$F$1&M50&$F$1) -> "textualPostCode" | U50: =IF($A50="Implicit","",$F$1&E50&$F$1) -> "" | V50: =IF($A50="Implicit","",$F$1&N50&$F$1) -> "string" | W50: =IF($A50="Implicit","",COUNTIFS($C$8:C50,C50,$A$8:A50,"Explicit")) -> 8 | X50: =IF($A50="Implicit","",$F$1&SUBSTITUTE(IF(I50=0,"",I50),",",";")&$F$1) -> "Address details" | Y50: =IF($A50="Implicit","",$F$1&SUBSTITUTE(IF(J50=0,"",J50),",",";")&$F$1) -> "Postal / ZIP code" | Z50: =IF($A50="Implicit","",$F$1&IF(G50=1,"false","true")&$F$1) -> "false" | AA50: =IF($A50="Implicit","",$F$1&IF(OR(E50="Enum",E50="CodeList"),"true","false")&$F$1) -> "false" | AB50: =IF($A50="Implicit","",$F$1&P50&$F$1) -> "" | AC50: =IF($A50="Implicit","",$F$1&C50&$F$1) -> "https://onerecord.iata.org/ns/cargo#Address" | AD50: =IF($A50="Implicit","",$F$1&D50&$F$1) -> "https://onerecord.iata.org/ns/cargo#textualPostCode" | AE50: =IF($A50="Implicit","",$F$1&F50&$F$1) -> "http://www.w3.org/2001/XMLSchema#string" | AF50: =IF(A50="Implicit","",R50&","&S50&","&T50&","&U50&","&V50&","&W50&","&X50&","&Y50&","&Z50&","&AA50&","&AB50&","&AC50&","&AD50&","&AE50) -> "Embedded","Address","textualPostCode","","string",8,"Address details","Postal / ZIP code","false","false","","https://onerecord.iata.org/ns/cargo#Address","https://onerecord.iata.org/ns/cargo#textualPostCode","http://www.w3.org/2001/XMLSchema#string" | AG50: =IF(Q50="Data","",$F$1&B50&"."&L50&$F$1) -> "Embedded.Address" | AH50: =IF(Q50="Data","",$F$1&M50&$F$1) -> "textualPostCode" | AI50: =IF(Q50="Data","",$F$1&E50&"."&N50&$F$1) -> ".string" | AJ50: =IF(Q50="Data","",$F$1&O50&$F$1) -> "" | AK50: =IF(Q50="Data","",$F$1&IF(G50=1,"hasOne","hasMany")&$F$1) -> "hasOne" | AL50: =IF(Q50="Data","",AG50&","&AH50&","&AI50&","&AJ50&","&AK50) -> "Embedded.Address","textualPostCode",".string","","hasOne" | AN50: =COUNTIF(View_conceptual!G:G,L50) -> 0 | AO50: =COUNTIF(View_conceptual!H:H,L50)+COUNTIF(View_conceptual!I:I,N50) -> 0 | AQ50: =IF(AN50=1,AF50,"") | AR50: =IF(AO50=2,AL50,"") | AT50: =COUNTIF(View_full!G:G,L50) -> 1 | AU50: =COUNTIF(View_full!H:H,L50)+COUNTIF(View_full!I:I,N50) -> 0 | AV50: =COUNTIFS(Property_Manual!$A$2:$A$1206,Raw!L50,Property_Manual!$B$2:$B$1206,Raw!M50,Property_Manual!$C$2:$C$1206,Raw!N50,Property_Manual!$D$2:$D$1206,Raw!O50,Property_Manual!$F$2:$F$1206,"x") -> 0 | AW50: =IF(AT50=1,AF50,"") -> "Embedded","Address","textualPostCode","","string",8,"Address details","Postal / ZIP code","false","false","","https://onerecord.iata.org/ns/cargo#Address","https://onerecord.iata.org/ns/cargo#textualPostCode","http://www.w3.org/2001/XMLSchema#string" | AX50: =IF(AU50=2,AL50,"") | AY50: =IF(AV50=1,AL50,"")
A51: Explicit | B51: Embedded | C51: https://onerecord.iata.org/ns/cargo#Address | D51: https://onerecord.iata.org/ns/cargo#streetAddressLines | F51: http://www.w3.org/2001/XMLSchema#string | I51: Address details | J51: Street address including street name, street number, building number, apartment etc | L51: =SUBSTITUTE(SUBSTITUTE(SUBSTITUTE(C51,$B$2,$A$2),$B$3,$A$3),$B$4,$A$4) -> Address | M51: =SUBSTITUTE(SUBSTITUTE(SUBSTITUTE(D51,$B$2,$A$2),$B$3,$A$3),$A$4,$B$4) -> streetAddressLines | N51: =SUBSTITUTE(SUBSTITUTE(SUBSTITUTE(F51,$B$2,$A$2),$B$3,$A$3),$B$4,$A$4) -> string | O51: =SUBSTITUTE(SUBSTITUTE(SUBSTITUTE(H51,$B$2,$A$2),$B$3,$A$3),$B$4,$A$4) | P51: =SUBSTITUTE(SUBSTITUTE(SUBSTITUTE(K51,$B$2,$A$2),$B$3,$A$3),$B$4,$A$4) | Q51: =IF(LEFT(N51,3)="xsd","Data","Object") -> Object | R51: =IF($A51="Implicit","",$F$1&B51&$F$1) -> "Embedded" | S51: =IF($A51="Implicit","",$F$1&L51&$F$1) -> "Address" | T51: =IF($A51="Implicit","",$F$1&M51&$F$1) -> "streetAddressLines" | U51: =IF($A51="Implicit","",$F$1&E51&$F$1) -> "" | V51: =IF($A51="Implicit","",$F$1&N51&$F$1) -> "string" | W51: =IF($A51="Implicit","",COUNTIFS($C$8:C51,C51,$A$8:A51,"Explicit")) -> 9 | X51: =IF($A51="Implicit","",$F$1&SUBSTITUTE(IF(I51=0,"",I51),",",";")&$F$1) -> "Address details" | Y51: =IF($A51="Implicit","",$F$1&SUBSTITUTE(IF(J51=0,"",J51),",",";")&$F$1) -> "Street address including street name; street number; building number; apartment etc" | Z51: =IF($A51="Implicit","",$F$1&IF(G51=1,"false","true")&$F$1) -> "true" | AA51: =IF($A51="Implicit","",$F$1&IF(OR(E51="Enum",E51="CodeList"),"true","false")&$F$1) -> "false" | AB51: =IF($A51="Implicit","",$F$1&P51&$F$1) -> "" | AC51: =IF($A51="Implicit","",$F$1&C51&$F$1) -> "https://onerecord.iata.org/ns/cargo#Address" | AD51: =IF($A51="Implicit","",$F$1&D51&$F$1) -> "https://onerecord.iata.org/ns/cargo#streetAddressLines" | AE51: =IF($A51="Implicit","",$F$1&F51&$F$1) -> "http://www.w3.org/2001/XMLSchema#string" | AF51: =IF(A51="Implicit","",R51&","&S51&","&T51&","&U51&","&V51&","&W51&","&X51&","&Y51&","&Z51&","&AA51&","&AB51&","&AC51&","&AD51&","&AE51) -> "Embedded","Address","streetAddressLines","","string",9,"Address details","Street address including street name; street number; building number; apartment etc","true","false","","https://onerecord.iata.org/ns/cargo#Address","https://onerecord.iata.org/ns/cargo#streetAddressLines","http://www.w3.org/2001/XMLSchema#string" | AG51: =IF(Q51="Data","",$F$1&B51&"."&L51&$F$1) -> "Embedded.Address" | AH51: =IF(Q51="Data","",$F$1&M51&$F$1) -> "streetAddressLines" | AI51: =IF(Q51="Data","",$F$1&E51&"."&N51&$F$1) -> ".string" | AJ51: =IF(Q51="Data","",$F$1&O51&$F$1) -> "" | AK51: =IF(Q51="Data","",$F$1&IF(G51=1,"hasOne","hasMany")&$F$1) -> "hasMany" | AL51: =IF(Q51="Data","",AG51&","&AH51&","&AI51&","&AJ51&","&AK51) -> "Embedded.Address","streetAddressLines",".string","","hasMany" | AN51: =COUNTIF(View_conceptual!G:G,L51) -> 0 | AO51: =COUNTIF(View_conceptual!H:H,L51)+COUNTIF(View_conceptual!I:I,N51) -> 0 | AQ51: =IF(AN51=1,AF51,"") | AR51: =IF(AO51=2,AL51,"") | AT51: =COUNTIF(View_full!G:G,L51) -> 1 | AU51: =COUNTIF(View_full!H:H,L51)+COUNTIF(View_full!I:I,N51) -> 0 | AV51: =COUNTIFS(Property_Manual!$A$2:$A$1206,Raw!L51,Property_Manual!$B$2:$B$1206,Raw!M51,Property_Manual!$C$2:$C$1206,Raw!N51,Property_Manual!$D$2:$D$1206,Raw!O51,Property_Manual!$F$2:$F$1206,"x") -> 0 | AW51: =IF(AT51=1,AF51,"") -> "Embedded","Address","streetAddressLines","","string",9,"Address details","Street address including street name; street number; building number; apartment etc","true","false","","https://onerecord.iata.org/ns/cargo#Address","https://onerecord.iata.org/ns/cargo#streetAddressLines","http://www.w3.org/2001/XMLSchema#string" | AX51: =IF(AU51=2,AL51,"") | AY51: =IF(AV51=1,AL51,"")
A52: Explicit | B52: Embedded | C52: https://onerecord.iata.org/ns/cargo#Adjustments | D52: https://onerecord.iata.org/ns/cargo#correctionNumber | F52: http://www.w3.org/2001/XMLSchema#integer | G52: 1 | I52: Adjustments in the context of CASS records | J52: Number of the adjustment | L52: =SUBSTITUTE(SUBSTITUTE(SUBSTITUTE(C52,$B$2,$A$2),$B$3,$A$3),$B$4,$A$4) -> Adjustments | M52: =SUBSTITUTE(SUBSTITUTE(SUBSTITUTE(D52,$B$2,$A$2),$B$3,$A$3),$A$4,$B$4) -> correctionNumber | N52: =SUBSTITUTE(SUBSTITUTE(SUBSTITUTE(F52,$B$2,$A$2),$B$3,$A$3),$B$4,$A$4) -> integer | O52: =SUBSTITUTE(SUBSTITUTE(SUBSTITUTE(H52,$B$2,$A$2),$B$3,$A$3),$B$4,$A$4) | P52: =SUBSTITUTE(SUBSTITUTE(SUBSTITUTE(K52,$B$2,$A$2),$B$3,$A$3),$B$4,$A$4) | Q52: =IF(LEFT(N52,3)="xsd","Data","Object") -> Object | R52: =IF($A52="Implicit","",$F$1&B52&$F$1) -> "Embedded" | S52: =IF($A52="Implicit","",$F$1&L52&$F$1) -> "Adjustments" | T52: =IF($A52="Implicit","",$F$1&M52&$F$1) -> "correctionNumber" | U52: =IF($A52="Implicit","",$F$1&E52&$F$1) -> "" | V52: =IF($A52="Implicit","",$F$1&N52&$F$1) -> "integer" | W52: =IF($A52="Implicit","",COUNTIFS($C$8:C52,C52,$A$8:A52,"Explicit")) -> 1 | X52: =IF($A52="Implicit","",$F$1&SUBSTITUTE(IF(I52=0,"",I52),",",";")&$F$1) -> "Adjustments in the context of CASS records" | Y52: =IF($A52="Implicit","",$F$1&SUBSTITUTE(IF(J52=0,"",J52),",",";")&$F$1) -> "Number of the adjustment" | Z52: =IF($A52="Implicit","",$F$1&IF(G52=1,"false","true")&$F$1) -> "false" | AA52: =IF($A52="Implicit","",$F$1&IF(OR(E52="Enum",E52="CodeList"),"true","false")&$F$1) -> "false" | AB52: =IF($A52="Implicit","",$F$1&P52&$F$1) -> "" | AC52: =IF($A52="Implicit","",$F$1&C52&$F$1) -> "https://onerecord.iata.org/ns/cargo#Adjustments" | AD52: =IF($A52="Implicit","",$F$1&D52&$F$1) -> "https://onerecord.iata.org/ns/cargo#correctionNumber" | AE52: =IF($A52="Implicit","",$F$1&F52&$F$1) -> "http://www.w3.org/2001/XMLSchema#integer" | AF52: =IF(A52="Implicit","",R52&","&S52&","&T52&","&U52&","&V52&","&W52&","&X52&","&Y52&","&Z52&","&AA52&","&AB52&","&AC52&","&AD52&","&AE52) -> "Embedded","Adjustments","correctionNumber","","integer",1,"Adjustments in the context of CASS records","Number of the adjustment","false","false","","https://onerecord.iata.org/ns/cargo#Adjustments","https://onerecord.iata.org/ns/cargo#correctionNumber","http://www.w3.org/2001/XMLSchema#integer" | AG52: =IF(Q52="Data","",$F$1&B52&"."&L52&$F$1) -> "Embedded.Adjustments" | AH52: =IF(Q52="Data","",$F$1&M52&$F$1) -> "correctionNumber" | AI52: =IF(Q52="Data","",$F$1&E52&"."&N52&$F$1) -> ".integer" | AJ52: =IF(Q52="Data","",$F$1&O52&$F$1) -> "" | AK52: =IF(Q52="Data","",$F$1&IF(G52=1,"hasOne","hasMany")&$F$1) -> "hasOne" | AL52: =IF(Q52="Data","",AG52&","&AH52&","&AI52&","&AJ52&","&AK52) -> "Embedded.Adjustments","correctionNumber",".integer","","hasOne" | AN52: =COUNTIF(View_conceptual!G:G,L52) -> 0 | AO52: =COUNTIF(View_conceptual!H:H,L52)+COUNTIF(View_conceptual!I:I,N52) -> 0 | AQ52: =IF(AN52=1,AF52,"") | AR52: =IF(AO52=2,AL52,"") | AT52: =COUNTIF(View_full!G:G,L52) -> 1 | AU52: =COUNTIF(View_full!H:H,L52)+COUNTIF(View_full!I:I,N52) -> 0 | AV52: =COUNTIFS(Property_Manual!$A$2:$A$1206,Raw!L52,Property_Manual!$B$2:$B$1206,Raw!M52,Property_Manual!$C$2:$C$1206,Raw!N52,Property_Manual!$D$2:$D$1206,Raw!O52,Property_Manual!$F$2:$F$1206,"x") -> 0 | AW52: =IF(AT52=1,AF52,"") -> "Embedded","Adjustments","correctionNumber","","integer",1,"Adjustments in the context of CASS records","Number of the adjustment","false","false","","https://onerecord.iata.org/ns/cargo#Adjustments","https://onerecord.iata.org/ns/cargo#correctionNumber","http://www.w3.org/2001/XMLSchema#integer" | AX52: =IF(AU52=2,AL52,"") | AY52: =IF(AV52=1,AL52,"")
A53: Explicit | B53: Embedded | C53: https://onerecord.iata.org/ns/cargo#Adjustments | D53: https://onerecord.iata.org/ns/cargo#correctionSerialNumber | F53: http://www.w3.org/2001/XMLSchema#string | G53: 1 | I53: Adjustments in the context of CASS records | J53: Serial Number of the correction | L53: =SUBSTITUTE(SUBSTITUTE(SUBSTITUTE(C53,$B$2,$A$2),$B$3,$A$3),$B$4,$A$4) -> Adjustments | M53: =SUBSTITUTE(SUBSTITUTE(SUBSTITUTE(D53,$B$2,$A$2),$B$3,$A$3),$A$4,$B$4) -> correctionSerialNumber | N53: =SUBSTITUTE(SUBSTITUTE(SUBSTITUTE(F53,$B$2,$A$2),$B$3,$A$3),$B$4,$A$4) -> string | O53: =SUBSTITUTE(SUBSTITUTE(SUBSTITUTE(H53,$B$2,$A$2),$B$3,$A$3),$B$4,$A$4) | P53: =SUBSTITUTE(SUBSTITUTE(SUBSTITUTE(K53,$B$2,$A$2),$B$3,$A$3),$B$4,$A$4) | Q53: =IF(LEFT(N53,3)="xsd","Data","Object") -> Object | R53: =IF($A53="Implicit","",$F$1&B53&$F$1) -> "Embedded" | S53: =IF($A53="Implicit","",$F$1&L53&$F$1) -> "Adjustments" | T53: =IF($A53="Implicit","",$F$1&M53&$F$1) -> "correctionSerialNumber" | U53: =IF($A53="Implicit","",$F$1&E53&$F$1) -> "" | V53: =IF($A53="Implicit","",$F$1&N53&$F$1) -> "string" | W53: =IF($A53="Implicit","",COUNTIFS($C$8:C53,C53,$A$8:A53,"Explicit")) -> 2 | X53: =IF($A53="Implicit","",$F$1&SUBSTITUTE(IF(I53=0,"",I53),",",";")&$F$1) -> "Adjustments in the context of CASS records" | Y53: =IF($A53="Implicit","",$F$1&SUBSTITUTE(IF(J53=0,"",J53),",",";")&$F$1) -> "Serial Number of the correction" | Z53: =IF($A53="Implicit","",$F$1&IF(G53=1,"false","true")&$F$1) -> "false" | AA53: =IF($A53="Implicit","",$F$1&IF(OR(E53="Enum",E53="CodeList"),"true","false")&$F$1) -> "false" | AB53: =IF($A53="Implicit","",$F$1&P53&$F$1) -> "" | AC53: =IF($A53="Implicit","",$F$1&C53&$F$1) -> "https://onerecord.iata.org/ns/cargo#Adjustments" | AD53: =IF($A53="Implicit","",$F$1&D53&$F$1) -> "https://onerecord.iata.org/ns/cargo#correctionSerialNumber" | AE53: =IF($A53="Implicit","",$F$1&F53&$F$1) -> "http://www.w3.org/2001/XMLSchema#string" | AF53: =IF(A53="Implicit","",R53&","&S53&","&T53&","&U53&","&V53&","&W53&","&X53&","&Y53&","&Z53&","&AA53&","&AB53&","&AC53&","&AD53&","&AE53) -> "Embedded","Adjustments","correctionSerialNumber","","string",2,"Adjustments in the context of CASS records","Serial Number of the correction","false","false","","https://onerecord.iata.org/ns/cargo#Adjustments","https://onerecord.iata.org/ns/cargo#correctionSerialNumber","http://www.w3.org/2001/XMLSchema#string" | AG53: =IF(Q53="Data","",$F$1&B53&"."&L53&$F$1) -> "Embedded.Adjustments" | AH53: =IF(Q53="Data","",$F$1&M53&$F$1) -> "correctionSerialNumber" | AI53: =IF(Q53="Data","",$F$1&E53&"."&N53&$F$1) -> ".string" | AJ53: =IF(Q53="Data","",$F$1&O53&$F$1) -> "" | AK53: =IF(Q53="Data","",$F$1&IF(G53=1,"hasOne","hasMany")&$F$1) -> "hasOne" | AL53: =IF(Q53="Data","",AG53&","&AH53&","&AI53&","&AJ53&","&AK53) -> "Embedded.Adjustments","correctionSerialNumber",".string","","hasOne" | AN53: =COUNTIF(View_conceptual!G:G,L53) -> 0 | AO53: =COUNTIF(View_conceptual!H:H,L53)+COUNTIF(View_conceptual!I:I,N53) -> 0 | AQ53: =IF(AN53=1,AF53,"") | AR53: =IF(AO53=2,AL53,"") | AT53: =COUNTIF(View_full!G:G,L53) -> 1 | AU53: =COUNTIF(View_full!H:H,L53)+COUNTIF(View_full!I:I,N53) -> 0 | AV53: =COUNTIFS(Property_Manual!$A$2:$A$1206,Raw!L53,Property_Manual!$B$2:$B$1206,Raw!M53,Property_Manual!$C$2:$C$1206,Raw!N53,Property_Manual!$D$2:$D$1206,Raw!O53,Property_Manual!$F$2:$F$1206,"x") -> 0 | AW53: =IF(AT53=1,AF53,"") -> "Embedded","Adjustments","correctionSerialNumber","","string",2,"Adjustments in the context of CASS records","Serial Number of the correction","false","false","","https://onerecord.iata.org/ns/cargo#Adjustments","https://onerecord.iata.org/ns/cargo#correctionSerialNumber","http://www.w3.org/2001/XMLSchema#string" | AX53: =IF(AU53=2,AL53,"") | AY53: =IF(AV53=1,AL53,"")
A54: Explicit | B54: Embedded | C54: https://onerecord.iata.org/ns/cargo#Adjustments | D54: https://onerecord.iata.org/ns/cargo#reasonsForAdjustments | F54: http://www.w3.org/2001/XMLSchema#string | G54: 1 | I54: Adjustments in the context of CASS records | J54: A free text for user to include a reason for correction | L54: =SUBSTITUTE(SUBSTITUTE(SUBSTITUTE(C54,$B$2,$A$2),$B$3,$A$3),$B$4,$A$4) -> Adjustments | M54: =SUBSTITUTE(SUBSTITUTE(SUBSTITUTE(D54,$B$2,$A$2),$B$3,$A$3),$A$4,$B$4) -> reasonsForAdjustments | N54: =SUBSTITUTE(SUBSTITUTE(SUBSTITUTE(F54,$B$2,$A$2),$B$3,$A$3),$B$4,$A$4) -> string | O54: =SUBSTITUTE(SUBSTITUTE(SUBSTITUTE(H54,$B$2,$A$2),$B$3,$A$3),$B$4,$A$4) | P54: =SUBSTITUTE(SUBSTITUTE(SUBSTITUTE(K54,$B$2,$A$2),$B$3,$A$3),$B$4,$A$4) | Q54: =IF(LEFT(N54,3)="xsd","Data","Object") -> Object | R54: =IF($A54="Implicit","",$F$1&B54&$F$1) -> "Embedded" | S54: =IF($A54="Implicit","",$F$1&L54&$F$1) -> "Adjustments" | T54: =IF($A54="Implicit","",$F$1&M54&$F$1) -> "reasonsForAdjustments" | U54: =IF($A54="Implicit","",$F$1&E54&$F$1) -> "" | V54: =IF($A54="Implicit","",$F$1&N54&$F$1) -> "string" | W54: =IF($A54="Implicit","",COUNTIFS($C$8:C54,C54,$A$8:A54,"Explicit")) -> 3 | X54: =IF($A54="Implicit","",$F$1&SUBSTITUTE(IF(I54=0,"",I54),",",";")&$F$1) -> "Adjustments in the context of CASS records" | Y54: =IF($A54="Implicit","",$F$1&SUBSTITUTE(IF(J54=0,"",J54),",",";")&$F$1) -> "A free text for user to include a reason for correction" | Z54: =IF($A54="Implicit","",$F$1&IF(G54=1,"false","true")&$F$1) -> "false" | AA54: =IF($A54="Implicit","",$F$1&IF(OR(E54="Enum",E54="CodeList"),"true","false")&$F$1) -> "false" | AB54: =IF($A54="Implicit","",$F$1&P54&$F$1) -> "" | AC54: =IF($A54="Implicit","",$F$1&C54&$F$1) -> "https://onerecord.iata.org/ns/cargo#Adjustments" | AD54: =IF($A54="Implicit","",$F$1&D54&$F$1) -> "https://onerecord.iata.org/ns/cargo#reasonsForAdjustments" | AE54: =IF($A54="Implicit","",$F$1&F54&$F$1) -> "http://www.w3.org/2001/XMLSchema#string" | AF54: =IF(A54="Implicit","",R54&","&S54&","&T54&","&U54&","&V54&","&W54&","&X54&","&Y54&","&Z54&","&AA54&","&AB54&","&AC54&","&AD54&","&AE54) -> "Embedded","Adjustments","reasonsForAdjustments","","string",3,"Adjustments in the context of CASS records","A free text for user to include a reason for correction","false","false","","https://onerecord.iata.org/ns/cargo#Adjustments","https://onerecord.iata.org/ns/cargo#reasonsForAdjustments","http://www.w3.org/2001/XMLSchema#string" | AG54: =IF(Q54="Data","",$F$1&B54&"."&L54&$F$1) -> "Embedded.Adjustments" | AH54: =IF(Q54="Data","",$F$1&M54&$F$1) -> "reasonsForAdjustments" | AI54: =IF(Q54="Data","",$F$1&E54&"."&N54&$F$1) -> ".string" | AJ54: =IF(Q54="Data","",$F$1&O54&$F$1) -> "" | AK54: =IF(Q54="Data","",$F$1&IF(G54=1,"hasOne","hasMany")&$F$1) -> "hasOne" | AL54: =IF(Q54="Data","",AG54&","&AH54&","&AI54&","&AJ54&","&AK54) -> "Embedded.Adjustments","reasonsForAdjustments",".string","","hasOne" | AN54: =COUNTIF(View_conceptual!G:G,L54) -> 0 | AO54: =COUNTIF(View_conceptual!H:H,L54)+COUNTIF(View_conceptual!I:I,N54) -> 0 | AQ54: =IF(AN54=1,AF54,"") | AR54: =IF(AO54=2,AL54,"") | AT54: =COUNTIF(View_full!G:G,L54) -> 1 | AU54: =COUNTIF(View_full!H:H,L54)+COUNTIF(View_full!I:I,N54) -> 0 | AV54: =COUNTIFS(Property_Manual!$A$2:$A$1206,Raw!L54,Property_Manual!$B$2:$B$1206,Raw!M54,Property_Manual!$C$2:$C$1206,Raw!N54,Property_Manual!$D$2:$D$1206,Raw!O54,Property_Manual!$F$2:$F$1206,"x") -> 0 | AW54: =IF(AT54=1,AF54,"") -> "Embedded","Adjustments","reasonsForAdjustments","","string",3,"Adjustments in the context of CASS records","A free text for user to include a reason for correction","false","false","","https://onerecord.iata.org/ns/cargo#Adjustments","https://onerecord.iata.org/ns/cargo#reasonsForAdjustments","http://www.w3.org/2001/XMLSchema#string" | AX54: =IF(AU54=2,AL54,"") | AY54: =IF(AV54=1,AL54,"")
A55: Explicit | B55: Common | C55: https://onerecord.iata.org/ns/cargo#Answer | D55: https://onerecord.iata.org/ns/cargo#question | E55: Common | F55: https://onerecord.iata.org/ns/cargo#Question | G55: 1 | H55: https://onerecord.iata.org/ns/cargo#answer | I55: Answer holds the answer to one Question | J55: Reference to the Question the Answer is for | L55: =SUBSTITUTE(SUBSTITUTE(SUBSTITUTE(C55,$B$2,$A$2),$B$3,$A$3),$B$4,$A$4) -> Answer | M55: =SUBSTITUTE(SUBSTITUTE(SUBSTITUTE(D55,$B$2,$A$2),$B$3,$A$3),$A$4,$B$4) -> question | N55: =SUBSTITUTE(SUBSTITUTE(SUBSTITUTE(F55,$B$2,$A$2),$B$3,$A$3),$B$4,$A$4) -> Question | O55: =SUBSTITUTE(SUBSTITUTE(SUBSTITUTE(H55,$B$2,$A$2),$B$3,$A$3),$B$4,$A$4) -> answer | P55: =SUBSTITUTE(SUBSTITUTE(SUBSTITUTE(K55,$B$2,$A$2),$B$3,$A$3),$B$4,$A$4) | Q55: =IF(LEFT(N55,3)="xsd","Data","Object") -> Object | R55: =IF($A55="Implicit","",$F$1&B55&$F$1) -> "Common" | S55: =IF($A55="Implicit","",$F$1&L55&$F$1) -> "Answer" | T55: =IF($A55="Implicit","",$F$1&M55&$F$1) -> "question" | U55: =IF($A55="Implicit","",$F$1&E55&$F$1) -> "Common" | V55: =IF($A55="Implicit","",$F$1&N55&$F$1) -> "Question" | W55: =IF($A55="Implicit","",COUNTIFS($C$8:C55,C55,$A$8:A55,"Explicit")) -> 1 | X55: =IF($A55="Implicit","",$F$1&SUBSTITUTE(IF(I55=0,"",I55),",",";")&$F$1) -> "Answer holds the answer to one Question" | Y55: =IF($A55="Implicit","",$F$1&SUBSTITUTE(IF(J55=0,"",J55),",",";")&$F$1) -> "Reference to the Question the Answer is for" | Z55: =IF($A55="Implicit","",$F$1&IF(G55=1,"false","true")&$F$1) -> "false" | AA55: =IF($A55="Implicit","",$F$1&IF(OR(E55="Enum",E55="CodeList"),"true","false")&$F$1) -> "false" | AB55: =IF($A55="Implicit","",$F$1&P55&$F$1) -> "" | AC55: =IF($A55="Implicit","",$F$1&C55&$F$1) -> "https://onerecord.iata.org/ns/cargo#Answer" | AD55: =IF($A55="Implicit","",$F$1&D55&$F$1) -> "https://onerecord.iata.org/ns/cargo#question" | AE55: =IF($A55="Implicit","",$F$1&F55&$F$1) -> "https://onerecord.iata.org/ns/cargo#Question" | AF55: =IF(A55="Implicit","",R55&","&S55&","&T55&","&U55&","&V55&","&W55&","&X55&","&Y55&","&Z55&","&AA55&","&AB55&","&AC55&","&AD55&","&AE55) -> "Common","Answer","question","Common","Question",1,"Answer holds the answer to one Question","Reference to the Question the Answer is for","false","false","","https://onerecord.iata.org/ns/cargo#Answer","https://onerecord.iata.org/ns/cargo#question","https://onerecord.iata.org/ns/cargo#Question" | AG55: =IF(Q55="Data","",$F$1&B55&"."&L55&$F$1) -> "Common.Answer" | AH55: =IF(Q55="Data","",$F$1&M55&$F$1) -> "question" | AI55: =IF(Q55="Data","",$F$1&E55&"."&N55&$F$1) -> "Common.Question" | AJ55: =IF(Q55="Data","",$F$1&O55&$F$1) -> "answer" | AK55: =IF(Q55="Data","",$F$1&IF(G55=1,"hasOne","hasMany")&$F$1) -> "hasOne" | AL55: =IF(Q55="Data","",AG55&","&AH55&","&AI55&","&AJ55&","&AK55) -> "Common.Answer","question","Common.Question","answer","hasOne" | AN55: =COUNTIF(View_conceptual!G:G,L55) -> 0 | AO55: =COUNTIF(View_conceptual!H:H,L55)+COUNTIF(View_conceptual!I:I,N55) -> 0 | AQ55: =IF(AN55=1,AF55,"") | AR55: =IF(AO55=2,AL55,"") | AT55: =COUNTIF(View_full!G:G,L55) -> 1 | AU55: =COUNTIF(View_full!H:H,L55)+COUNTIF(View_full!I:I,N55) -> 2 | AV55: =COUNTIFS(Property_Manual!$A$2:$A$1206,Raw!L55,Property_Manual!$B$2:$B$1206,Raw!M55,Property_Manual!$C$2:$C$1206,Raw!N55,Property_Manual!$D$2:$D$1206,Raw!O55,Property_Manual!$F$2:$F$1206,"x") -> 1 | AW55: =IF(AT55=1,AF55,"") -> "Common","Answer","question","Common","Question",1,"Answer holds the answer to one Question","Reference to the Question the Answer is for","false","false","","https://onerecord.iata.org/ns/cargo#Answer","https://onerecord.iata.org/ns/cargo#question","https://onerecord.iata.org/ns/cargo#Question" | AX55: =IF(AU55=2,AL55,"") -> "Common.Answer","question","Common.Question","answer","hasOne" | AY55: =IF(AV55=1,AL55,"") -> "Common.Answer","question","Common.Question","answer","hasOne"
A56: Implicit | B56: Common | C56: https://onerecord.iata.org/ns/cargo#Answer | D56: https://onerecord.iata.org/ns/cargo#question | E56: Common | F56: https://onerecord.iata.org/ns/cargo#Question | G56: 1 | H56: https://onerecord.iata.org/ns/cargo#answer | I56: Answer holds the answer to one Question | J56: Reference to the Question the Answer is for | L56: =SUBSTITUTE(SUBSTITUTE(SUBSTITUTE(C56,$B$2,$A$2),$B$3,$A$3),$B$4,$A$4) -> Answer | M56: =SUBSTITUTE(SUBSTITUTE(SUBSTITUTE(D56,$B$2,$A$2),$B$3,$A$3),$A$4,$B$4) -> question | N56: =SUBSTITUTE(SUBSTITUTE(SUBSTITUTE(F56,$B$2,$A$2),$B$3,$A$3),$B$4,$A$4) -> Question | O56: =SUBSTITUTE(SUBSTITUTE(SUBSTITUTE(H56,$B$2,$A$2),$B$3,$A$3),$B$4,$A$4) -> answer | P56: =SUBSTITUTE(SUBSTITUTE(SUBSTITUTE(K56,$B$2,$A$2),$B$3,$A$3),$B$4,$A$4) | Q56: =IF(LEFT(N56,3)="xsd","Data","Object") -> Object | R56: =IF($A56="Implicit","",$F$1&B56&$F$1) | S56: =IF($A56="Implicit","",$F$1&L56&$F$1) | T56: =IF($A56="Implicit","",$F$1&M56&$F$1) | U56: =IF($A56="Implicit","",$F$1&E56&$F$1) | V56: =IF($A56="Implicit","",$F$1&N56&$F$1) | W56: =IF($A56="Implicit","",COUNTIFS($C$8:C56,C56,$A$8:A56,"Explicit")) | X56: =IF($A56="Implicit","",$F$1&SUBSTITUTE(IF(I56=0,"",I56),",",";")&$F$1) | Y56: =IF($A56="Implicit","",$F$1&SUBSTITUTE(IF(J56=0,"",J56),",",";")&$F$1) | Z56: =IF($A56="Implicit","",$F$1&IF(G56=1,"false","true")&$F$1) | AA56: =IF($A56="Implicit","",$F$1&IF(OR(E56="Enum",E56="CodeList"),"true","false")&$F$1) | AB56: =IF($A56="Implicit","",$F$1&P56&$F$1) | AC56: =IF($A56="Implicit","",$F$1&C56&$F$1) | AD56: =IF($A56="Implicit","",$F$1&D56&$F$1) | AE56: =IF($A56="Implicit","",$F$1&F56&$F$1) | AF56: =IF(A56="Implicit","",R56&","&S56&","&T56&","&U56&","&V56&","&W56&","&X56&","&Y56&","&Z56&","&AA56&","&AB56&","&AC56&","&AD56&","&AE56) | AG56: =IF(Q56="Data","",$F$1&B56&"."&L56&$F$1) -> "Common.Answer" | AH56: =IF(Q56="Data","",$F$1&M56&$F$1) -> "question" | AI56: =IF(Q56="Data","",$F$1&E56&"."&N56&$F$1) -> "Common.Question" | AJ56: =IF(Q56="Data","",$F$1&O56&$F$1) -> "answer" | AK56: =IF(Q56="Data","",$F$1&IF(G56=1,"hasOne","hasMany")&$F$1) -> "hasOne" | AL56: =IF(Q56="Data","",AG56&","&AH56&","&AI56&","&AJ56&","&AK56) -> "Common.Answer","question","Common.Question","answer","hasOne" | AN56: =COUNTIF(View_conceptual!G:G,L56) -> 0 | AO56: =COUNTIF(View_conceptual!H:H,L56)+COUNTIF(View_conceptual!I:I,N56) -> 0 | AQ56: =IF(AN56=1,AF56,"") | AR56: =IF(AO56=2,AL56,"") | AT56: =COUNTIF(View_full!G:G,L56) -> 1 | AU56: =COUNTIF(View_full!H:H,L56)+COUNTIF(View_full!I:I,N56) -> 2 | AV56: =COUNTIFS(Property_Manual!$A$2:$A$1206,Raw!L56,Property_Manual!$B$2:$B$1206,Raw!M56,Property_Manual!$C$2:$C$1206,Raw!N56,Property_Manual!$D$2:$D$1206,Raw!O56,Property_Manual!$F$2:$F$1206,"x") -> 1 | AW56: =IF(AT56=1,AF56,"") | AX56: =IF(AU56=2,AL56,"") -> "Common.Answer","question","Common.Question","answer","hasOne" | AY56: =IF(AV56=1,AL56,"") -> "Common.Answer","question","Common.Question","answer","hasOne"
A57: Explicit | B57: Common | C57: https://onerecord.iata.org/ns/cargo#Answer | D57: https://onerecord.iata.org/ns/cargo#answerActor | E57: Agent | F57: https://onerecord.iata.org/ns/cargo#Actor | G57: 1 | I57: Answer holds the answer to one Question | J57: Reference to the Actor giving the Answer | K57: https://onerecord.iata.org/ns/cargo#Person|https://onerecord.iata.org/ns/cargo#NonHumanActor | L57: =SUBSTITUTE(SUBSTITUTE(SUBSTITUTE(C57,$B$2,$A$2),$B$3,$A$3),$B$4,$A$4) -> Answer | M57: =SUBSTITUTE(SUBSTITUTE(SUBSTITUTE(D57,$B$2,$A$2),$B$3,$A$3),$A$4,$B$4) -> answerActor | N57: =SUBSTITUTE(SUBSTITUTE(SUBSTITUTE(F57,$B$2,$A$2),$B$3,$A$3),$B$4,$A$4) -> Actor | O57: =SUBSTITUTE(SUBSTITUTE(SUBSTITUTE(H57,$B$2,$A$2),$B$3,$A$3),$B$4,$A$4) | P57: =SUBSTITUTE(SUBSTITUTE(SUBSTITUTE(K57,$B$2,$A$2),$B$3,$A$3),$B$4,$A$4) -> Person|NonHumanActor | Q57: =IF(LEFT(N57,3)="xsd","Data","Object") -> Object | R57: =IF($A57="Implicit","",$F$1&B57&$F$1) -> "Common" | S57: =IF($A57="Implicit","",$F$1&L57&$F$1) -> "Answer" | T57: =IF($A57="Implicit","",$F$1&M57&$F$1) -> "answerActor" | U57: =IF($A57="Implicit","",$F$1&E57&$F$1) -> "Agent" | V57: =IF($A57="Implicit","",$F$1&N57&$F$1) -> "Actor" | W57: =IF($A57="Implicit","",COUNTIFS($C$8:C57,C57,$A$8:A57,"Explicit")) -> 2 | X57: =IF($A57="Implicit","",$F$1&SUBSTITUTE(IF(I57=0,"",I57),",",";")&$F$1) -> "Answer holds the answer to one Question" | Y57: =IF($A57="Implicit","",$F$1&SUBSTITUTE(IF(J57=0,"",J57),",",";")&$F$1) -> "Reference to the Actor giving the Answer" | Z57: =IF($A57="Implicit","",$F$1&IF(G57=1,"false","true")&$F$1) -> "false" | AA57: =IF($A57="Implicit","",$F$1&IF(OR(E57="Enum",E57="CodeList"),"true","false")&$F$1) -> "false" | AB57: =IF($A57="Implicit","",$F$1&P57&$F$1) -> "Person|NonHumanActor" | AC57: =IF($A57="Implicit","",$F$1&C57&$F$1) -> "https://onerecord.iata.org/ns/cargo#Answer" | AD57: =IF($A57="Implicit","",$F$1&D57&$F$1) -> "https://onerecord.iata.org/ns/cargo#answerActor" | AE57: =IF($A57="Implicit","",$F$1&F57&$F$1) -> "https://onerecord.iata.org/ns/cargo#Actor" | AF57: =IF(A57="Implicit","",R57&","&S57&","&T57&","&U57&","&V57&","&W57&","&X57&","&Y57&","&Z57&","&AA57&","&AB57&","&AC57&","&AD57&","&AE57) -> "Common","Answer","answerActor","Agent","Actor",2,"Answer holds the answer to one Question","Reference to the Actor giving the Answer","false","false","Person|NonHumanActor","https://onerecord.iata.org/ns/cargo#Answer","https://onerecord.iata.org/ns/cargo#answerActor","https://onerecord.iata.org/ns/cargo#Actor" | AG57: =IF(Q57="Data","",$F$1&B57&"."&L57&$F$1) -> "Common.Answer" | AH57: =IF(Q57="Data","",$F$1&M57&$F$1) -> "answerActor" | AI57: =IF(Q57="Data","",$F$1&E57&"."&N57&$F$1) -> "Agent.Actor" | AJ57: =IF(Q57="Data","",$F$1&O57&$F$1) -> "" | AK57: =IF(Q57="Data","",$F$1&IF(G57=1,"hasOne","hasMany")&$F$1) -> "hasOne" | AL57: =IF(Q57="Data","",AG57&","&AH57&","&AI57&","&AJ57&","&AK57) -> "Common.Answer","answerActor","Agent.Actor","","hasOne" | AN57: =COUNTIF(View_conceptual!G:G,L57) -> 0 | AO57: =COUNTIF(View_conceptual!H:H,L57)+COUNTIF(View_conceptual!I:I,N57) -> 0 | AQ57: =IF(AN57=1,AF57,"") | AR57: =IF(AO57=2,AL57,"") | AT57: =COUNTIF(View_full!G:G,L57) -> 1 | AU57: =COUNTIF(View_full!H:H,L57)+COUNTIF(View_full!I:I,N57) -> 1 | AV57: =COUNTIFS(Property_Manual!$A$2:$A$1206,Raw!L57,Property_Manual!$B$2:$B$1206,Raw!M57,Property_Manual!$C$2:$C$1206,Raw!N57,Property_Manual!$D$2:$D$1206,Raw!O57,Property_Manual!$F$2:$F$1206,"x") -> 0 | AW57: =IF(AT57=1,AF57,"") -> "Common","Answer","answerActor","Agent","Actor",2,"Answer holds the answer to one Question","Reference to the Actor giving the Answer","false","false","Person|NonHumanActor","https://onerecord.iata.org/ns/cargo#Answer","https://onerecord.iata.org/ns/cargo#answerActor","https://onerecord.iata.org/ns/cargo#Actor" | AX57: =IF(AU57=2,AL57,"") | AY57: =IF(AV57=1,AL57,"")
A58: Explicit | B58: Common | C58: https://onerecord.iata.org/ns/cargo#Answer | D58: https://onerecord.iata.org/ns/cargo#answerValue | E58: Embedded | F58: https://onerecord.iata.org/ns/cargo#Value | G58: 1 | I58: Answer holds the answer to one Question | J58: Information about an answer Value of any kind of the Answer | L58: =SUBSTITUTE(SUBSTITUTE(SUBSTITUTE(C58,$B$2,$A$2),$B$3,$A$3),$B$4,$A$4) -> Answer | M58: =SUBSTITUTE(SUBSTITUTE(SUBSTITUTE(D58,$B$2,$A$2),$B$3,$A$3),$A$4,$B$4) -> answerValue | N58: =SUBSTITUTE(SUBSTITUTE(SUBSTITUTE(F58,$B$2,$A$2),$B$3,$A$3),$B$4,$A$4) -> Value | O58: =SUBSTITUTE(SUBSTITUTE(SUBSTITUTE(H58,$B$2,$A$2),$B$3,$A$3),$B$4,$A$4) | P58: =SUBSTITUTE(SUBSTITUTE(SUBSTITUTE(K58,$B$2,$A$2),$B$3,$A$3),$B$4,$A$4) | Q58: =IF(LEFT(N58,3)="xsd","Data","Object") -> Object | R58: =IF($A58="Implicit","",$F$1&B58&$F$1) -> "Common" | S58: =IF($A58="Implicit","",$F$1&L58&$F$1) -> "Answer" | T58: =IF($A58="Implicit","",$F$1&M58&$F$1) -> "answerValue" | U58: =IF($A58="Implicit","",$F$1&E58&$F$1) -> "Embedded" | V58: =IF($A58="Implicit","",$F$1&N58&$F$1) -> "Value" | W58: =IF($A58="Implicit","",COUNTIFS($C$8:C58,C58,$A$8:A58,"Explicit")) -> 3 | X58: =IF($A58="Implicit","",$F$1&SUBSTITUTE(IF(I58=0,"",I58),",",";")&$F$1) -> "Answer holds the answer to one Question" | Y58: =IF($A58="Implicit","",$F$1&SUBSTITUTE(IF(J58=0,"",J58),",",";")&$F$1) -> "Information about an answer Value of any kind of the Answer" | Z58: =IF($A58="Implicit","",$F$1&IF(G58=1,"false","true")&$F$1) -> "false" | AA58: =IF($A58="Implicit","",$F$1&IF(OR(E58="Enum",E58="CodeList"),"true","false")&$F$1) -> "false" | AB58: =IF($A58="Implicit","",$F$1&P58&$F$1) -> "" | AC58: =IF($A58="Implicit","",$F$1&C58&$F$1) -> "https://onerecord.iata.org/ns/cargo#Answer" | AD58: =IF($A58="Implicit","",$F$1&D58&$F$1) -> "https://onerecord.iata.org/ns/cargo#answerValue" | AE58: =IF($A58="Implicit","",$F$1&F58&$F$1) -> "https://onerecord.iata.org/ns/cargo#Value" | AF58: =IF(A58="Implicit","",R58&","&S58&","&T58&","&U58&","&V58&","&W58&","&X58&","&Y58&","&Z58&","&AA58&","&AB58&","&AC58&","&AD58&","&AE58) -> "Common","Answer","answerValue","Embedded","Value",3,"Answer holds the answer to one Question","Information about an answer Value of any kind of the Answer","false","false","","https://onerecord.iata.org/ns/cargo#Answer","https://onerecord.iata.org/ns/cargo#answerValue","https://onerecord.iata.org/ns/cargo#Value" | AG58: =IF(Q58="Data","",$F$1&B58&"."&L58&$F$1) -> "Common.Answer" | AH58: =IF(Q58="Data","",$F$1&M58&$F$1) -> "answerValue" | AI58: =IF(Q58="Data","",$F$1&E58&"."&N58&$F$1) -> "Embedded.Value" | AJ58: =IF(Q58="Data","",$F$1&O58&$F$1) -> "" | AK58: =IF(Q58="Data","",$F$1&IF(G58=1,"hasOne","hasMany")&$F$1) -> "hasOne" | AL58: =IF(Q58="Data","",AG58&","&AH58&","&AI58&","&AJ58&","&AK58) -> "Common.Answer","answerValue","Embedded.Value","","hasOne" | AN58: =COUNTIF(View_conceptual!G:G,L58) -> 0 | AO58: =COUNTIF(View_conceptual!H:H,L58)+COUNTIF(View_conceptual!I:I,N58) -> 0 | AQ58: =IF(AN58=1,AF58,"") | AR58: =IF(AO58=2,AL58,"") | AT58: =COUNTIF(View_full!G:G,L58) -> 1 | AU58: =COUNTIF(View_full!H:H,L58)+COUNTIF(View_full!I:I,N58) -> 1 | AV58: =COUNTIFS(Property_Manual!$A$2:$A$1206,Raw!L58,Property_Manual!$B$2:$B$1206,Raw!M58,Property_Manual!$C$2:$C$1206,Raw!N58,Property_Manual!$D$2:$D$1206,Raw!O58,Property_Manual!$F$2:$F$1206,"x") -> 0 | AW58: =IF(AT58=1,AF58,"") -> "Common","Answer","answerValue","Embedded","Value",3,"Answer holds the answer to one Question","Information about an answer Value of any kind of the Answer","false","false","","https://onerecord.iata.org/ns/cargo#Answer","https://onerecord.iata.org/ns/cargo#answerValue","https://onerecord.iata.org/ns/cargo#Value" | AX58: =IF(AU58=2,AL58,"") | AY58: =IF(AV58=1,AL58,"")
A59: Explicit | B59: Common | C59: https://onerecord.iata.org/ns/cargo#Answer | D59: https://onerecord.iata.org/ns/cargo#givenAtLocation | E59: Common | F59: https://onerecord.iata.org/ns/cargo#Location | G59: 1 | I59: Answer holds the answer to one Question | J59: Reference to the Location from which the Question was answered, relevant for split checks with documentary and physical elements | L59: =SUBSTITUTE(SUBSTITUTE(SUBSTITUTE(C59,$B$2,$A$2),$B$3,$A$3),$B$4,$A$4) -> Answer | M59: =SUBSTITUTE(SUBSTITUTE(SUBSTITUTE(D59,$B$2,$A$2),$B$3,$A$3),$A$4,$B$4) -> givenAtLocation | N59: =SUBSTITUTE(SUBSTITUTE(SUBSTITUTE(F59,$B$2,$A$2),$B$3,$A$3),$B$4,$A$4) -> Location | O59: =SUBSTITUTE(SUBSTITUTE(SUBSTITUTE(H59,$B$2,$A$2),$B$3,$A$3),$B$4,$A$4) | P59: =SUBSTITUTE(SUBSTITUTE(SUBSTITUTE(K59,$B$2,$A$2),$B$3,$A$3),$B$4,$A$4) | Q59: =IF(LEFT(N59,3)="xsd","Data","Object") -> Object | R59: =IF($A59="Implicit","",$F$1&B59&$F$1) -> "Common" | S59: =IF($A59="Implicit","",$F$1&L59&$F$1) -> "Answer" | T59: =IF($A59="Implicit","",$F$1&M59&$F$1) -> "givenAtLocation" | U59: =IF($A59="Implicit","",$F$1&E59&$F$1) -> "Common" | V59: =IF($A59="Implicit","",$F$1&N59&$F$1) -> "Location" | W59: =IF($A59="Implicit","",COUNTIFS($C$8:C59,C59,$A$8:A59,"Explicit")) -> 4 | X59: =IF($A59="Implicit","",$F$1&SUBSTITUTE(IF(I59=0,"",I59),",",";")&$F$1) -> "Answer holds the answer to one Question" | Y59: =IF($A59="Implicit","",$F$1&SUBSTITUTE(IF(J59=0,"",J59),",",";")&$F$1) -> "Reference to the Location from which the Question was answered; relevant for split checks with documentary and physical elements" | Z59: =IF($A59="Implicit","",$F$1&IF(G59=1,"false","true")&$F$1) -> "false" | AA59: =IF($A59="Implicit","",$F$1&IF(OR(E59="Enum",E59="CodeList"),"true","false")&$F$1) -> "false" | AB59: =IF($A59="Implicit","",$F$1&P59&$F$1) -> "" | AC59: =IF($A59="Implicit","",$F$1&C59&$F$1) -> "https://onerecord.iata.org/ns/cargo#Answer" | AD59: =IF($A59="Implicit","",$F$1&D59&$F$1) -> "https://onerecord.iata.org/ns/cargo#givenAtLocation" | AE59: =IF($A59="Implicit","",$F$1&F59&$F$1) -> "https://onerecord.iata.org/ns/cargo#Location" | AF59: =IF(A59="Implicit","",R59&","&S59&","&T59&","&U59&","&V59&","&W59&","&X59&","&Y59&","&Z59&","&AA59&","&AB59&","&AC59&","&AD59&","&AE59) -> "Common","Answer","givenAtLocation","Common","Location",4,"Answer holds the answer to one Question","Reference to the Location from which the Question was answered; relevant for split checks with documentary and physical elements","false","false","","https://onerecord.iata.org/ns/cargo#Answer","https://onerecord.iata.org/ns/cargo#givenAtLocation","https://onerecord.iata.org/ns/cargo#Location" | AG59: =IF(Q59="Data","",$F$1&B59&"."&L59&$F$1) -> "Common.Answer" | AH59: =IF(Q59="Data","",$F$1&M59&$F$1) -> "givenAtLocation" | AI59: =IF(Q59="Data","",$F$1&E59&"."&N59&$F$1) -> "Common.Location" | AJ59: =IF(Q59="Data","",$F$1&O59&$F$1) -> "" | AK59: =IF(Q59="Data","",$F$1&IF(G59=1,"hasOne","hasMany")&$F$1) -> "hasOne" | AL59: =IF(Q59="Data","",AG59&","&AH59&","&AI59&","&AJ59&","&AK59) -> "Common.Answer","givenAtLocation","Common.Location","","hasOne" | AN59: =COUNTIF(View_conceptual!G:G,L59) -> 0 | AO59: =COUNTIF(View_conceptual!H:H,L59)+COUNTIF(View_conceptual!I:I,N59) -> 0 | AQ59: =IF(AN59=1,AF59,"") | AR59: =IF(AO59=2,AL59,"") | AT59: =COUNTIF(View_full!G:G,L59) -> 1 | AU59: =COUNTIF(View_full!H:H,L59)+COUNTIF(View_full!I:I,N59) -> 1 | AV59: =COUNTIFS(Property_Manual!$A$2:$A$1206,Raw!L59,Property_Manual!$B$2:$B$1206,Raw!M59,Property_Manual!$C$2:$C$1206,Raw!N59,Property_Manual!$D$2:$D$1206,Raw!O59,Property_Manual!$F$2:$F$1206,"x") -> 0 | AW59: =IF(AT59=1,AF59,"") -> "Common","Answer","givenAtLocation","Common","Location",4,"Answer holds the answer to one Question","Reference to the Location from which the Question was answered; relevant for split checks with documentary and physical elements","false","false","","https://onerecord.iata.org/ns/cargo#Answer","https://onerecord.iata.org/ns/cargo#givenAtLocation","https://onerecord.iata.org/ns/cargo#Location" | AX59: =IF(AU59=2,AL59,"") | AY59: =IF(AV59=1,AL59,"")
A60: Explicit | B60: Common | C60: https://onerecord.iata.org/ns/cargo#Answer | D60: https://onerecord.iata.org/ns/cargo#checks | E60: Action | F60: https://onerecord.iata.org/ns/cargo#Check | H60: https://onerecord.iata.org/ns/cargo#checkedObject | I60: Answer holds the answer to one Question | J60: References to the CheckActions performed on the object | L60: =SUBSTITUTE(SUBSTITUTE(SUBSTITUTE(C60,$B$2,$A$2),$B$3,$A$3),$B$4,$A$4) -> Answer | M60: =SUBSTITUTE(SUBSTITUTE(SUBSTITUTE(D60,$B$2,$A$2),$B$3,$A$3),$A$4,$B$4) -> checks | N60: =SUBSTITUTE(SUBSTITUTE(SUBSTITUTE(F60,$B$2,$A$2),$B$3,$A$3),$B$4,$A$4) -> Check | O60: =SUBSTITUTE(SUBSTITUTE(SUBSTITUTE(H60,$B$2,$A$2),$B$3,$A$3),$B$4,$A$4) -> checkedObject | P60: =SUBSTITUTE(SUBSTITUTE(SUBSTITUTE(K60,$B$2,$A$2),$B$3,$A$3),$B$4,$A$4) | Q60: =IF(LEFT(N60,3)="xsd","Data","Object") -> Object | R60: =IF($A60="Implicit","",$F$1&B60&$F$1) -> "Common" | S60: =IF($A60="Implicit","",$F$1&L60&$F$1) -> "Answer" | T60: =IF($A60="Implicit","",$F$1&M60&$F$1) -> "checks" | U60: =IF($A60="Implicit","",$F$1&E60&$F$1) -> "Action" | V60: =IF($A60="Implicit","",$F$1&N60&$F$1) -> "Check" | W60: =IF($A60="Implicit","",COUNTIFS($C$8:C60,C60,$A$8:A60,"Explicit")) -> 5 | X60: =IF($A60="Implicit","",$F$1&SUBSTITUTE(IF(I60=0,"",I60),",",";")&$F$1) -> "Answer holds the answer to one Question" | Y60: =IF($A60="Implicit","",$F$1&SUBSTITUTE(IF(J60=0,"",J60),",",";")&$F$1) -> "References to the CheckActions performed on the object" | Z60: =IF($A60="Implicit","",$F$1&IF(G60=1,"false","true")&$F$1) -> "true" | AA60: =IF($A60="Implicit","",$F$1&IF(OR(E60="Enum",E60="CodeList"),"true","false")&$F$1) -> "false" | AB60: =IF($A60="Implicit","",$F$1&P60&$F$1) -> "" | AC60: =IF($A60="Implicit","",$F$1&C60&$F$1) -> "https://onerecord.iata.org/ns/cargo#Answer" | AD60: =IF($A60="Implicit","",$F$1&D60&$F$1) -> "https://onerecord.iata.org/ns/cargo#checks" | AE60: =IF($A60="Implicit","",$F$1&F60&$F$1) -> "https://onerecord.iata.org/ns/cargo#Check" | AF60: =IF(A60="Implicit","",R60&","&S60&","&T60&","&U60&","&V60&","&W60&","&X60&","&Y60&","&Z60&","&AA60&","&AB60&","&AC60&","&AD60&","&AE60) -> "Common","Answer","checks","Action","Check",5,"Answer holds the answer to one Question","References to the CheckActions performed on the object","true","false","","https://onerecord.iata.org/ns/cargo#Answer","https://onerecord.iata.org/ns/cargo#checks","https://onerecord.iata.org/ns/cargo#Check" | AG60: =IF(Q60="Data","",$F$1&B60&"."&L60&$F$1) -> "Common.Answer" | AH60: =IF(Q60="Data","",$F$1&M60&$F$1) -> "checks" | AI60: =IF(Q60="Data","",$F$1&E60&"."&N60&$F$1) -> "Action.Check" | AJ60: =IF(Q60="Data","",$F$1&O60&$F$1) -> "checkedObject" | AK60: =IF(Q60="Data","",$F$1&IF(G60=1,"hasOne","hasMany")&$F$1) -> "hasMany" | AL60: =IF(Q60="Data","",AG60&","&AH60&","&AI60&","&AJ60&","&AK60) -> "Common.Answer","checks","Action.Check","checkedObject","hasMany" | AN60: =COUNTIF(View_conceptual!G:G,L60) -> 0 | AO60: =COUNTIF(View_conceptual!H:H,L60)+COUNTIF(View_conceptual!I:I,N60) -> 0 | AQ60: =IF(AN60=1,AF60,"") | AR60: =IF(AO60=2,AL60,"") | AT60: =COUNTIF(View_full!G:G,L60) -> 1 | AU60: =COUNTIF(View_full!H:H,L60)+COUNTIF(View_full!I:I,N60) -> 1 | AV60: =COUNTIFS(Property_Manual!$A$2:$A$1206,Raw!L60,Property_Manual!$B$2:$B$1206,Raw!M60,Property_Manual!$C$2:$C$1206,Raw!N60,Property_Manual!$D$2:$D$1206,Raw!O60,Property_Manual!$F$2:$F$1206,"x") -> 0 | AW60: =IF(AT60=1,AF60,"") -> "Common","Answer","checks","Action","Check",5,"Answer holds the answer to one Question","References to the CheckActions performed on the object","true","false","","https://onerecord.iata.org/ns/cargo#Answer","https://onerecord.iata.org/ns/cargo#checks","https://onerecord.iata.org/ns/cargo#Check" | AX60: =IF(AU60=2,AL60,"") | AY60: =IF(AV60=1,AL60,"")
A61: Explicit | B61: Common | C61: https://onerecord.iata.org/ns/cargo#Answer | D61: https://onerecord.iata.org/ns/cargo#externalReferences | E61: Common | F61: https://onerecord.iata.org/ns/cargo#ExternalReference | H61: https://onerecord.iata.org/ns/cargo#referenceForObjects | I61: Answer holds the answer to one Question | J61: References to all associated ExternalReferences | L61: =SUBSTITUTE(SUBSTITUTE(SUBSTITUTE(C61,$B$2,$A$2),$B$3,$A$3),$B$4,$A$4) -> Answer | M61: =SUBSTITUTE(SUBSTITUTE(SUBSTITUTE(D61,$B$2,$A$2),$B$3,$A$3),$A$4,$B$4) -> externalReferences | N61: =SUBSTITUTE(SUBSTITUTE(SUBSTITUTE(F61,$B$2,$A$2),$B$3,$A$3),$B$4,$A$4) -> ExternalReference | O61: =SUBSTITUTE(SUBSTITUTE(SUBSTITUTE(H61,$B$2,$A$2),$B$3,$A$3),$B$4,$A$4) -> referenceForObjects | P61: =SUBSTITUTE(SUBSTITUTE(SUBSTITUTE(K61,$B$2,$A$2),$B$3,$A$3),$B$4,$A$4) | Q61: =IF(LEFT(N61,3)="xsd","Data","Object") -> Object | R61: =IF($A61="Implicit","",$F$1&B61&$F$1) -> "Common" | S61: =IF($A61="Implicit","",$F$1&L61&$F$1) -> "Answer" | T61: =IF($A61="Implicit","",$F$1&M61&$F$1) -> "externalReferences" | U61: =IF($A61="Implicit","",$F$1&E61&$F$1) -> "Common" | V61: =IF($A61="Implicit","",$F$1&N61&$F$1) -> "ExternalReference" | W61: =IF($A61="Implicit","",COUNTIFS($C$8:C61,C61,$A$8:A61,"Explicit")) -> 6 | X61: =IF($A61="Implicit","",$F$1&SUBSTITUTE(IF(I61=0,"",I61),",",";")&$F$1) -> "Answer holds the answer to one Question" | Y61: =IF($A61="Implicit","",$F$1&SUBSTITUTE(IF(J61=0,"",J61),",",";")&$F$1) -> "References to all associated ExternalReferences" | Z61: =IF($A61="Implicit","",$F$1&IF(G61=1,"false","true")&$F$1) -> "true" | AA61: =IF($A61="Implicit","",$F$1&IF(OR(E61="Enum",E61="CodeList"),"true","false")&$F$1) -> "false" | AB61: =IF($A61="Implicit","",$F$1&P61&$F$1) -> "" | AC61: =IF($A61="Implicit","",$F$1&C61&$F$1) -> "https://onerecord.iata.org/ns/cargo#Answer" | AD61: =IF($A61="Implicit","",$F$1&D61&$F$1) -> "https://onerecord.iata.org/ns/cargo#externalReferences" | AE61: =IF($A61="Implicit","",$F$1&F61&$F$1) -> "https://onerecord.iata.org/ns/cargo#ExternalReference" | AF61: =IF(A61="Implicit","",R61&","&S61&","&T61&","&U61&","&V61&","&W61&","&X61&","&Y61&","&Z61&","&AA61&","&AB61&","&AC61&","&AD61&","&AE61) -> "Common","Answer","externalReferences","Common","ExternalReference",6,"Answer holds the answer to one Question","References to all associated ExternalReferences","true","false","","https://onerecord.iata.org/ns/cargo#Answer","https://onerecord.iata.org/ns/cargo#externalReferences","https://onerecord.iata.org/ns/cargo#ExternalReference" | AG61: =IF(Q61="Data","",$F$1&B61&"."&L61&$F$1) -> "Common.Answer" | AH61: =IF(Q61="Data","",$F$1&M61&$F$1) -> "externalReferences" | AI61: =IF(Q61="Data","",$F$1&E61&"."&N61&$F$1) -> "Common.ExternalReference" | AJ61: =IF(Q61="Data","",$F$1&O61&$F$1) -> "referenceForObjects" | AK61: =IF(Q61="Data","",$F$1&IF(G61=1,"hasOne","hasMany")&$F$1) -> "hasMany" | AL61: =IF(Q61="Data","",AG61&","&AH61&","&AI61&","&AJ61&","&AK61) -> "Common.Answer","externalReferences","Common.ExternalReference","referenceForObjects","hasMany" | AN61: =COUNTIF(View_conceptual!G:G,L61) -> 0 | AO61: =COUNTIF(View_conceptual!H:H,L61)+COUNTIF(View_conceptual!I:I,N61) -> 0 | AQ61: =IF(AN61=1,AF61,"") | AR61: =IF(AO61=2,AL61,"") | AT61: =COUNTIF(View_full!G:G,L61) -> 1 | AU61: =COUNTIF(View_full!H:H,L61)+COUNTIF(View_full!I:I,N61) -> 1 | AV61: =COUNTIFS(Property_Manual!$A$2:$A$1206,Raw!L61,Property_Manual!$B$2:$B$1206,Raw!M61,Property_Manual!$C$2:$C$1206,Raw!N61,Property_Manual!$D$2:$D$1206,Raw!O61,Property_Manual!$F$2:$F$1206,"x") -> 0 | AW61: =IF(AT61=1,AF61,"") -> "Common","Answer","externalReferences","Common","ExternalReference",6,"Answer holds the answer to one Question","References to all associated ExternalReferences","true","false","","https://onerecord.iata.org/ns/cargo#Answer","https://onerecord.iata.org/ns/cargo#externalReferences","https://onerecord.iata.org/ns/cargo#ExternalReference" | AX61: =IF(AU61=2,AL61,"") | AY61: =IF(AV61=1,AL61,"")
A62: Implicit | B62: Common | C62: https://onerecord.iata.org/ns/cargo#Answer | D62: https://onerecord.iata.org/ns/cargo#answerActor | E62: Agent | F62: https://onerecord.iata.org/ns/cargo#Actor | G62: 1 | I62: Answer holds the answer to one Question | J62: Reference to the Actor giving the Answer | K62: https://onerecord.iata.org/ns/cargo#Person|https://onerecord.iata.org/ns/cargo#NonHumanActor | L62: =SUBSTITUTE(SUBSTITUTE(SUBSTITUTE(C62,$B$2,$A$2),$B$3,$A$3),$B$4,$A$4) -> Answer | M62: =SUBSTITUTE(SUBSTITUTE(SUBSTITUTE(D62,$B$2,$A$2),$B$3,$A$3),$A$4,$B$4) -> answerActor | N62: =SUBSTITUTE(SUBSTITUTE(SUBSTITUTE(F62,$B$2,$A$2),$B$3,$A$3),$B$4,$A$4) -> Actor | O62: =SUBSTITUTE(SUBSTITUTE(SUBSTITUTE(H62,$B$2,$A$2),$B$3,$A$3),$B$4,$A$4) | P62: =SUBSTITUTE(SUBSTITUTE(SUBSTITUTE(K62,$B$2,$A$2),$B$3,$A$3),$B$4,$A$4) -> Person|NonHumanActor | Q62: =IF(LEFT(N62,3)="xsd","Data","Object") -> Object | R62: =IF($A62="Implicit","",$F$1&B62&$F$1) | S62: =IF($A62="Implicit","",$F$1&L62&$F$1) | T62: =IF($A62="Implicit","",$F$1&M62&$F$1) | U62: =IF($A62="Implicit","",$F$1&E62&$F$1) | V62: =IF($A62="Implicit","",$F$1&N62&$F$1) | W62: =IF($A62="Implicit","",COUNTIFS($C$8:C62,C62,$A$8:A62,"Explicit")) | X62: =IF($A62="Implicit","",$F$1&SUBSTITUTE(IF(I62=0,"",I62),",",";")&$F$1) | Y62: =IF($A62="Implicit","",$F$1&SUBSTITUTE(IF(J62=0,"",J62),",",";")&$F$1) | Z62: =IF($A62="Implicit","",$F$1&IF(G62=1,"false","true")&$F$1) | AA62: =IF($A62="Implicit","",$F$1&IF(OR(E62="Enum",E62="CodeList"),"true","false")&$F$1) | AB62: =IF($A62="Implicit","",$F$1&P62&$F$1) | AC62: =IF($A62="Implicit","",$F$1&C62&$F$1) | AD62: =IF($A62="Implicit","",$F$1&D62&$F$1) | AE62: =IF($A62="Implicit","",$F$1&F62&$F$1) | AF62: =IF(A62="Implicit","",R62&","&S62&","&T62&","&U62&","&V62&","&W62&","&X62&","&Y62&","&Z62&","&AA62&","&AB62&","&AC62&","&AD62&","&AE62) | AG62: =IF(Q62="Data","",$F$1&B62&"."&L62&$F$1) -> "Common.Answer" | AH62: =IF(Q62="Data","",$F$1&M62&$F$1) -> "answerActor" | AI62: =IF(Q62="Data","",$F$1&E62&"."&N62&$F$1) -> "Agent.Actor" | AJ62: =IF(Q62="Data","",$F$1&O62&$F$1) -> "" | AK62: =IF(Q62="Data","",$F$1&IF(G62=1,"hasOne","hasMany")&$F$1) -> "hasOne" | AL62: =IF(Q62="Data","",AG62&","&AH62&","&AI62&","&AJ62&","&AK62) -> "Common.Answer","answerActor","Agent.Actor","","hasOne" | AN62: =COUNTIF(View_conceptual!G:G,L62) -> 0 | AO62: =COUNTIF(View_conceptual!H:H,L62)+COUNTIF(View_conceptual!I:I,N62) -> 0 | AQ62: =IF(AN62=1,AF62,"") | AR62: =IF(AO62=2,AL62,"") | AT62: =COUNTIF(View_full!G:G,L62) -> 1 | AU62: =COUNTIF(View_full!H:H,L62)+COUNTIF(View_full!I:I,N62) -> 1 | AV62: =COUNTIFS(Property_Manual!$A$2:$A$1206,Raw!L62,Property_Manual!$B$2:$B$1206,Raw!M62,Property_Manual!$C$2:$C$1206,Raw!N62,Property_Manual!$D$2:$D$1206,Raw!O62,Property_Manual!$F$2:$F$1206,"x") -> 0 | AW62: =IF(AT62=1,AF62,"") | AX62: =IF(AU62=2,AL62,"") | AY62: =IF(AV62=1,AL62,"")
A63: Implicit | B63: Common | C63: https://onerecord.iata.org/ns/cargo#Answer | D63: https://onerecord.iata.org/ns/cargo#answerActor | E63: Agent | F63: https://onerecord.iata.org/ns/cargo#Person | G63: 1 | I63: Answer holds the answer to one Question | J63: Reference to the Actor giving the Answer | L63: =SUBSTITUTE(SUBSTITUTE(SUBSTITUTE(C63,$B$2,$A$2),$B$3,$A$3),$B$4,$A$4) -> Answer | M63: =SUBSTITUTE(SUBSTITUTE(SUBSTITUTE(D63,$B$2,$A$2),$B$3,$A$3),$A$4,$B$4) -> answerActor | N63: =SUBSTITUTE(SUBSTITUTE(SUBSTITUTE(F63,$B$2,$A$2),$B$3,$A$3),$B$4,$A$4) -> Person | O63: =SUBSTITUTE(SUBSTITUTE(SUBSTITUTE(H63,$B$2,$A$2),$B$3,$A$3),$B$4,$A$4) | P63: =SUBSTITUTE(SUBSTITUTE(SUBSTITUTE(K63,$B$2,$A$2),$B$3,$A$3),$B$4,$A$4) | Q63: =IF(LEFT(N63,3)="xsd","Data","Object") -> Object | R63: =IF($A63="Implicit","",$F$1&B63&$F$1) | S63: =IF($A63="Implicit","",$F$1&L63&$F$1) | T63: =IF($A63="Implicit","",$F$1&M63&$F$1) | U63: =IF($A63="Implicit","",$F$1&E63&$F$1) | V63: =IF($A63="Implicit","",$F$1&N63&$F$1) | W63: =IF($A63="Implicit","",COUNTIFS($C$8:C63,C63,$A$8:A63,"Explicit")) | X63: =IF($A63="Implicit","",$F$1&SUBSTITUTE(IF(I63=0,"",I63),",",";")&$F$1) | Y63: =IF($A63="Implicit","",$F$1&SUBSTITUTE(IF(J63=0,"",J63),",",";")&$F$1) | Z63: =IF($A63="Implicit","",$F$1&IF(G63=1,"false","true")&$F$1) | AA63: =IF($A63="Implicit","",$F$1&IF(OR(E63="Enum",E63="CodeList"),"true","false")&$F$1) | AB63: =IF($A63="Implicit","",$F$1&P63&$F$1) | AC63: =IF($A63="Implicit","",$F$1&C63&$F$1) | AD63: =IF($A63="Implicit","",$F$1&D63&$F$1) | AE63: =IF($A63="Implicit","",$F$1&F63&$F$1) | AF63: =IF(A63="Implicit","",R63&","&S63&","&T63&","&U63&","&V63&","&W63&","&X63&","&Y63&","&Z63&","&AA63&","&AB63&","&AC63&","&AD63&","&AE63) | AG63: =IF(Q63="Data","",$F$1&B63&"."&L63&$F$1) -> "Common.Answer" | AH63: =IF(Q63="Data","",$F$1&M63&$F$1) -> "answerActor" | AI63: =IF(Q63="Data","",$F$1&E63&"."&N63&$F$1) -> "Agent.Person" | AJ63: =IF(Q63="Data","",$F$1&O63&$F$1) -> "" | AK63: =IF(Q63="Data","",$F$1&IF(G63=1,"hasOne","hasMany")&$F$1) -> "hasOne" | AL63: =IF(Q63="Data","",AG63&","&AH63&","&AI63&","&AJ63&","&AK63) -> "Common.Answer","answerActor","Agent.Person","","hasOne" | AN63: =COUNTIF(View_conceptual!G:G,L63) -> 0 | AO63: =COUNTIF(View_conceptual!H:H,L63)+COUNTIF(View_conceptual!I:I,N63) -> 0 | AQ63: =IF(AN63=1,AF63,"") | AR63: =IF(AO63=2,AL63,"") | AT63: =COUNTIF(View_full!G:G,L63) -> 1 | AU63: =COUNTIF(View_full!H:H,L63)+COUNTIF(View_full!I:I,N63) -> 1 | AV63: =COUNTIFS(Property_Manual!$A$2:$A$1206,Raw!L63,Property_Manual!$B$2:$B$1206,Raw!M63,Property_Manual!$C$2:$C$1206,Raw!N63,Property_Manual!$D$2:$D$1206,Raw!O63,Property_Manual!$F$2:$F$1206,"x") -> 0 | AW63: =IF(AT63=1,AF63,"") | AX63: =IF(AU63=2,AL63,"") | AY63: =IF(AV63=1,AL63,"")
